Workbook

Sheet 店长看板
A1: 店长看板 · Store Manager Daily Dashboard
A2: 先看灯，再看今天的三件事，最后才翻矩阵找原因。所有数值来自「每日经营日报」，所有红黄绿来自「目标与口径」——两张表都改得动。
A3: 最新营业日 | B3: =MAX(每日经营日报!$A$5:$A$18) -> 46252 | D3: 当日结论 | E3: =IF(COUNTIF($D$6:$D$22,"红")>0,"有 "&COUNTIF($D$6:$D$22,"红")&" 项红灯，按下方「今天的三件事」执行",IF(COUNTIF($D$6:$D$22,"黄")>0,"无红灯，"&COUNTIF($D$6:$D$22,"黄")&" 项关注","全绿：把时间用在训练和顾客身上")) -> 有 3 项红灯，按下方「今天的三件事」执行
A5: 指标 | B5: 最新值 | C5: 目标 | D5: 状态 | E5: 绿线 | F5: 黄线 | G5: 超线带宽 | H5: 责任人 | I5: 行动卡
A6: 销售达成率 | B6: =IFERROR(INDEX(每日经营日报!$G$5:$G$18,MATCH($B$3,每日经营日报!$A$5:$A$18,0)),0) -> 0.97868414 | C6: =INDEX(目标与口径!$F$5:$F$36,MATCH("sales_vs_forecast",目标与口径!$A$5:$A$36,0)) -> 1 | D6: =IFERROR(IF(INDEX(目标与口径!$E$5:$E$36,MATCH("sales_vs_forecast",目标与口径!$A$5:$A$36,0))="越高越好",IF($B$6>=INDEX(目标与口径!$G$5:$G$36,MATCH("sales_vs_forecast",目标与口径!$A$5:$A$36,0)),"绿",IF($B$6>=INDEX(目标与口径!$H$5:$H$36,MATCH("sales_vs_forecast",目标与口径!$A$5:$A$36,0)),"黄","红")),IF($B$6<=INDEX(目标与口径!$G$5:$G$36,MATCH("sales_vs_forecast",目标与口径!$A$5:$A$36,0)),"绿",IF($B$6<=INDEX(目标与口径!$H$5:$H$36,MATCH("sales_vs_forecast",目标与口径!$A$5:$A$36,0)),"黄","红"))),"—") -> 黄 | E6: =INDEX(目标与口径!$G$5:$G$36,MATCH("sales_vs_forecast",目标与口径!$A$5:$A$36,0)) -> 0.98 | F6: =INDEX(目标与口径!$H$5:$H$36,MATCH("sales_vs_forecast",目标与口径!$A$5:$A$36,0)) -> 0.93 | G6: =IFERROR(MAX(0,IF(INDEX(目标与口径!$E$5:$E$36,MATCH("sales_vs_forecast",目标与口径!$A$5:$A$36,0))="越高越好",INDEX(目标与口径!$G$5:$G$36,MATCH("sales_vs_forecast",目标与口径!$A$5:$A$36,0))-$B$6,$B$6-INDEX(目标与口径!$G$5:$G$36,MATCH("sales_vs_forecast",目标与口径!$A$5:$A$36,0)))/ABS(INDEX(目标与口径!$H$5:$H$36,MATCH("sales_vs_forecast",目标与口径!$A$5:$A$36,0))-INDEX(目标与口径!$G$5:$G$36,MATCH("sales_vs_forecast",目标与口径!$A$5:$A$36,0)))),0) -> 0.026317265 | H6: =INDEX(目标与口径!$J$5:$J$36,MATCH("sales_vs_forecast",目标与口径!$A$5:$A$36,0)) -> 店长 | I6: =INDEX(目标与口径!$N$5:$N$36,MATCH("sales_vs_forecast",目标与口径!$A$5:$A$36,0)) -> PB-01
A7: 净销售额 | B7: =IFERROR(INDEX(每日经营日报!$D$5:$D$18,MATCH($B$3,每日经营日报!$A$5:$A$18,0)),0) -> 55987.74 | C7: =INDEX(目标与口径!$F$5:$F$36,MATCH("net_sales",目标与口径!$A$5:$A$36,0)) -> 62000 | D7: =IFERROR(IF(INDEX(目标与口径!$E$5:$E$36,MATCH("net_sales",目标与口径!$A$5:$A$36,0))="越高越好",IF($B$7>=INDEX(目标与口径!$G$5:$G$36,MATCH("net_sales",目标与口径!$A$5:$A$36,0)),"绿",IF($B$7>=INDEX(目标与口径!$H$5:$H$36,MATCH("net_sales",目标与口径!$A$5:$A$36,0)),"黄","红")),IF($B$7<=INDEX(目标与口径!$G$5:$G$36,MATCH("net_sales",目标与口径!$A$5:$A$36,0)),"绿",IF($B$7<=INDEX(目标与口径!$H$5:$H$36,MATCH("net_sales",目标与口径!$A$5:$A$36,0)),"黄","红"))),"—") -> 黄 | E7: =INDEX(目标与口径!$G$5:$G$36,MATCH("net_sales",目标与口径!$A$5:$A$36,0)) -> 58000 | F7: =INDEX(目标与口径!$H$5:$H$36,MATCH("net_sales",目标与口径!$A$5:$A$36,0)) -> 52000 | G7: =IFERROR(MAX(0,IF(INDEX(目标与口径!$E$5:$E$36,MATCH("net_sales",目标与口径!$A$5:$A$36,0))="越高越好",INDEX(目标与口径!$G$5:$G$36,MATCH("net_sales",目标与口径!$A$5:$A$36,0))-$B$7,$B$7-INDEX(目标与口径!$G$5:$G$36,MATCH("net_sales",目标与口径!$A$5:$A$36,0)))/ABS(INDEX(目标与口径!$H$5:$H$36,MATCH("net_sales",目标与口径!$A$5:$A$36,0))-INDEX(目标与口径!$G$5:$G$36,MATCH("net_sales",目标与口径!$A$5:$A$36,0)))),0) -> 0.33537667 | H7: =INDEX(目标与口径!$J$5:$J$36,MATCH("net_sales",目标与口径!$A$5:$A$36,0)) -> 店长 | I7: =INDEX(目标与口径!$N$5:$N$36,MATCH("net_sales",目标与口径!$A$5:$A$36,0)) -> PB-01
A8: 交易笔数 | B8: =IFERROR(INDEX(每日经营日报!$E$5:$E$18,MATCH($B$3,每日经营日报!$A$5:$A$18,0)),0) -> 1564 | C8: =INDEX(目标与口径!$F$5:$F$36,MATCH("guest_count",目标与口径!$A$5:$A$36,0)) -> 1750 | D8: =IFERROR(IF(INDEX(目标与口径!$E$5:$E$36,MATCH("guest_count",目标与口径!$A$5:$A$36,0))="越高越好",IF($B$8>=INDEX(目标与口径!$G$5:$G$36,MATCH("guest_count",目标与口径!$A$5:$A$36,0)),"绿",IF($B$8>=INDEX(目标与口径!$H$5:$H$36,MATCH("guest_count",目标与口径!$A$5:$A$36,0)),"黄","红")),IF($B$8<=INDEX(目标与口径!$G$5:$G$36,MATCH("guest_count",目标与口径!$A$5:$A$36,0)),"绿",IF($B$8<=INDEX(目标与口径!$H$5:$H$36,MATCH("guest_count",目标与口径!$A$5:$A$36,0)),"黄","红"))),"—") -> 黄 | E8: =INDEX(目标与口径!$G$5:$G$36,MATCH("guest_count",目标与口径!$A$5:$A$36,0)) -> 1620 | F8: =INDEX(目标与口径!$H$5:$H$36,MATCH("guest_count",目标与口径!$A$5:$A$36,0)) -> 1480 | G8: =IFERROR(MAX(0,IF(INDEX(目标与口径!$E$5:$E$36,MATCH("guest_count",目标与口径!$A$5:$A$36,0))="越高越好",INDEX(目标与口径!$G$5:$G$36,MATCH("guest_count",目标与口径!$A$5:$A$36,0))-$B$8,$B$8-INDEX(目标与口径!$G$5:$G$36,MATCH("guest_count",目标与口径!$A$5:$A$36,0)))/ABS(INDEX(目标与口径!$H$5:$H$36,MATCH("guest_count",目标与口径!$A$5:$A$36,0))-INDEX(目标与口径!$G$5:$G$36,MATCH("guest_count",目标与口径!$A$5:$A$36,0)))),0) -> 0.4 | H8: =INDEX(目标与口径!$J$5:$J$36,MATCH("guest_count",目标与口径!$A$5:$A$36,0)) -> 店长 | I8: =INDEX(目标与口径!$N$5:$N$36,MATCH("guest_count",目标与口径!$A$5:$A$36,0)) -> PB-01
A9: 客单价 | B9: =IFERROR(INDEX(每日经营日报!$F$5:$F$18,MATCH($B$3,每日经营日报!$A$5:$A$18,0)),0) -> 35.797788 | C9: =INDEX(目标与口径!$F$5:$F$36,MATCH("avg_check",目标与口径!$A$5:$A$36,0)) -> 35.5 | D9: =IFERROR(IF(INDEX(目标与口径!$E$5:$E$36,MATCH("avg_check",目标与口径!$A$5:$A$36,0))="越高越好",IF($B$9>=INDEX(目标与口径!$G$5:$G$36,MATCH("avg_check",目标与口径!$A$5:$A$36,0)),"绿",IF($B$9>=INDEX(目标与口径!$H$5:$H$36,MATCH("avg_check",目标与口径!$A$5:$A$36,0)),"黄","红")),IF($B$9<=INDEX(目标与口径!$G$5:$G$36,MATCH("avg_check",目标与口径!$A$5:$A$36,0)),"绿",IF($B$9<=INDEX(目标与口径!$H$5:$H$36,MATCH("avg_check",目标与口径!$A$5:$A$36,0)),"黄","红"))),"—") -> 绿 | E9: =INDEX(目标与口径!$G$5:$G$36,MATCH("avg_check",目标与口径!$A$5:$A$36,0)) -> 35 | F9: =INDEX(目标与口径!$H$5:$H$36,MATCH("avg_check",目标与口径!$A$5:$A$36,0)) -> 33 | G9: =IFERROR(MAX(0,IF(INDEX(目标与口径!$E$5:$E$36,MATCH("avg_check",目标与口径!$A$5:$A$36,0))="越高越好",INDEX(目标与口径!$G$5:$G$36,MATCH("avg_check",目标与口径!$A$5:$A$36,0))-$B$9,$B$9-INDEX(目标与口径!$G$5:$G$36,MATCH("avg_check",目标与口径!$A$5:$A$36,0)))/ABS(INDEX(目标与口径!$H$5:$H$36,MATCH("avg_check",目标与口径!$A$5:$A$36,0))-INDEX(目标与口径!$G$5:$G$36,MATCH("avg_check",目标与口径!$A$5:$A$36,0)))),0) -> 0 | H9: =INDEX(目标与口径!$J$5:$J$36,MATCH("avg_check",目标与口径!$A$5:$A$36,0)) -> 值班经理 | I9: =INDEX(目标与口径!$N$5:$N$36,MATCH("avg_check",目标与口径!$A$5:$A$36,0)) -> PB-02
A10: 食品成本率 | B10: =IFERROR(INDEX(每日经营日报!$Q$5:$Q$18,MATCH($B$3,每日经营日报!$A$5:$A$18,0)),0) -> 0.31219353 | C10: =INDEX(目标与口径!$F$5:$F$36,MATCH("food_cost_pct",目标与口径!$A$5:$A$36,0)) -> 0.305 | D10: =IFERROR(IF(INDEX(目标与口径!$E$5:$E$36,MATCH("food_cost_pct",目标与口径!$A$5:$A$36,0))="越高越好",IF($B$10>=INDEX(目标与口径!$G$5:$G$36,MATCH("food_cost_pct",目标与口径!$A$5:$A$36,0)),"绿",IF($B$10>=INDEX(目标与口径!$H$5:$H$36,MATCH("food_cost_pct",目标与口径!$A$5:$A$36,0)),"黄","红")),IF($B$10<=INDEX(目标与口径!$G$5:$G$36,MATCH("food_cost_pct",目标与口径!$A$5:$A$36,0)),"绿",IF($B$10<=INDEX(目标与口径!$H$5:$H$36,MATCH("food_cost_pct",目标与口径!$A$5:$A$36,0)),"黄","红"))),"—") -> 黄 | E10: =INDEX(目标与口径!$G$5:$G$36,MATCH("food_cost_pct",目标与口径!$A$5:$A$36,0)) -> 0.31 | F10: =INDEX(目标与口径!$H$5:$H$36,MATCH("food_cost_pct",目标与口径!$A$5:$A$36,0)) -> 0.325 | G10: =IFERROR(MAX(0,IF(INDEX(目标与口径!$E$5:$E$36,MATCH("food_cost_pct",目标与口径!$A$5:$A$36,0))="越高越好",INDEX(目标与口径!$G$5:$G$36,MATCH("food_cost_pct",目标与口径!$A$5:$A$36,0))-$B$10,$B$10-INDEX(目标与口径!$G$5:$G$36,MATCH("food_cost_pct",目标与口径!$A$5:$A$36,0)))/ABS(INDEX(目标与口径!$H$5:$H$36,MATCH("food_cost_pct",目标与口径!$A$5:$A$36,0))-INDEX(目标与口径!$G$5:$G$36,MATCH("food_cost_pct",目标与口径!$A$5:$A$36,0)))),0) -> 0.14623511 | H10: =INDEX(目标与口径!$J$5:$J$36,MATCH("food_cost_pct",目标与口径!$A$5:$A$36,0)) -> 店长 | I10: =INDEX(目标与口径!$N$5:$N$36,MATCH("food_cost_pct",目标与口径!$A$5:$A$36,0)) -> PB-06
A11: 废弃率 | B11: =IFERROR(INDEX(每日经营日报!$S$5:$S$18,MATCH($B$3,每日经营日报!$A$5:$A$18,0)),0) -> 0.011011518 | C11: =INDEX(目标与口径!$F$5:$F$36,MATCH("waste_pct",目标与口径!$A$5:$A$36,0)) -> 0.008 | D11: =IFERROR(IF(INDEX(目标与口径!$E$5:$E$36,MATCH("waste_pct",目标与口径!$A$5:$A$36,0))="越高越好",IF($B$11>=INDEX(目标与口径!$G$5:$G$36,MATCH("waste_pct",目标与口径!$A$5:$A$36,0)),"绿",IF($B$11>=INDEX(目标与口径!$H$5:$H$36,MATCH("waste_pct",目标与口径!$A$5:$A$36,0)),"黄","红")),IF($B$11<=INDEX(目标与口径!$G$5:$G$36,MATCH("waste_pct",目标与口径!$A$5:$A$36,0)),"绿",IF($B$11<=INDEX(目标与口径!$H$5:$H$36,MATCH("waste_pct",目标与口径!$A$5:$A$36,0)),"黄","红"))),"—") -> 黄 | E11: =INDEX(目标与口径!$G$5:$G$36,MATCH("waste_pct",目标与口径!$A$5:$A$36,0)) -> 0.01 | F11: =INDEX(目标与口径!$H$5:$H$36,MATCH("waste_pct",目标与口径!$A$5:$A$36,0)) -> 0.015 | G11: =IFERROR(MAX(0,IF(INDEX(目标与口径!$E$5:$E$36,MATCH("waste_pct",目标与口径!$A$5:$A$36,0))="越高越好",INDEX(目标与口径!$G$5:$G$36,MATCH("waste_pct",目标与口径!$A$5:$A$36,0))-$B$11,$B$11-INDEX(目标与口径!$G$5:$G$36,MATCH("waste_pct",目标与口径!$A$5:$A$36,0)))/ABS(INDEX(目标与口径!$H$5:$H$36,MATCH("waste_pct",目标与口径!$A$5:$A$36,0))-INDEX(目标与口径!$G$5:$G$36,MATCH("waste_pct",目标与口径!$A$5:$A$36,0)))),0) -> 0.20230358 | H11: =INDEX(目标与口径!$J$5:$J$36,MATCH("waste_pct",目标与口径!$A$5:$A$36,0)) -> 值班经理 | I11: =INDEX(目标与口径!$N$5:$N$36,MATCH("waste_pct",目标与口径!$A$5:$A$36,0)) -> PB-06
A12: 人工成本率 | B12: =IFERROR(INDEX(每日经营日报!$Z$5:$Z$18,MATCH($B$3,每日经营日报!$A$5:$A$18,0)),0) -> 0.13246748 | C12: =INDEX(目标与口径!$F$5:$F$36,MATCH("labor_cost_pct",目标与口径!$A$5:$A$36,0)) -> 0.135 | D12: =IFERROR(IF(INDEX(目标与口径!$E$5:$E$36,MATCH("labor_cost_pct",目标与口径!$A$5:$A$36,0))="越高越好",IF($B$12>=INDEX(目标与口径!$G$5:$G$36,MATCH("labor_cost_pct",目标与口径!$A$5:$A$36,0)),"绿",IF($B$12>=INDEX(目标与口径!$H$5:$H$36,MATCH("labor_cost_pct",目标与口径!$A$5:$A$36,0)),"黄","红")),IF($B$12<=INDEX(目标与口径!$G$5:$G$36,MATCH("labor_cost_pct",目标与口径!$A$5:$A$36,0)),"绿",IF($B$12<=INDEX(目标与口径!$H$5:$H$36,MATCH("labor_cost_pct",目标与口径!$A$5:$A$36,0)),"黄","红"))),"—") -> 绿 | E12: =INDEX(目标与口径!$G$5:$G$36,MATCH("labor_cost_pct",目标与口径!$A$5:$A$36,0)) -> 0.14 | F12: =INDEX(目标与口径!$H$5:$H$36,MATCH("labor_cost_pct",目标与口径!$A$5:$A$36,0)) -> 0.155 | G12: =IFERROR(MAX(0,IF(INDEX(目标与口径!$E$5:$E$36,MATCH("labor_cost_pct",目标与口径!$A$5:$A$36,0))="越高越好",INDEX(目标与口径!$G$5:$G$36,MATCH("labor_cost_pct",目标与口径!$A$5:$A$36,0))-$B$12,$B$12-INDEX(目标与口径!$G$5:$G$36,MATCH("labor_cost_pct",目标与口径!$A$5:$A$36,0)))/ABS(INDEX(目标与口径!$H$5:$H$36,MATCH("labor_cost_pct",目标与口径!$A$5:$A$36,0))-INDEX(目标与口径!$G$5:$G$36,MATCH("labor_cost_pct",目标与口径!$A$5:$A$36,0)))),0) -> 0 | H12: =INDEX(目标与口径!$J$5:$J$36,MATCH("labor_cost_pct",目标与口径!$A$5:$A$36,0)) -> 店长 | I12: =INDEX(目标与口径!$N$5:$N$36,MATCH("labor_cost_pct",目标与口径!$A$5:$A$36,0)) -> PB-07
A13: 人时销售 SPLH | B13: =IFERROR(INDEX(每日经营日报!$AA$5:$AA$18,MATCH($B$3,每日经营日报!$A$5:$A$18,0)),0) -> 215.14714 | C13: =INDEX(目标与口径!$F$5:$F$36,MATCH("splh",目标与口径!$A$5:$A$36,0)) -> 210 | D13: =IFERROR(IF(INDEX(目标与口径!$E$5:$E$36,MATCH("splh",目标与口径!$A$5:$A$36,0))="越高越好",IF($B$13>=INDEX(目标与口径!$G$5:$G$36,MATCH("splh",目标与口径!$A$5:$A$36,0)),"绿",IF($B$13>=INDEX(目标与口径!$H$5:$H$36,MATCH("splh",目标与口径!$A$5:$A$36,0)),"黄","红")),IF($B$13<=INDEX(目标与口径!$G$5:$G$36,MATCH("splh",目标与口径!$A$5:$A$36,0)),"绿",IF($B$13<=INDEX(目标与口径!$H$5:$H$36,MATCH("splh",目标与口径!$A$5:$A$36,0)),"黄","红"))),"—") -> 绿 | E13: =INDEX(目标与口径!$G$5:$G$36,MATCH("splh",目标与口径!$A$5:$A$36,0)) -> 205 | F13: =INDEX(目标与口径!$H$5:$H$36,MATCH("splh",目标与口径!$A$5:$A$36,0)) -> 185 | G13: =IFERROR(MAX(0,IF(INDEX(目标与口径!$E$5:$E$36,MATCH("splh",目标与口径!$A$5:$A$36,0))="越高越好",INDEX(目标与口径!$G$5:$G$36,MATCH("splh",目标与口径!$A$5:$A$36,0))-$B$13,$B$13-INDEX(目标与口径!$G$5:$G$36,MATCH("splh",目标与口径!$A$5:$A$36,0)))/ABS(INDEX(目标与口径!$H$5:$H$36,MATCH("splh",目标与口径!$A$5:$A$36,0))-INDEX(目标与口径!$G$5:$G$36,MATCH("splh",目标与口径!$A$5:$A$36,0)))),0) -> 0 | H13: =INDEX(目标与口径!$J$5:$J$36,MATCH("splh",目标与口径!$A$5:$A$36,0)) -> 值班经理 | I13: =INDEX(目标与口径!$N$5:$N$36,MATCH("splh",目标与口径!$A$5:$A$36,0)) -> PB-07
A14: 服务速度达标率 | B14: =IFERROR(INDEX(每日经营日报!$AI$5:$AI$18,MATCH($B$3,每日经营日报!$A$5:$A$18,0)),0) -> 0.76598465 | C14: =INDEX(目标与口径!$F$5:$F$36,MATCH("speed_hit_rate",目标与口径!$A$5:$A$36,0)) -> 0.9 | D14: =IFERROR(IF(INDEX(目标与口径!$E$5:$E$36,MATCH("speed_hit_rate",目标与口径!$A$5:$A$36,0))="越高越好",IF($B$14>=INDEX(目标与口径!$G$5:$G$36,MATCH("speed_hit_rate",目标与口径!$A$5:$A$36,0)),"绿",IF($B$14>=INDEX(目标与口径!$H$5:$H$36,MATCH("speed_hit_rate",目标与口径!$A$5:$A$36,0)),"黄","红")),IF($B$14<=INDEX(目标与口径!$G$5:$G$36,MATCH("speed_hit_rate",目标与口径!$A$5:$A$36,0)),"绿",IF($B$14<=INDEX(目标与口径!$H$5:$H$36,MATCH("speed_hit_rate",目标与口径!$A$5:$A$36,0)),"黄","红"))),"—") -> 红 | E14: =INDEX(目标与口径!$G$5:$G$36,MATCH("speed_hit_rate",目标与口径!$A$5:$A$36,0)) -> 0.88 | F14: =INDEX(目标与口径!$H$5:$H$36,MATCH("speed_hit_rate",目标与口径!$A$5:$A$36,0)) -> 0.8 | G14: =IFERROR(MAX(0,IF(INDEX(目标与口径!$E$5:$E$36,MATCH("speed_hit_rate",目标与口径!$A$5:$A$36,0))="越高越好",INDEX(目标与口径!$G$5:$G$36,MATCH("speed_hit_rate",目标与口径!$A$5:$A$36,0))-$B$14,$B$14-INDEX(目标与口径!$G$5:$G$36,MATCH("speed_hit_rate",目标与口径!$A$5:$A$36,0)))/ABS(INDEX(目标与口径!$H$5:$H$36,MATCH("speed_hit_rate",目标与口径!$A$5:$A$36,0))-INDEX(目标与口径!$G$5:$G$36,MATCH("speed_hit_rate",目标与口径!$A$5:$A$36,0)))),0) -> 1.4251918 | H14: =INDEX(目标与口径!$J$5:$J$36,MATCH("speed_hit_rate",目标与口径!$A$5:$A$36,0)) -> 值班经理 | I14: =INDEX(目标与口径!$N$5:$N$36,MATCH("speed_hit_rate",目标与口径!$A$5:$A$36,0)) -> PB-04
A15: 得来速总时长 | B15: =IFERROR(INDEX(每日经营日报!$AC$5:$AC$18,MATCH($B$3,每日经营日报!$A$5:$A$18,0)),0) -> 158.34 | C15: =INDEX(目标与口径!$F$5:$F$36,MATCH("dt_total_time",目标与口径!$A$5:$A$36,0)) -> 180 | D15: =IFERROR(IF(INDEX(目标与口径!$E$5:$E$36,MATCH("dt_total_time",目标与口径!$A$5:$A$36,0))="越高越好",IF($B$15>=INDEX(目标与口径!$G$5:$G$36,MATCH("dt_total_time",目标与口径!$A$5:$A$36,0)),"绿",IF($B$15>=INDEX(目标与口径!$H$5:$H$36,MATCH("dt_total_time",目标与口径!$A$5:$A$36,0)),"黄","红")),IF($B$15<=INDEX(目标与口径!$G$5:$G$36,MATCH("dt_total_time",目标与口径!$A$5:$A$36,0)),"绿",IF($B$15<=INDEX(目标与口径!$H$5:$H$36,MATCH("dt_total_time",目标与口径!$A$5:$A$36,0)),"黄","红"))),"—") -> 绿 | E15: =INDEX(目标与口径!$G$5:$G$36,MATCH("dt_total_time",目标与口径!$A$5:$A$36,0)) -> 190 | F15: =INDEX(目标与口径!$H$5:$H$36,MATCH("dt_total_time",目标与口径!$A$5:$A$36,0)) -> 215 | G15: =IFERROR(MAX(0,IF(INDEX(目标与口径!$E$5:$E$36,MATCH("dt_total_time",目标与口径!$A$5:$A$36,0))="越高越好",INDEX(目标与口径!$G$5:$G$36,MATCH("dt_total_time",目标与口径!$A$5:$A$36,0))-$B$15,$B$15-INDEX(目标与口径!$G$5:$G$36,MATCH("dt_total_time",目标与口径!$A$5:$A$36,0)))/ABS(INDEX(目标与口径!$H$5:$H$36,MATCH("dt_total_time",目标与口径!$A$5:$A$36,0))-INDEX(目标与口径!$G$5:$G$36,MATCH("dt_total_time",目标与口径!$A$5:$A$36,0)))),0) -> 0 | H15: =INDEX(目标与口径!$J$5:$J$36,MATCH("dt_total_time",目标与口径!$A$5:$A$36,0)) -> 值班经理 | I15: =INDEX(目标与口径!$N$5:$N$36,MATCH("dt_total_time",目标与口径!$A$5:$A$36,0)) -> PB-04
A16: 订单准确率 | B16: =IFERROR(INDEX(每日经营日报!$AK$5:$AK$18,MATCH($B$3,每日经营日报!$A$5:$A$18,0)),0) -> 0.99936061 | C16: =INDEX(目标与口径!$F$5:$F$36,MATCH("order_accuracy",目标与口径!$A$5:$A$36,0)) -> 0.996 | D16: =IFERROR(IF(INDEX(目标与口径!$E$5:$E$36,MATCH("order_accuracy",目标与口径!$A$5:$A$36,0))="越高越好",IF($B$16>=INDEX(目标与口径!$G$5:$G$36,MATCH("order_accuracy",目标与口径!$A$5:$A$36,0)),"绿",IF($B$16>=INDEX(目标与口径!$H$5:$H$36,MATCH("order_accuracy",目标与口径!$A$5:$A$36,0)),"黄","红")),IF($B$16<=INDEX(目标与口径!$G$5:$G$36,MATCH("order_accuracy",目标与口径!$A$5:$A$36,0)),"绿",IF($B$16<=INDEX(目标与口径!$H$5:$H$36,MATCH("order_accuracy",目标与口径!$A$5:$A$36,0)),"黄","红"))),"—") -> 绿 | E16: =INDEX(目标与口径!$G$5:$G$36,MATCH("order_accuracy",目标与口径!$A$5:$A$36,0)) -> 0.994 | F16: =INDEX(目标与口径!$H$5:$H$36,MATCH("order_accuracy",目标与口径!$A$5:$A$36,0)) -> 0.99 | G16: =IFERROR(MAX(0,IF(INDEX(目标与口径!$E$5:$E$36,MATCH("order_accuracy",目标与口径!$A$5:$A$36,0))="越高越好",INDEX(目标与口径!$G$5:$G$36,MATCH("order_accuracy",目标与口径!$A$5:$A$36,0))-$B$16,$B$16-INDEX(目标与口径!$G$5:$G$36,MATCH("order_accuracy",目标与口径!$A$5:$A$36,0)))/ABS(INDEX(目标与口径!$H$5:$H$36,MATCH("order_accuracy",目标与口径!$A$5:$A$36,0))-INDEX(目标与口径!$G$5:$G$36,MATCH("order_accuracy",目标与口径!$A$5:$A$36,0)))),0) -> 0 | H16: =INDEX(目标与口径!$J$5:$J$36,MATCH("order_accuracy",目标与口径!$A$5:$A$36,0)) -> 值班经理 | I16: =INDEX(目标与口径!$N$5:$N$36,MATCH("order_accuracy",目标与口径!$A$5:$A$36,0)) -> PB-05
A17: 食安日检得分 | B17: =IFERROR(INDEX(每日经营日报!$AM$5:$AM$18,MATCH($B$3,每日经营日报!$A$5:$A$18,0)),0) -> 100 | C17: =INDEX(目标与口径!$F$5:$F$36,MATCH("food_safety_score",目标与口径!$A$5:$A$36,0)) -> 100 | D17: =IFERROR(IF(INDEX(目标与口径!$E$5:$E$36,MATCH("food_safety_score",目标与口径!$A$5:$A$36,0))="越高越好",IF($B$17>=INDEX(目标与口径!$G$5:$G$36,MATCH("food_safety_score",目标与口径!$A$5:$A$36,0)),"绿",IF($B$17>=INDEX(目标与口径!$H$5:$H$36,MATCH("food_safety_score",目标与口径!$A$5:$A$36,0)),"黄","红")),IF($B$17<=INDEX(目标与口径!$G$5:$G$36,MATCH("food_safety_score",目标与口径!$A$5:$A$36,0)),"绿",IF($B$17<=INDEX(目标与口径!$H$5:$H$36,MATCH("food_safety_score",目标与口径!$A$5:$A$36,0)),"黄","红"))),"—") -> 绿 | E17: =INDEX(目标与口径!$G$5:$G$36,MATCH("food_safety_score",目标与口径!$A$5:$A$36,0)) -> 98 | F17: =INDEX(目标与口径!$H$5:$H$36,MATCH("food_safety_score",目标与口径!$A$5:$A$36,0)) -> 95 | G17: =IFERROR(MAX(0,IF(INDEX(目标与口径!$E$5:$E$36,MATCH("food_safety_score",目标与口径!$A$5:$A$36,0))="越高越好",INDEX(目标与口径!$G$5:$G$36,MATCH("food_safety_score",目标与口径!$A$5:$A$36,0))-$B$17,$B$17-INDEX(目标与口径!$G$5:$G$36,MATCH("food_safety_score",目标与口径!$A$5:$A$36,0)))/ABS(INDEX(目标与口径!$H$5:$H$36,MATCH("food_safety_score",目标与口径!$A$5:$A$36,0))-INDEX(目标与口径!$G$5:$G$36,MATCH("food_safety_score",目标与口径!$A$5:$A$36,0)))),0) -> 0 | H17: =INDEX(目标与口径!$J$5:$J$36,MATCH("food_safety_score",目标与口径!$A$5:$A$36,0)) -> 店长 | I17: =INDEX(目标与口径!$N$5:$N$36,MATCH("food_safety_score",目标与口径!$A$5:$A$36,0)) -> PB-09
A18: 关键温度点异常数 | B18: =IFERROR(INDEX(每日经营日报!$AN$5:$AN$18,MATCH($B$3,每日经营日报!$A$5:$A$18,0)),0) -> 0 | C18: =INDEX(目标与口径!$F$5:$F$36,MATCH("critical_temp_fail",目标与口径!$A$5:$A$36,0)) -> 0 | D18: =IFERROR(IF(INDEX(目标与口径!$E$5:$E$36,MATCH("critical_temp_fail",目标与口径!$A$5:$A$36,0))="越高越好",IF($B$18>=INDEX(目标与口径!$G$5:$G$36,MATCH("critical_temp_fail",目标与口径!$A$5:$A$36,0)),"绿",IF($B$18>=INDEX(目标与口径!$H$5:$H$36,MATCH("critical_temp_fail",目标与口径!$A$5:$A$36,0)),"黄","红")),IF($B$18<=INDEX(目标与口径!$G$5:$G$36,MATCH("critical_temp_fail",目标与口径!$A$5:$A$36,0)),"绿",IF($B$18<=INDEX(目标与口径!$H$5:$H$36,MATCH("critical_temp_fail",目标与口径!$A$5:$A$36,0)),"黄","红"))),"—") -> 绿 | E18: =INDEX(目标与口径!$G$5:$G$36,MATCH("critical_temp_fail",目标与口径!$A$5:$A$36,0)) -> 0 | F18: =INDEX(目标与口径!$H$5:$H$36,MATCH("critical_temp_fail",目标与口径!$A$5:$A$36,0)) -> 1 | G18: =IFERROR(MAX(0,IF(INDEX(目标与口径!$E$5:$E$36,MATCH("critical_temp_fail",目标与口径!$A$5:$A$36,0))="越高越好",INDEX(目标与口径!$G$5:$G$36,MATCH("critical_temp_fail",目标与口径!$A$5:$A$36,0))-$B$18,$B$18-INDEX(目标与口径!$G$5:$G$36,MATCH("critical_temp_fail",目标与口径!$A$5:$A$36,0)))/ABS(INDEX(目标与口径!$H$5:$H$36,MATCH("critical_temp_fail",目标与口径!$A$5:$A$36,0))-INDEX(目标与口径!$G$5:$G$36,MATCH("critical_temp_fail",目标与口径!$A$5:$A$36,0)))),0) -> 0 | H18: =INDEX(目标与口径!$J$5:$J$36,MATCH("critical_temp_fail",目标与口径!$A$5:$A$36,0)) -> 值班经理 | I18: =INDEX(目标与口径!$N$5:$N$36,MATCH("critical_temp_fail",目标与口径!$A$5:$A$36,0)) -> PB-09
A19: 设备停机时长 | B19: =IFERROR(INDEX(每日经营日报!$AS$5:$AS$18,MATCH($B$3,每日经营日报!$A$5:$A$18,0)),0) -> 76 | C19: =INDEX(目标与口径!$F$5:$F$36,MATCH("equipment_downtime",目标与口径!$A$5:$A$36,0)) -> 0 | D19: =IFERROR(IF(INDEX(目标与口径!$E$5:$E$36,MATCH("equipment_downtime",目标与口径!$A$5:$A$36,0))="越高越好",IF($B$19>=INDEX(目标与口径!$G$5:$G$36,MATCH("equipment_downtime",目标与口径!$A$5:$A$36,0)),"绿",IF($B$19>=INDEX(目标与口径!$H$5:$H$36,MATCH("equipment_downtime",目标与口径!$A$5:$A$36,0)),"黄","红")),IF($B$19<=INDEX(目标与口径!$G$5:$G$36,MATCH("equipment_downtime",目标与口径!$A$5:$A$36,0)),"绿",IF($B$19<=INDEX(目标与口径!$H$5:$H$36,MATCH("equipment_downtime",目标与口径!$A$5:$A$36,0)),"黄","红"))),"—") -> 红 | E19: =INDEX(目标与口径!$G$5:$G$36,MATCH("equipment_downtime",目标与口径!$A$5:$A$36,0)) -> 15 | F19: =INDEX(目标与口径!$H$5:$H$36,MATCH("equipment_downtime",目标与口径!$A$5:$A$36,0)) -> 60 | G19: =IFERROR(MAX(0,IF(INDEX(目标与口径!$E$5:$E$36,MATCH("equipment_downtime",目标与口径!$A$5:$A$36,0))="越高越好",INDEX(目标与口径!$G$5:$G$36,MATCH("equipment_downtime",目标与口径!$A$5:$A$36,0))-$B$19,$B$19-INDEX(目标与口径!$G$5:$G$36,MATCH("equipment_downtime",目标与口径!$A$5:$A$36,0)))/ABS(INDEX(目标与口径!$H$5:$H$36,MATCH("equipment_downtime",目标与口径!$A$5:$A$36,0))-INDEX(目标与口径!$G$5:$G$36,MATCH("equipment_downtime",目标与口径!$A$5:$A$36,0)))),0) -> 1.3555556 | H19: =INDEX(目标与口径!$J$5:$J$36,MATCH("equipment_downtime",目标与口径!$A$5:$A$36,0)) -> 店长 | I19: =INDEX(目标与口径!$N$5:$N$36,MATCH("equipment_downtime",目标与口径!$A$5:$A$36,0)) -> PB-11
A20: 出勤达成率 | B20: =IFERROR(INDEX(每日经营日报!$AV$5:$AV$18,MATCH($B$3,每日经营日报!$A$5:$A$18,0)),0) -> 1 | C20: =INDEX(目标与口径!$F$5:$F$36,MATCH("attendance_rate",目标与口径!$A$5:$A$36,0)) -> 1 | D20: =IFERROR(IF(INDEX(目标与口径!$E$5:$E$36,MATCH("attendance_rate",目标与口径!$A$5:$A$36,0))="越高越好",IF($B$20>=INDEX(目标与口径!$G$5:$G$36,MATCH("attendance_rate",目标与口径!$A$5:$A$36,0)),"绿",IF($B$20>=INDEX(目标与口径!$H$5:$H$36,MATCH("attendance_rate",目标与口径!$A$5:$A$36,0)),"黄","红")),IF($B$20<=INDEX(目标与口径!$G$5:$G$36,MATCH("attendance_rate",目标与口径!$A$5:$A$36,0)),"绿",IF($B$20<=INDEX(目标与口径!$H$5:$H$36,MATCH("attendance_rate",目标与口径!$A$5:$A$36,0)),"黄","红"))),"—") -> 绿 | E20: =INDEX(目标与口径!$G$5:$G$36,MATCH("attendance_rate",目标与口径!$A$5:$A$36,0)) -> 0.97 | F20: =INDEX(目标与口径!$H$5:$H$36,MATCH("attendance_rate",目标与口径!$A$5:$A$36,0)) -> 0.92 | G20: =IFERROR(MAX(0,IF(INDEX(目标与口径!$E$5:$E$36,MATCH("attendance_rate",目标与口径!$A$5:$A$36,0))="越高越好",INDEX(目标与口径!$G$5:$G$36,MATCH("attendance_rate",目标与口径!$A$5:$A$36,0))-$B$20,$B$20-INDEX(目标与口径!$G$5:$G$36,MATCH("attendance_rate",目标与口径!$A$5:$A$36,0)))/ABS(INDEX(目标与口径!$H$5:$H$36,MATCH("attendance_rate",目标与口径!$A$5:$A$36,0))-INDEX(目标与口径!$G$5:$G$36,MATCH("attendance_rate",目标与口径!$A$5:$A$36,0)))),0) -> 0 | H20: =INDEX(目标与口径!$J$5:$J$36,MATCH("attendance_rate",目标与口径!$A$5:$A$36,0)) -> 值班经理 | I20: =INDEX(目标与口径!$N$5:$N$36,MATCH("attendance_rate",目标与口径!$A$5:$A$36,0)) -> PB-07
A21: 迟到率 | B21: =IFERROR(INDEX(每日经营日报!$AX$5:$AX$18,MATCH($B$3,每日经营日报!$A$5:$A$18,0)),0) -> 0.10526316 | C21: =INDEX(目标与口径!$F$5:$F$36,MATCH("late_rate",目标与口径!$A$5:$A$36,0)) -> 0.02 | D21: =IFERROR(IF(INDEX(目标与口径!$E$5:$E$36,MATCH("late_rate",目标与口径!$A$5:$A$36,0))="越高越好",IF($B$21>=INDEX(目标与口径!$G$5:$G$36,MATCH("late_rate",目标与口径!$A$5:$A$36,0)),"绿",IF($B$21>=INDEX(目标与口径!$H$5:$H$36,MATCH("late_rate",目标与口径!$A$5:$A$36,0)),"黄","红")),IF($B$21<=INDEX(目标与口径!$G$5:$G$36,MATCH("late_rate",目标与口径!$A$5:$A$36,0)),"绿",IF($B$21<=INDEX(目标与口径!$H$5:$H$36,MATCH("late_rate",目标与口径!$A$5:$A$36,0)),"黄","红"))),"—") -> 红 | E21: =INDEX(目标与口径!$G$5:$G$36,MATCH("late_rate",目标与口径!$A$5:$A$36,0)) -> 0.03 | F21: =INDEX(目标与口径!$H$5:$H$36,MATCH("late_rate",目标与口径!$A$5:$A$36,0)) -> 0.08 | G21: =IFERROR(MAX(0,IF(INDEX(目标与口径!$E$5:$E$36,MATCH("late_rate",目标与口径!$A$5:$A$36,0))="越高越好",INDEX(目标与口径!$G$5:$G$36,MATCH("late_rate",目标与口径!$A$5:$A$36,0))-$B$21,$B$21-INDEX(目标与口径!$G$5:$G$36,MATCH("late_rate",目标与口径!$A$5:$A$36,0)))/ABS(INDEX(目标与口径!$H$5:$H$36,MATCH("late_rate",目标与口径!$A$5:$A$36,0))-INDEX(目标与口径!$G$5:$G$36,MATCH("late_rate",目标与口径!$A$5:$A$36,0)))),0) -> 1.5052632 | H21: =INDEX(目标与口径!$J$5:$J$36,MATCH("late_rate",目标与口径!$A$5:$A$36,0)) -> 组长 | I21: =INDEX(目标与口径!$N$5:$N$36,MATCH("late_rate",目标与口径!$A$5:$A$36,0)) -> PB-07
A22: 顾客满意度 | B22: =IFERROR(INDEX(每日经营日报!$BD$5:$BD$18,MATCH($B$3,每日经营日报!$A$5:$A$18,0)),0) -> 92.571429 | C22: =INDEX(目标与口径!$F$5:$F$36,MATCH("csat",目标与口径!$A$5:$A$36,0)) -> 88 | D22: =IFERROR(IF(INDEX(目标与口径!$E$5:$E$36,MATCH("csat",目标与口径!$A$5:$A$36,0))="越高越好",IF($B$22>=INDEX(目标与口径!$G$5:$G$36,MATCH("csat",目标与口径!$A$5:$A$36,0)),"绿",IF($B$22>=INDEX(目标与口径!$H$5:$H$36,MATCH("csat",目标与口径!$A$5:$A$36,0)),"黄","红")),IF($B$22<=INDEX(目标与口径!$G$5:$G$36,MATCH("csat",目标与口径!$A$5:$A$36,0)),"绿",IF($B$22<=INDEX(目标与口径!$H$5:$H$36,MATCH("csat",目标与口径!$A$5:$A$36,0)),"黄","红"))),"—") -> 绿 | E22: =INDEX(目标与口径!$G$5:$G$36,MATCH("csat",目标与口径!$A$5:$A$36,0)) -> 85 | F22: =INDEX(目标与口径!$H$5:$H$36,MATCH("csat",目标与口径!$A$5:$A$36,0)) -> 78 | G22: =IFERROR(MAX(0,IF(INDEX(目标与口径!$E$5:$E$36,MATCH("csat",目标与口径!$A$5:$A$36,0))="越高越好",INDEX(目标与口径!$G$5:$G$36,MATCH("csat",目标与口径!$A$5:$A$36,0))-$B$22,$B$22-INDEX(目标与口径!$G$5:$G$36,MATCH("csat",目标与口径!$A$5:$A$36,0)))/ABS(INDEX(目标与口径!$H$5:$H$36,MATCH("csat",目标与口径!$A$5:$A$36,0))-INDEX(目标与口径!$G$5:$G$36,MATCH("csat",目标与口径!$A$5:$A$36,0)))),0) -> 0 | H22: =INDEX(目标与口径!$J$5:$J$36,MATCH("csat",目标与口径!$A$5:$A$36,0)) -> 店长 | I22: =INDEX(目标与口径!$N$5:$N$36,MATCH("csat",目标与口径!$A$5:$A$36,0)) -> PB-05
A23: 外卖平台评分 | B23: =IFERROR(INDEX(每日经营日报!$BE$5:$BE$18,MATCH($B$3,每日经营日报!$A$5:$A$18,0)),0) -> 4.1375 | C23: =INDEX(目标与口径!$F$5:$F$36,MATCH("delivery_rating",目标与口径!$A$5:$A$36,0)) -> 4.8 | D23: =IFERROR(IF(INDEX(目标与口径!$E$5:$E$36,MATCH("delivery_rating",目标与口径!$A$5:$A$36,0))="越高越好",IF($B$23>=INDEX(目标与口径!$G$5:$G$36,MATCH("delivery_rating",目标与口径!$A$5:$A$36,0)),"绿",IF($B$23>=INDEX(目标与口径!$H$5:$H$36,MATCH("delivery_rating",目标与口径!$A$5:$A$36,0)),"黄","红")),IF($B$23<=INDEX(目标与口径!$G$5:$G$36,MATCH("delivery_rating",目标与口径!$A$5:$A$36,0)),"绿",IF($B$23<=INDEX(目标与口径!$H$5:$H$36,MATCH("delivery_rating",目标与口径!$A$5:$A$36,0)),"黄","红"))),"—") -> 红 | E23: =INDEX(目标与口径!$G$5:$G$36,MATCH("delivery_rating",目标与口径!$A$5:$A$36,0)) -> 4.7 | F23: =INDEX(目标与口径!$H$5:$H$36,MATCH("delivery_rating",目标与口径!$A$5:$A$36,0)) -> 4.5 | G23: =IFERROR(MAX(0,IF(INDEX(目标与口径!$E$5:$E$36,MATCH("delivery_rating",目标与口径!$A$5:$A$36,0))="越高越好",INDEX(目标与口径!$G$5:$G$36,MATCH("delivery_rating",目标与口径!$A$5:$A$36,0))-$B$23,$B$23-INDEX(目标与口径!$G$5:$G$36,MATCH("delivery_rating",目标与口径!$A$5:$A$36,0)))/ABS(INDEX(目标与口径!$H$5:$H$36,MATCH("delivery_rating",目标与口径!$A$5:$A$36,0))-INDEX(目标与口径!$G$5:$G$36,MATCH("delivery_rating",目标与口径!$A$5:$A$36,0)))),0) -> 2.8125 | H23: =INDEX(目标与口径!$J$5:$J$36,MATCH("delivery_rating",目标与口径!$A$5:$A$36,0)) -> 店长 | I23: =INDEX(目标与口径!$N$5:$N$36,MATCH("delivery_rating",目标与口径!$A$5:$A$36,0)) -> PB-03
A25: B. 六个家族的灯（绿 / 黄 / 红 计数）
A26: 家族 | B26: 绿 | C26: 黄 | D26: 红 | E26: 状态
A27: 生意 | B27: =COUNTIF(($D$6~$D$7~$D$8~$D$9),"绿") -> 1 | C27: =COUNTIF(($D$6~$D$7~$D$8~$D$9),"黄") -> 3 | D27: =COUNTIF(($D$6~$D$7~$D$8~$D$9),"红") -> 0 | E27: =IF(D27>0,"红",IF(C27>0,"黄","绿")) -> 黄
A28: 速度 | B28: =COUNTIF(($D$14~$D$15~$D$16),"绿") -> 2 | C28: =COUNTIF(($D$14~$D$15~$D$16),"黄") -> 0 | D28: =COUNTIF(($D$14~$D$15~$D$16),"红") -> 1 | E28: =IF(D28>0,"红",IF(C28>0,"黄","绿")) -> 红
A29: 成本 | B29: =COUNTIF(($D$10~$D$11~$D$12~$D$13),"绿") -> 2 | C29: =COUNTIF(($D$10~$D$11~$D$12~$D$13),"黄") -> 2 | D29: =COUNTIF(($D$10~$D$11~$D$12~$D$13),"红") -> 0 | E29: =IF(D29>0,"红",IF(C29>0,"黄","绿")) -> 黄
A30: 品质与食安 | B30: =COUNTIF(($D$17~$D$18~$D$19),"绿") -> 2 | C30: =COUNTIF(($D$17~$D$18~$D$19),"黄") -> 0 | D30: =COUNTIF(($D$17~$D$18~$D$19),"红") -> 1 | E30: =IF(D30>0,"红",IF(C30>0,"黄","绿")) -> 红
A31: 人员 | B31: =COUNTIF(($D$20~$D$21),"绿") -> 1 | C31: =COUNTIF(($D$20~$D$21),"黄") -> 0 | D31: =COUNTIF(($D$20~$D$21),"红") -> 1 | E31: =IF(D31>0,"红",IF(C31>0,"黄","绿")) -> 红
A32: 顾客 | B32: =COUNTIF(($D$22~$D$23),"绿") -> 1 | C32: =COUNTIF(($D$22~$D$23),"黄") -> 0 | D32: =COUNTIF(($D$22~$D$23),"红") -> 1 | E32: =IF(D32>0,"红",IF(C32>0,"黄","绿")) -> 红
A34: C. 今天的三件事（取「优先级矩阵」行动分最高的三项，公式动态排名）
A35: # | B35: 指标 | C35: 最新值 | D35: 状态 | E35: 象限 | F35: 责任人 | G35: 行动卡 | H35: 行动分 | I35: 第一动作
A36: 1 | B36: =IFERROR(INDEX(优先级矩阵!$B$5:$B$36,MATCH(LARGE(优先级矩阵!$J$5:$J$36,1),优先级矩阵!$J$5:$J$36,0)),"") -> 外卖平台评分 | C36: =IFERROR(INDEX(优先级矩阵!$C$5:$C$36,MATCH(LARGE(优先级矩阵!$J$5:$J$36,1),优先级矩阵!$J$5:$J$36,0)),"") -> 4.1375 | D36: =IFERROR(INDEX(优先级矩阵!$E$5:$E$36,MATCH(LARGE(优先级矩阵!$J$5:$J$36,1),优先级矩阵!$J$5:$J$36,0)),"") -> 红 | E36: =IFERROR(INDEX(优先级矩阵!$H$5:$H$36,MATCH(LARGE(优先级矩阵!$J$5:$J$36,1),优先级矩阵!$J$5:$J$36,0)),"") -> Q2 上报求援 | F36: =IFERROR(INDEX(优先级矩阵!$I$5:$I$36,MATCH(LARGE(优先级矩阵!$J$5:$J$36,1),优先级矩阵!$J$5:$J$36,0)),"") -> 店长 | G36: =IFERROR(INDEX(优先级矩阵!$K$5:$K$36,MATCH(LARGE(优先级矩阵!$J$5:$J$36,1),优先级矩阵!$J$5:$J$36,0)),"") -> PB-03 | H36: =IFERROR(INDEX(优先级矩阵!$J$5:$J$36,MATCH(LARGE(优先级矩阵!$J$5:$J$36,1),优先级矩阵!$J$5:$J$36,0)),"") -> 2.17 | I36: =IFERROR(INDEX(优先级矩阵!$L$5:$L$36,MATCH(LARGE(优先级矩阵!$J$5:$J$36,1),优先级矩阵!$J$5:$J$36,0)),"") -> 全时段慢=打包流程问题（上报）；只高峰慢=给外送单独留打包位
A37: 2 | B37: =IFERROR(INDEX(优先级矩阵!$B$5:$B$36,MATCH(LARGE(优先级矩阵!$J$5:$J$36,2),优先级矩阵!$J$5:$J$36,0)),"") -> 服务速度达标率 | C37: =IFERROR(INDEX(优先级矩阵!$C$5:$C$36,MATCH(LARGE(优先级矩阵!$J$5:$J$36,2),优先级矩阵!$J$5:$J$36,0)),"") -> 0.76598465 | D37: =IFERROR(INDEX(优先级矩阵!$E$5:$E$36,MATCH(LARGE(优先级矩阵!$J$5:$J$36,2),优先级矩阵!$J$5:$J$36,0)),"") -> 红 | E37: =IFERROR(INDEX(优先级矩阵!$H$5:$H$36,MATCH(LARGE(优先级矩阵!$J$5:$J$36,2),优先级矩阵!$J$5:$J$36,0)),"") -> Q1 今天就做 | F37: =IFERROR(INDEX(优先级矩阵!$I$5:$I$36,MATCH(LARGE(优先级矩阵!$J$5:$J$36,2),优先级矩阵!$J$5:$J$36,0)),"") -> 值班经理 | G37: =IFERROR(INDEX(优先级矩阵!$K$5:$K$36,MATCH(LARGE(优先级矩阵!$J$5:$J$36,2),优先级矩阵!$J$5:$J$36,0)),"") -> PB-04 | H37: =IFERROR(INDEX(优先级矩阵!$J$5:$J$36,MATCH(LARGE(优先级矩阵!$J$5:$J$36,2),优先级矩阵!$J$5:$J$36,0)),"") -> 2.06 | I37: =IFERROR(INDEX(优先级矩阵!$L$5:$L$36,MATCH(LARGE(优先级矩阵!$J$5:$J$36,2),优先级矩阵!$J$5:$J$36,0)),"") -> 先分段定位（点单/排队/取餐窗/制作），再看是结构问题还是产能问题
A38: 3 | B38: =IFERROR(INDEX(优先级矩阵!$B$5:$B$36,MATCH(LARGE(优先级矩阵!$J$5:$J$36,3),优先级矩阵!$J$5:$J$36,0)),"") -> 迟到率 | C38: =IFERROR(INDEX(优先级矩阵!$C$5:$C$36,MATCH(LARGE(优先级矩阵!$J$5:$J$36,3),优先级矩阵!$J$5:$J$36,0)),"") -> 0.10526316 | D38: =IFERROR(INDEX(优先级矩阵!$E$5:$E$36,MATCH(LARGE(优先级矩阵!$J$5:$J$36,3),优先级矩阵!$J$5:$J$36,0)),"") -> 红 | E38: =IFERROR(INDEX(优先级矩阵!$H$5:$H$36,MATCH(LARGE(优先级矩阵!$J$5:$J$36,3),优先级矩阵!$J$5:$J$36,0)),"") -> Q3 顺手做掉 | F38: =IFERROR(INDEX(优先级矩阵!$I$5:$I$36,MATCH(LARGE(优先级矩阵!$J$5:$J$36,3),优先级矩阵!$J$5:$J$36,0)),"") -> 组长 | G38: =IFERROR(INDEX(优先级矩阵!$K$5:$K$36,MATCH(LARGE(优先级矩阵!$J$5:$J$36,3),优先级矩阵!$J$5:$J$36,0)),"") -> PB-07 | H38: =IFERROR(INDEX(优先级矩阵!$J$5:$J$36,MATCH(LARGE(优先级矩阵!$J$5:$J$36,3),优先级矩阵!$J$5:$J$36,0)),"") -> 1.02 | I38: =IFERROR(INDEX(优先级矩阵!$L$5:$L$36,MATCH(LARGE(优先级矩阵!$J$5:$J$36,3),优先级矩阵!$J$5:$J$36,0)),"") -> 看 SPLH 与速度的组合：都差 = 排班结构错，调岗位不是加人头
A40: 「最新值」= 从「每日经营日报」按 B3 的日期取当天的数；「目标/绿线/黄线/责任人/行动卡」= 从「目标与口径」按指标ID 回查；「超线带宽」= 越过绿线几个黄灯带宽（(绿线−实际)÷|黄线−绿线|），用来在不同量纲的指标之间排优先级——不能用相对偏差，否则目标 2% 的迟到率会天天霸占第一。

Sheet 每日经营日报
A1: 每日经营日报 · Daily Operations Report
A2: 一行一天。浅蓝色是每天要填的原子数，白色是公式（客单价、各类比率、SPLH 等）自动计算。改任何一个浅蓝格子，右边的派生列和「店长看板」会一起更新。
A4: 日期 | B4: 星期 | C4: 销售预测 | D4: 净销售额 | E4: 交易笔数 | F4: 客单价 | G4: 销售达成率 | H4: 商品件数 | I4: 单均件数 | J4: 数字渠道占比 | K4: 外送销售额 | L4: 外送占比 | M4: 人工点单数 | N4: 附加销售单数 | O4: 附加销售率 | P4: 食品成本额 | Q4: 食品成本率 | R4: 废弃金额 | S4: 废弃率 | T4: 实际工时 | U4: 计划工时 | V4: 平均时薪 | W4: 班组计划工时 | X4: 班组实际工时 | Y4: 人工成本 | Z4: 人工成本率 | AA4: 人时销售SPLH | AB4: 工时排班偏差 | AC4: 得来速总时长 | AD4: 得来速取餐窗 | AE4: 后厨制作时长 | AF4: 前台交付OTD | AG4: 外送出餐时长 | AH4: 达标订单数 | AI4: 服务速度达标率 | AJ4: 差错事件数 | AK4: 订单准确率 | AL4: 千单投诉数 | AM4: 食安日检得分 | AN4: 关键温度异常 | AO4: 保温批次数 | AP4: 保温废弃数 | AQ4: 保温超时率 | AR4: 清洁巡检得分 | AS4: 设备停机分钟 | AT4: 排班人次 | AU4: 到岗人次 | AV4: 出勤达成率 | AW4: 迟到人次 | AX4: 迟到率 | AY4: 认证人次 | AZ4: 岗位认证覆盖率 | BA4: 30日流失率 | BB4: 调研总分 | BC4: 调研份数 | BD4: 顾客满意度 | BE4: 外卖平台评分 | BF4: 现金短溢 | BG4: 店长备注
A5: 46239 | B5: =TEXT(A5,"aaa") -> Wed | C5: 61806.75 | D5: 60215.69 | E5: 1661 | F5: =IFERROR(D5/E5,0) -> 36.252673 | G5: =IFERROR(D5/C5,0) -> 0.9742575 | H5: 5624 | I5: =IFERROR(H5/E5,0) -> 3.3859121 | J5: 0.64057797 | K5: 16257.27 | L5: =IFERROR(K5/D5,0) -> 0.26998395 | M5: 597 | N5: 143 | O5: =IFERROR(N5/M5,0) -> 0.23953099 | P5: 18573.69 | Q5: =IFERROR(P5/D5,0) -> 0.30845266 | R5: 646.87 | S5: =IFERROR(R5/D5,0) -> 0.010742549 | T5: 271.72 | U5: 282.5 | V5: 28.5 | W5: 248.5 | X5: 237.7225 | Y5: =T5*V5 -> 7744.02 | Z5: =IFERROR(Y5/D5,0) -> 0.12860469 | AA5: =IFERROR(D5/T5,0) -> 221.60934 | AB5: =IFERROR(ABS(X5-W5)/W5,0) -> 0.043370221 | AC5: 156.87 | AD5: 58.06 | AE5: 86.39 | AF5: 128.96 | AG5: 418.23 | AH5: 1259 | AI5: =IFERROR(AH5/E5,0) -> 0.75797712 | AJ5: 4 | AK5: =IFERROR(1-AJ5/E5,0) -> 0.99759181 | AL5: =IFERROR(AJ5/E5*1000,0) -> 2.4081878 | AM5: 99.333 | AN5: 0 | AO5: 2160 | AP5: 64 | AQ5: =IFERROR(AP5/AO5,0) -> 0.02962963 | AR5: 91.4 | AS5: 0 | AT5: 40 | AU5: 40 | AV5: =IFERROR(AU5/AT5,0) -> 1 | AW5: 3 | AX5: =IFERROR(AW5/AU5,0) -> 0.075 | AY5: 34 | AZ5: =IFERROR(AY5/AT5,0) -> 0.85 | BA5: 0.10769231 | BB5: 133 | BC5: 30 | BD5: =IFERROR(BB5/BC5*20,0) -> 88.666667 | BE5: 4.1332 | BF5: 37.25
A6: 46240 | B6: =TEXT(A6,"aaa") -> Thu | C6: 57823.97 | D6: 55843.81 | E6: 1565 | F6: =IFERROR(D6/E6,0) -> 35.682946 | G6: =IFERROR(D6/C6,0) -> 0.96575538 | H6: 5232 | I6: =IFERROR(H6/E6,0) -> 3.343131 | J6: 0.63258786 | K6: 14190.62 | L6: =IFERROR(K6/D6,0) -> 0.25411268 | M6: 575 | N6: 126 | O6: =IFERROR(N6/M6,0) -> 0.21913043 | P6: 17096.37 | Q6: =IFERROR(P6/D6,0) -> 0.3061462 | R6: 628.62 | S6: =IFERROR(R6/D6,0) -> 0.011256753 | T6: 260.44 | U6: 272.55 | V6: 28.5 | W6: 238.55 | X6: 226.4375 | Y6: =T6*V6 -> 7422.54 | Z6: =IFERROR(Y6/D6,0) -> 0.13291607 | AA6: =IFERROR(D6/T6,0) -> 214.42102 | AB6: =IFERROR(ABS(X6-W6)/W6,0) -> 0.050775519 | AC6: 155.6 | AD6: 58.33 | AE6: 86.49 | AF6: 128.76 | AG6: 415.58 | AH6: 1225 | AI6: =IFERROR(AH6/E6,0) -> 0.7827476 | AJ6: 3 | AK6: =IFERROR(1-AJ6/E6,0) -> 0.99808307 | AL6: =IFERROR(AJ6/E6*1000,0) -> 1.9169329 | AM6: 98 | AN6: 0 | AO6: 1995 | AP6: 46 | AQ6: =IFERROR(AP6/AO6,0) -> 0.023057644 | AR6: 91.667 | AS6: 38 | AT6: 38 | AU6: 34 | AV6: =IFERROR(AU6/AT6,0) -> 0.89473684 | AW6: 5 | AX6: =IFERROR(AW6/AU6,0) -> 0.14705882 | AY6: 37 | AZ6: =IFERROR(AY6/AT6,0) -> 0.97368421 | BA6: 0.10769231 | BB6: 154 | BC6: 35 | BD6: =IFERROR(BB6/BC6*20,0) -> 88 | BE6: 4.0907 | BF6: 34.76
A7: 46241 | B7: =TEXT(A7,"aaa") -> Fri | C7: 75744.98 | D7: 74500.09 | E7: 2067 | F7: =IFERROR(D7/E7,0) -> 36.042617 | G7: =IFERROR(D7/C7,0) -> 0.98356472 | H7: 6949 | I7: =IFERROR(H7/E7,0) -> 3.3618771 | J7: 0.63812288 | K7: 20532.42 | L7: =IFERROR(K7/D7,0) -> 0.27560262 | M7: 748 | N7: 163 | O7: =IFERROR(N7/M7,0) -> 0.21791444 | P7: 22878.77 | Q7: =IFERROR(P7/D7,0) -> 0.30709721 | R7: 797.43 | S7: =IFERROR(R7/D7,0) -> 0.010703745 | T7: 313.86 | U7: 324.85 | V7: 28.5 | W7: 290.85 | X7: 279.865 | Y7: =T7*V7 -> 8945.01 | Z7: =IFERROR(Y7/D7,0) -> 0.1200671 | AA7: =IFERROR(D7/T7,0) -> 237.36727 | AB7: =IFERROR(ABS(X7-W7)/W7,0) -> 0.037768609 | AC7: 157.68 | AD7: 58.66 | AE7: 88.07 | AF7: 132.14 | AG7: 425.23 | AH7: 1492 | AI7: =IFERROR(AH7/E7,0) -> 0.72181906 | AJ7: 2 | AK7: =IFERROR(1-AJ7/E7,0) -> 0.99903241 | AL7: =IFERROR(AJ7/E7*1000,0) -> 0.96758587 | AM7: 99.333 | AN7: 0 | AO7: 2767 | AP7: 73 | AQ7: =IFERROR(AP7/AO7,0) -> 0.026382364 | AR7: 91.533 | AS7: 0 | AT7: 47 | AU7: 46 | AV7: =IFERROR(AU7/AT7,0) -> 0.9787234 | AW7: 5 | AX7: =IFERROR(AW7/AU7,0) -> 0.10869565 | AY7: 43 | AZ7: =IFERROR(AY7/AT7,0) -> 0.91489362 | BA7: 0.092307692 | BB7: 230 | BC7: 51 | BD7: =IFERROR(BB7/BC7*20,0) -> 90.196078 | BE7: 4.0245 | BF7: 40.77
A8: 46242 | B8: =TEXT(A8,"aaa") -> Sat | C8: 82007.96 | D8: 80843.72 | E8: 2248 | F8: =IFERROR(D8/E8,0) -> 35.962509 | G8: =IFERROR(D8/C8,0) -> 0.98580333 | H8: 7533 | I8: =IFERROR(H8/E8,0) -> 3.3509786 | J8: 0.63745552 | K8: 21337.65 | L8: =IFERROR(K8/D8,0) -> 0.26393701 | M8: 815 | N8: 193 | O8: =IFERROR(N8/M8,0) -> 0.23680982 | P8: 25050.68 | Q8: =IFERROR(P8/D8,0) -> 0.3098655 | R8: 934.38 | S8: =IFERROR(R8/D8,0) -> 0.011557855 | T8: 331.65 | U8: 343.73 | V8: 28.5 | W8: 309.725 | X8: 297.645 | Y8: =T8*V8 -> 9452.025 | Z8: =IFERROR(Y8/D8,0) -> 0.11691724 | AA8: =IFERROR(D8/T8,0) -> 243.76216 | AB8: =IFERROR(ABS(X8-W8)/W8,0) -> 0.039002341 | AC8: 159.75 | AD8: 58.56 | AE8: 88.06 | AF8: 132.97 | AG8: 434.63 | AH8: 1618 | AI8: =IFERROR(AH8/E8,0) -> 0.71975089 | AJ8: 5 | AK8: =IFERROR(1-AJ8/E8,0) -> 0.9977758 | AL8: =IFERROR(AJ8/E8*1000,0) -> 2.2241993 | AM8: 98.667 | AN8: 4 | AO8: 3033 | AP8: 70 | AQ8: =IFERROR(AP8/AO8,0) -> 0.023079459 | AR8: 93.667 | AS8: 0 | AT8: 50 | AU8: 47 | AV8: =IFERROR(AU8/AT8,0) -> 0.94 | AW8: 2 | AX8: =IFERROR(AW8/AU8,0) -> 0.042553191 | AY8: 43 | AZ8: =IFERROR(AY8/AT8,0) -> 0.86 | BA8: 0.078125 | BB8: 188 | BC8: 41 | BD8: =IFERROR(BB8/BC8*20,0) -> 91.707317 | BE8: 4.0281 | BF8: 65.49
A9: 46243 | B9: =TEXT(A9,"aaa") -> Sun | C9: 72603.35 | D9: 71838.61 | E9: 1996 | F9: =IFERROR(D9/E9,0) -> 35.991288 | G9: =IFERROR(D9/C9,0) -> 0.98946688 | H9: 6719 | I9: =IFERROR(H9/E9,0) -> 3.3662325 | J9: 0.64679359 | K9: 18940.76 | L9: =IFERROR(K9/D9,0) -> 0.26365711 | M9: 705 | N9: 155 | O9: =IFERROR(N9/M9,0) -> 0.21985816 | P9: 22072.55 | Q9: =IFERROR(P9/D9,0) -> 0.30725191 | R9: 900.9 | S9: =IFERROR(R9/D9,0) -> 0.01254061 | T9: 305.96 | U9: 317.52 | V9: 28.5 | W9: 283.525 | X9: 271.955 | Y9: =T9*V9 -> 8719.86 | Z9: =IFERROR(Y9/D9,0) -> 0.12138125 | AA9: =IFERROR(D9/T9,0) -> 234.79739 | AB9: =IFERROR(ABS(X9-W9)/W9,0) -> 0.040807689 | AC9: 158.57 | AD9: 59.07 | AE9: 87.92 | AF9: 131.59 | AG9: 430.21 | AH9: 1482 | AI9: =IFERROR(AH9/E9,0) -> 0.74248497 | AJ9: 1 | AK9: =IFERROR(1-AJ9/E9,0) -> 0.999499 | AL9: =IFERROR(AJ9/E9*1000,0) -> 0.501002 | AM9: 99.333 | AN9: 0 | AO9: 2530 | AP9: 59 | AQ9: =IFERROR(AP9/AO9,0) -> 0.023320158 | AR9: 92.267 | AS9: 0 | AT9: 45 | AU9: 42 | AV9: =IFERROR(AU9/AT9,0) -> 0.93333333 | AW9: 5 | AX9: =IFERROR(AW9/AU9,0) -> 0.11904762 | AY9: 40 | AZ9: =IFERROR(AY9/AT9,0) -> 0.88888889 | BA9: 0.09375 | BB9: 187 | BC9: 42 | BD9: =IFERROR(BB9/BC9*20,0) -> 89.047619 | BE9: 4.0526 | BF9: 10.98
A10: 46244 | B10: =TEXT(A10,"aaa") -> Mon | C10: 56778.37 | D10: 56477.72 | E10: 1564 | F10: =IFERROR(D10/E10,0) -> 36.111074 | G10: =IFERROR(D10/C10,0) -> 0.99470485 | H10: 5249 | I10: =IFERROR(H10/E10,0) -> 3.3561381 | J10: 0.64641944 | K10: 15189.73 | L10: =IFERROR(K10/D10,0) -> 0.26895084 | M10: 553 | N10: 144 | O10: =IFERROR(N10/M10,0) -> 0.26039783 | P10: 17592.76 | Q10: =IFERROR(P10/D10,0) -> 0.31149912 | R10: 635.11 | S10: =IFERROR(R10/D10,0) -> 0.011245319 | T10: 261.91 | U10: 272.45 | V10: 28.5 | W10: 238.45 | X10: 227.9125 | Y10: =T10*V10 -> 7464.435 | Z10: =IFERROR(Y10/D10,0) -> 0.13216601 | AA10: =IFERROR(D10/T10,0) -> 215.63789 | AB10: =IFERROR(ABS(X10-W10)/W10,0) -> 0.044191654 | AC10: 152.63 | AD10: 56.02 | AE10: 85.39 | AF10: 126.8 | AG10: 419.83 | AH10: 1235 | AI10: =IFERROR(AH10/E10,0) -> 0.78964194 | AJ10: 0 | AK10: =IFERROR(1-AJ10/E10,0) -> 1 | AL10: =IFERROR(AJ10/E10*1000,0) -> 0 | AM10: 99.333 | AN10: 0 | AO10: 2049 | AP10: 41 | AQ10: =IFERROR(AP10/AO10,0) -> 0.020009761 | AR10: 88.667 | AS10: 0 | AT10: 38 | AU10: 35 | AV10: =IFERROR(AU10/AT10,0) -> 0.92105263 | AW10: 2 | AX10: =IFERROR(AW10/AU10,0) -> 0.057142857 | AY10: 30 | AZ10: =IFERROR(AY10/AT10,0) -> 0.78947368 | BA10: 0.063492063 | BB10: 110 | BC10: 24 | BD10: =IFERROR(BB10/BC10*20,0) -> 91.666667 | BE10: 4.1019 | BF10: 53.02
A11: 46245 | B11: =TEXT(A11,"aaa") -> Tue | C11: 55476.38 | D11: 53979.5 | E11: 1487 | F11: =IFERROR(D11/E11,0) -> 36.300941 | G11: =IFERROR(D11/C11,0) -> 0.97301771 | H11: 5009 | I11: =IFERROR(H11/E11,0) -> 3.3685272 | J11: 0.63483524 | K11: 14907.81 | L11: =IFERROR(K11/D11,0) -> 0.2761754 | M11: 543 | N11: 119 | O11: =IFERROR(N11/M11,0) -> 0.21915285 | P11: 16622.76 | Q11: =IFERROR(P11/D11,0) -> 0.30794579 | R11: 666.07 | S11: =IFERROR(R11/D11,0) -> 0.012339314 | T11: 252.77 | U11: 264.42 | V11: 28.5 | W11: 230.425 | X11: 218.7725 | Y11: =T11*V11 -> 7203.945 | Z11: =IFERROR(Y11/D11,0) -> 0.13345705 | AA11: =IFERROR(D11/T11,0) -> 213.55185 | AB11: =IFERROR(ABS(X11-W11)/W11,0) -> 0.0505696 | AC11: 153.37 | AD11: 56.68 | AE11: 85.31 | AF11: 127.24 | AG11: 413.62 | AH11: 1188 | AI11: =IFERROR(AH11/E11,0) -> 0.79892401 | AJ11: 2 | AK11: =IFERROR(1-AJ11/E11,0) -> 0.99865501 | AL11: =IFERROR(AJ11/E11*1000,0) -> 1.3449899 | AM11: 96.667 | AN11: 1 | AO11: 1808 | AP11: 43 | AQ11: =IFERROR(AP11/AO11,0) -> 0.023783186 | AR11: 94 | AS11: 0 | AT11: 36 | AU11: 36 | AV11: =IFERROR(AU11/AT11,0) -> 1 | AW11: 2 | AX11: =IFERROR(AW11/AU11,0) -> 0.055555556 | AY11: 33 | AZ11: =IFERROR(AY11/AT11,0) -> 0.91666667 | BA11: 0.063492063 | BB11: 170 | BC11: 38 | BD11: =IFERROR(BB11/BC11*20,0) -> 89.473684 | BE11: 4.1638 | BF11: 28.59
A12: 46246 | B12: =TEXT(A12,"aaa") -> Wed | C12: 57815.1 | D12: 57173.74 | E12: 1588 | F12: =IFERROR(D12/E12,0) -> 36.003615 | G12: =IFERROR(D12/C12,0) -> 0.9889067 | H12: 5323 | I12: =IFERROR(H12/E12,0) -> 3.3520151 | J12: 0.63287154 | K12: 15265.07 | L12: =IFERROR(K12/D12,0) -> 0.26699443 | M12: 583 | N12: 147 | O12: =IFERROR(N12/M12,0) -> 0.25214408 | P12: 17764.16 | Q12: =IFERROR(P12/D12,0) -> 0.31070488 | R12: 694.55 | S12: =IFERROR(R12/D12,0) -> 0.01214806 | T12: 264.38 | U12: 274.92 | V12: 28.5 | W12: 240.925 | X12: 230.3825 | Y12: =T12*V12 -> 7534.83 | Z12: =IFERROR(Y12/D12,0) -> 0.1317883 | AA12: =IFERROR(D12/T12,0) -> 216.25592 | AB12: =IFERROR(ABS(X12-W12)/W12,0) -> 0.043758431 | AC12: 154.07 | AD12: 57.08 | AE12: 86.31 | AF12: 129.92 | AG12: 412.56 | AH12: 1245 | AI12: =IFERROR(AH12/E12,0) -> 0.78400504 | AJ12: 2 | AK12: =IFERROR(1-AJ12/E12,0) -> 0.99874055 | AL12: =IFERROR(AJ12/E12*1000,0) -> 1.2594458 | AM12: 98 | AN12: 0 | AO12: 1992 | AP12: 46 | AQ12: =IFERROR(AP12/AO12,0) -> 0.023092369 | AR12: 90.333 | AS12: 0 | AT12: 38 | AU12: 34 | AV12: =IFERROR(AU12/AT12,0) -> 0.89473684 | AW12: 2 | AX12: =IFERROR(AW12/AU12,0) -> 0.058823529 | AY12: 35 | AZ12: =IFERROR(AY12/AT12,0) -> 0.92105263 | BA12: 0.048387097 | BB12: 184 | BC12: 41 | BD12: =IFERROR(BB12/BC12*20,0) -> 89.756098 | BE12: 4.1731 | BF12: 40.52
A13: 46247 | B13: =TEXT(A13,"aaa") -> Thu | C13: 59225.78 | D13: 57041.08 | E13: 1593 | F13: =IFERROR(D13/E13,0) -> 35.807332 | G13: =IFERROR(D13/C13,0) -> 0.96311235 | H13: 5312 | I13: =IFERROR(H13/E13,0) -> 3.3345888 | J13: 0.64030132 | K13: 14864.39 | L13: =IFERROR(K13/D13,0) -> 0.26059096 | M13: 573 | N13: 134 | O13: =IFERROR(N13/M13,0) -> 0.23385689 | P13: 17694.54 | Q13: =IFERROR(P13/D13,0) -> 0.31020696 | R13: 685.45 | S13: =IFERROR(R13/D13,0) -> 0.012016778 | T13: 264.17 | U13: 275.45 | V13: 28.5 | W13: 241.45 | X13: 230.1675 | Y13: =T13*V13 -> 7528.845 | Z13: =IFERROR(Y13/D13,0) -> 0.13198987 | AA13: =IFERROR(D13/T13,0) -> 215.92565 | AB13: =IFERROR(ABS(X13-W13)/W13,0) -> 0.046728101 | AC13: 155.89 | AD13: 58.35 | AE13: 86.28 | AF13: 128.93 | AG13: 414.87 | AH13: 1234 | AI13: =IFERROR(AH13/E13,0) -> 0.77463905 | AJ13: 1 | AK13: =IFERROR(1-AJ13/E13,0) -> 0.99937225 | AL13: =IFERROR(AJ13/E13*1000,0) -> 0.62774639 | AM13: 98.667 | AN13: 0 | AO13: 1933 | AP13: 54 | AQ13: =IFERROR(AP13/AO13,0) -> 0.027935851 | AR13: 93.267 | AS13: 0 | AT13: 38 | AU13: 37 | AV13: =IFERROR(AU13/AT13,0) -> 0.97368421 | AW13: 3 | AX13: =IFERROR(AW13/AU13,0) -> 0.081081081 | AY13: 34 | AZ13: =IFERROR(AY13/AT13,0) -> 0.89473684 | BA13: 0.048387097 | BB13: 168 | BC13: 37 | BD13: =IFERROR(BB13/BC13*20,0) -> 90.810811 | BE13: 4.2575 | BF13: 17.96
A14: 46248 | B14: =TEXT(A14,"aaa") -> Fri | C14: 70765.05 | D14: 68068.84 | E14: 1922 | F14: =IFERROR(D14/E14,0) -> 35.41563 | G14: =IFERROR(D14/C14,0) -> 0.96189913 | H14: 6386 | I14: =IFERROR(H14/E14,0) -> 3.3225806 | J14: 0.62278876 | K14: 17581.81 | L14: =IFERROR(K14/D14,0) -> 0.25829454 | M14: 725 | N14: 157 | O14: =IFERROR(N14/M14,0) -> 0.21655172 | P14: 21122.82 | Q14: =IFERROR(P14/D14,0) -> 0.31031556 | R14: 788.28 | S14: =IFERROR(R14/D14,0) -> 0.011580629 | T14: 300.13 | U14: 309.77 | V14: 28.5 | W14: 275.775 | X14: 266.1325 | Y14: =T14*V14 -> 8553.705 | Z14: =IFERROR(Y14/D14,0) -> 0.12566256 | AA14: =IFERROR(D14/T14,0) -> 226.79785 | AB14: =IFERROR(ABS(X14-W14)/W14,0) -> 0.034965098 | AC14: 155.69 | AD14: 57.58 | AE14: 86.94 | AF14: 130.29 | AG14: 421.83 | AH14: 1472 | AI14: =IFERROR(AH14/E14,0) -> 0.76586889 | AJ14: 5 | AK14: =IFERROR(1-AJ14/E14,0) -> 0.99739854 | AL14: =IFERROR(AJ14/E14*1000,0) -> 2.6014568 | AM14: 98.667 | AN14: 5 | AO14: 2479 | AP14: 74 | AQ14: =IFERROR(AP14/AO14,0) -> 0.029850746 | AR14: 91.667 | AS14: 0 | AT14: 44 | AU14: 44 | AV14: =IFERROR(AU14/AT14,0) -> 1 | AW14: 0 | AX14: =IFERROR(AW14/AU14,0) -> 0 | AY14: 38 | AZ14: =IFERROR(AY14/AT14,0) -> 0.86363636 | BA14: 0.048387097 | BB14: 186 | BC14: 42 | BD14: =IFERROR(BB14/BC14*20,0) -> 88.571429 | BE14: 4.0874 | BF14: 38.21
A15: 46249 | B15: =TEXT(A15,"aaa") -> Sat | C15: 75705.5 | D15: 76512.05 | E15: 2125 | F15: =IFERROR(D15/E15,0) -> 36.005671 | G15: =IFERROR(D15/C15,0) -> 1.0106538 | H15: 7122 | I15: =IFERROR(H15/E15,0) -> 3.3515294 | J15: 0.64564706 | K15: 20624.22 | L15: =IFERROR(K15/D15,0) -> 0.26955519 | M15: 753 | N15: 174 | O15: =IFERROR(N15/M15,0) -> 0.2310757 | P15: 23981.49 | Q15: =IFERROR(P15/D15,0) -> 0.31343416 | R15: 916.96 | S15: =IFERROR(R15/D15,0) -> 0.011984517 | T15: 319.66 | U15: 330.95 | V15: 28.5 | W15: 296.95 | X15: 285.6575 | Y15: =T15*V15 -> 9110.31 | Z15: =IFERROR(Y15/D15,0) -> 0.11907026 | AA15: =IFERROR(D15/T15,0) -> 239.35447 | AB15: =IFERROR(ABS(X15-W15)/W15,0) -> 0.038028288 | AC15: 158.02 | AD15: 58.32 | AE15: 88.18 | AF15: 131.69 | AG15: 434.35 | AH15: 1561 | AI15: =IFERROR(AH15/E15,0) -> 0.73458824 | AJ15: 3 | AK15: =IFERROR(1-AJ15/E15,0) -> 0.99858824 | AL15: =IFERROR(AJ15/E15*1000,0) -> 1.4117647 | AM15: 98.667 | AN15: 0 | AO15: 2685 | AP15: 76 | AQ15: =IFERROR(AP15/AO15,0) -> 0.0283054 | AR15: 91.533 | AS15: 0 | AT15: 48 | AU15: 45 | AV15: =IFERROR(AU15/AT15,0) -> 0.9375 | AW15: 4 | AX15: =IFERROR(AW15/AU15,0) -> 0.088888889 | AY15: 43 | AZ15: =IFERROR(AY15/AT15,0) -> 0.89583333 | BA15: 0.048387097 | BB15: 205 | BC15: 46 | BD15: =IFERROR(BB15/BC15*20,0) -> 89.130435 | BE15: 3.992 | BF15: 64.05
A16: 46250 | B16: =TEXT(A16,"aaa") -> Sun | C16: 71075.89 | D16: 68620.32 | E16: 1921 | F16: =IFERROR(D16/E16,0) -> 35.721145 | G16: =IFERROR(D16/C16,0) -> 0.96545144 | H16: 6402 | I16: =IFERROR(H16/E16,0) -> 3.3326393 | J16: 0.62363352 | K16: 18891.16 | L16: =IFERROR(K16/D16,0) -> 0.27529979 | M16: 723 | N16: 171 | O16: =IFERROR(N16/M16,0) -> 0.23651452 | P16: 21019.54 | Q16: =IFERROR(P16/D16,0) -> 0.30631655 | R16: 828.77 | S16: =IFERROR(R16/D16,0) -> 0.012077618 | T16: 298.75 | U16: 309.67 | V16: 28.5 | W16: 275.675 | X16: 264.7525 | Y16: =T16*V16 -> 8514.375 | Z16: =IFERROR(Y16/D16,0) -> 0.1240795 | AA16: =IFERROR(D16/T16,0) -> 229.69145 | AB16: =IFERROR(ABS(X16-W16)/W16,0) -> 0.03962093 | AC16: 159.01 | AD16: 58.19 | AE16: 86.79 | AF16: 130.02 | AG16: 424.74 | AH16: 1425 | AI16: =IFERROR(AH16/E16,0) -> 0.74180115 | AJ16: 2 | AK16: =IFERROR(1-AJ16/E16,0) -> 0.99895888 | AL16: =IFERROR(AJ16/E16*1000,0) -> 1.0411244 | AM16: 100 | AN16: 1 | AO16: 2454 | AP16: 65 | AQ16: =IFERROR(AP16/AO16,0) -> 0.026487368 | AR16: 89.667 | AS16: 0 | AT16: 44 | AU16: 44 | AV16: =IFERROR(AU16/AT16,0) -> 1 | AW16: 1 | AX16: =IFERROR(AW16/AU16,0) -> 0.022727273 | AY16: 38 | AZ16: =IFERROR(AY16/AT16,0) -> 0.86363636 | BA16: 0.048387097 | BB16: 168 | BC16: 36 | BD16: =IFERROR(BB16/BC16*20,0) -> 93.333333 | BE16: 4.0067 | BF16: 27.32
... A18: 46252 | B18: =TEXT(A18,"aaa") -> Tue | C18: 57207.16 | D18: 55987.74 | E18: 1564 | F18: =IFERROR(D18/E18,0) -> 35.797788 | G18: =IFERROR(D18/C18,0) -> 0.97868414 | H18: 5221 | I18: =IFERROR(H18/E18,0) -> 3.3382353 | J18: 0.62723785 | K18: 14893.8 | L18: =IFERROR(K18/D18,0) -> 0.26601895 | M18: 583 | N18: 143 | O18: =IFERROR(N18/M18,0) -> 0.24528302 | P18: 17479.01 | Q18: =IFERROR(P18/D18,0) -> 0.31219353 | R18: 616.51 | S18: =IFERROR(R18/D18,0) -> 0.011011518 | T18: 260.23 | U18: 272.45 | V18: 28.5 | W18: 238.45 | X18: 226.2325 | Y18: =T18*V18 -> 7416.555 | Z18: =IFERROR(Y18/D18,0) -> 0.13246748 | AA18: =IFERROR(D18/T18,0) -> 215.14714 | AB18: =IFERROR(ABS(X18-W18)/W18,0) -> 0.051237157 | AC18: 158.34 | AD18: 58.36 | AE18: 86.24 | AF18: 129.08 | AG18: 416.28 | AH18: 1198 | AI18: =IFERROR(AH18/E18,0) -> 0.76598465 | AJ18: 1 | AK18: =IFERROR(1-AJ18/E18,0) -> 0.99936061 | AL18: =IFERROR(AJ18/E18*1000,0) -> 0.63938619 | AM18: 100 | AN18: 0 | AO18: 1902 | AP18: 49 | AQ18: =IFERROR(AP18/AO18,0) -> 0.025762355 | AR18: 91.867 | AS18: 76 | AT18: 38 | AU18: 38 | AV18: =IFERROR(AU18/AT18,0) -> 1 | AW18: 4 | AX18: =IFERROR(AW18/AU18,0) -> 0.10526316 | AY18: 34 | AZ18: =IFERROR(AY18/AT18,0) -> 0.89473684 | BA18: 0.047619048 | BB18: 162 | BC18: 35 | BD18: =IFERROR(BB18/BC18*20,0) -> 92.571429 | BE18: 4.1375 | BF18: 8.5
A20: 浅蓝 = 每天填的原子数（来自 POS / KDS / 得来速计时 / 排班考勤 / 废弃登记 / 食安检查 / 顾客调研）。白色 = 公式，勿改。条件格式里的红线为示例硬编码值，与「目标与口径」保持一致时才准确——改了阈值请同步这里的条件格式，或直接看「店长看板」的状态列（那里是回查公式，永远准）。

Sheet 优先级矩阵
A1: 优先级矩阵 · Priority Matrix（影响度 × 可控度）
A2: 行动分 = 超线带宽 × 影响度 × 可控度 ×（红灯 2 倍）。全部是公式：改「目标与口径」的阈值或影响度/可控度，这里的分数和象限会一起变。
A4: 指标ID | B4: 指标 | C4: 最新值 | D4: 目标 | E4: 状态 | F4: 影响度 | G4: 可控度 | H4: 象限 | I4: 责任人 | J4: 行动分 | K4: 行动卡 | L4: 第一动作 | M4: 排名
A5: delivery_rating | B5: 外卖平台评分 | C5: =IFERROR(INDEX(每日经营日报!$BE$5:$BE$18,MATCH(店长看板!$B$3,每日经营日报!$A$5:$A$18,0)),0) -> 4.1375 | D5: =INDEX(目标与口径!$F$5:$F$36,MATCH("delivery_rating",目标与口径!$A$5:$A$36,0)) -> 4.8 | E5: =IFERROR(IF(INDEX(目标与口径!$E$5:$E$36,MATCH("delivery_rating",目标与口径!$A$5:$A$36,0))="越高越好",IF($C$5>=INDEX(目标与口径!$G$5:$G$36,MATCH("delivery_rating",目标与口径!$A$5:$A$36,0)),"绿",IF($C$5>=INDEX(目标与口径!$H$5:$H$36,MATCH("delivery_rating",目标与口径!$A$5:$A$36,0)),"黄","红")),IF($C$5<=INDEX(目标与口径!$G$5:$G$36,MATCH("delivery_rating",目标与口径!$A$5:$A$36,0)),"绿",IF($C$5<=INDEX(目标与口径!$H$5:$H$36,MATCH("delivery_rating",目标与口径!$A$5:$A$36,0)),"黄","红"))),"—") -> 红 | F5: =INDEX(目标与口径!$L$5:$L$36,MATCH("delivery_rating",目标与口径!$A$5:$A$36,0)) -> 0.7 | G5: =INDEX(目标与口径!$M$5:$M$36,MATCH("delivery_rating",目标与口径!$A$5:$A$36,0)) -> 0.55 | H5: =IF($F$5>=0.7,IF($G$5>=0.7,"Q1 今天就做","Q2 上报求援"),IF($G$5>=0.7,"Q3 顺手做掉","Q4 记录观察")) -> Q2 上报求援 | I5: =INDEX(目标与口径!$J$5:$J$36,MATCH("delivery_rating",目标与口径!$A$5:$A$36,0)) -> 店长 | J5: =IFERROR(ROUND(IFERROR(MAX(0,IF(INDEX(目标与口径!$E$5:$E$36,MATCH("delivery_rating",目标与口径!$A$5:$A$36,0))="越高越好",INDEX(目标与口径!$G$5:$G$36,MATCH("delivery_rating",目标与口径!$A$5:$A$36,0))-$C$5,$C$5-INDEX(目标与口径!$G$5:$G$36,MATCH("delivery_rating",目标与口径!$A$5:$A$36,0)))/ABS(INDEX(目标与口径!$H$5:$H$36,MATCH("delivery_rating",目标与口径!$A$5:$A$36,0))-INDEX(目标与口径!$G$5:$G$36,MATCH("delivery_rating",目标与口径!$A$5:$A$36,0)))),0)*$F$5*$G$5*IF($E$5="红",2,1),2),0) -> 2.17 | K5: =INDEX(目标与口径!$N$5:$N$36,MATCH("delivery_rating",目标与口径!$A$5:$A$36,0)) -> PB-03 | L5: 全时段慢=打包流程问题（上报）；只高峰慢=给外送单独留打包位 | M5: =RANK($J$5,$J$5:$J$36,0) -> 1
A6: speed_hit_rate | B6: 服务速度达标率 | C6: =IFERROR(INDEX(每日经营日报!$AI$5:$AI$18,MATCH(店长看板!$B$3,每日经营日报!$A$5:$A$18,0)),0) -> 0.76598465 | D6: =INDEX(目标与口径!$F$5:$F$36,MATCH("speed_hit_rate",目标与口径!$A$5:$A$36,0)) -> 0.9 | E6: =IFERROR(IF(INDEX(目标与口径!$E$5:$E$36,MATCH("speed_hit_rate",目标与口径!$A$5:$A$36,0))="越高越好",IF($C$6>=INDEX(目标与口径!$G$5:$G$36,MATCH("speed_hit_rate",目标与口径!$A$5:$A$36,0)),"绿",IF($C$6>=INDEX(目标与口径!$H$5:$H$36,MATCH("speed_hit_rate",目标与口径!$A$5:$A$36,0)),"黄","红")),IF($C$6<=INDEX(目标与口径!$G$5:$G$36,MATCH("speed_hit_rate",目标与口径!$A$5:$A$36,0)),"绿",IF($C$6<=INDEX(目标与口径!$H$5:$H$36,MATCH("speed_hit_rate",目标与口径!$A$5:$A$36,0)),"黄","红"))),"—") -> 红 | F6: =INDEX(目标与口径!$L$5:$L$36,MATCH("speed_hit_rate",目标与口径!$A$5:$A$36,0)) -> 0.85 | G6: =INDEX(目标与口径!$M$5:$M$36,MATCH("speed_hit_rate",目标与口径!$A$5:$A$36,0)) -> 0.85 | H6: =IF($F$6>=0.7,IF($G$6>=0.7,"Q1 今天就做","Q2 上报求援"),IF($G$6>=0.7,"Q3 顺手做掉","Q4 记录观察")) -> Q1 今天就做 | I6: =INDEX(目标与口径!$J$5:$J$36,MATCH("speed_hit_rate",目标与口径!$A$5:$A$36,0)) -> 值班经理 | J6: =IFERROR(ROUND(IFERROR(MAX(0,IF(INDEX(目标与口径!$E$5:$E$36,MATCH("speed_hit_rate",目标与口径!$A$5:$A$36,0))="越高越好",INDEX(目标与口径!$G$5:$G$36,MATCH("speed_hit_rate",目标与口径!$A$5:$A$36,0))-$C$6,$C$6-INDEX(目标与口径!$G$5:$G$36,MATCH("speed_hit_rate",目标与口径!$A$5:$A$36,0)))/ABS(INDEX(目标与口径!$H$5:$H$36,MATCH("speed_hit_rate",目标与口径!$A$5:$A$36,0))-INDEX(目标与口径!$G$5:$G$36,MATCH("speed_hit_rate",目标与口径!$A$5:$A$36,0)))),0)*$F$6*$G$6*IF($E$6="红",2,1),2),0) -> 2.06 | K6: =INDEX(目标与口径!$N$5:$N$36,MATCH("speed_hit_rate",目标与口径!$A$5:$A$36,0)) -> PB-04 | L6: 先分段定位（点单/排队/取餐窗/制作），再看是结构问题还是产能问题 | M6: =RANK($J$6,$J$5:$J$36,0) -> 2
A7: late_rate | B7: 迟到率 | C7: =IFERROR(INDEX(每日经营日报!$AX$5:$AX$18,MATCH(店长看板!$B$3,每日经营日报!$A$5:$A$18,0)),0) -> 0.10526316 | D7: =INDEX(目标与口径!$F$5:$F$36,MATCH("late_rate",目标与口径!$A$5:$A$36,0)) -> 0.02 | E7: =IFERROR(IF(INDEX(目标与口径!$E$5:$E$36,MATCH("late_rate",目标与口径!$A$5:$A$36,0))="越高越好",IF($C$7>=INDEX(目标与口径!$G$5:$G$36,MATCH("late_rate",目标与口径!$A$5:$A$36,0)),"绿",IF($C$7>=INDEX(目标与口径!$H$5:$H$36,MATCH("late_rate",目标与口径!$A$5:$A$36,0)),"黄","红")),IF($C$7<=INDEX(目标与口径!$G$5:$G$36,MATCH("late_rate",目标与口径!$A$5:$A$36,0)),"绿",IF($C$7<=INDEX(目标与口径!$H$5:$H$36,MATCH("late_rate",目标与口径!$A$5:$A$36,0)),"黄","红"))),"—") -> 红 | F7: =INDEX(目标与口径!$L$5:$L$36,MATCH("late_rate",目标与口径!$A$5:$A$36,0)) -> 0.4 | G7: =INDEX(目标与口径!$M$5:$M$36,MATCH("late_rate",目标与口径!$A$5:$A$36,0)) -> 0.85 | H7: =IF($F$7>=0.7,IF($G$7>=0.7,"Q1 今天就做","Q2 上报求援"),IF($G$7>=0.7,"Q3 顺手做掉","Q4 记录观察")) -> Q3 顺手做掉 | I7: =INDEX(目标与口径!$J$5:$J$36,MATCH("late_rate",目标与口径!$A$5:$A$36,0)) -> 组长 | J7: =IFERROR(ROUND(IFERROR(MAX(0,IF(INDEX(目标与口径!$E$5:$E$36,MATCH("late_rate",目标与口径!$A$5:$A$36,0))="越高越好",INDEX(目标与口径!$G$5:$G$36,MATCH("late_rate",目标与口径!$A$5:$A$36,0))-$C$7,$C$7-INDEX(目标与口径!$G$5:$G$36,MATCH("late_rate",目标与口径!$A$5:$A$36,0)))/ABS(INDEX(目标与口径!$H$5:$H$36,MATCH("late_rate",目标与口径!$A$5:$A$36,0))-INDEX(目标与口径!$G$5:$G$36,MATCH("late_rate",目标与口径!$A$5:$A$36,0)))),0)*$F$7*$G$7*IF($E$7="红",2,1),2),0) -> 1.02 | K7: =INDEX(目标与口径!$N$5:$N$36,MATCH("late_rate",目标与口径!$A$5:$A$36,0)) -> PB-07 | L7: 看 SPLH 与速度的组合：都差 = 排班结构错，调岗位不是加人头 | M7: =RANK($J$7,$J$5:$J$36,0) -> 3
A8: equipment_downtime | B8: 设备停机时长 | C8: =IFERROR(INDEX(每日经营日报!$AS$5:$AS$18,MATCH(店长看板!$B$3,每日经营日报!$A$5:$A$18,0)),0) -> 76 | D8: =INDEX(目标与口径!$F$5:$F$36,MATCH("equipment_downtime",目标与口径!$A$5:$A$36,0)) -> 0 | E8: =IFERROR(IF(INDEX(目标与口径!$E$5:$E$36,MATCH("equipment_downtime",目标与口径!$A$5:$A$36,0))="越高越好",IF($C$8>=INDEX(目标与口径!$G$5:$G$36,MATCH("equipment_downtime",目标与口径!$A$5:$A$36,0)),"绿",IF($C$8>=INDEX(目标与口径!$H$5:$H$36,MATCH("equipment_downtime",目标与口径!$A$5:$A$36,0)),"黄","红")),IF($C$8<=INDEX(目标与口径!$G$5:$G$36,MATCH("equipment_downtime",目标与口径!$A$5:$A$36,0)),"绿",IF($C$8<=INDEX(目标与口径!$H$5:$H$36,MATCH("equipment_downtime",目标与口径!$A$5:$A$36,0)),"黄","红"))),"—") -> 红 | F8: =INDEX(目标与口径!$L$5:$L$36,MATCH("equipment_downtime",目标与口径!$A$5:$A$36,0)) -> 0.7 | G8: =INDEX(目标与口径!$M$5:$M$36,MATCH("equipment_downtime",目标与口径!$A$5:$A$36,0)) -> 0.5 | H8: =IF($F$8>=0.7,IF($G$8>=0.7,"Q1 今天就做","Q2 上报求援"),IF($G$8>=0.7,"Q3 顺手做掉","Q4 记录观察")) -> Q2 上报求援 | I8: =INDEX(目标与口径!$J$5:$J$36,MATCH("equipment_downtime",目标与口径!$A$5:$A$36,0)) -> 店长 | J8: =IFERROR(ROUND(IFERROR(MAX(0,IF(INDEX(目标与口径!$E$5:$E$36,MATCH("equipment_downtime",目标与口径!$A$5:$A$36,0))="越高越好",INDEX(目标与口径!$G$5:$G$36,MATCH("equipment_downtime",目标与口径!$A$5:$A$36,0))-$C$8,$C$8-INDEX(目标与口径!$G$5:$G$36,MATCH("equipment_downtime",目标与口径!$A$5:$A$36,0)))/ABS(INDEX(目标与口径!$H$5:$H$36,MATCH("equipment_downtime",目标与口径!$A$5:$A$36,0))-INDEX(目标与口径!$G$5:$G$36,MATCH("equipment_downtime",目标与口径!$A$5:$A$36,0)))),0)*$F$8*$G$8*IF($E$8="红",2,1),2),0) -> 0.95 | K8: =INDEX(目标与口径!$N$5:$N$36,MATCH("equipment_downtime",目标与口径!$A$5:$A$36,0)) -> PB-11 | L8: 先决定是否停售并同步到所有点单渠道（含外送平台），再报修 | M8: =RANK($J$8,$J$5:$J$36,0) -> 4
A9: labor_schedule_variance | B9: 工时排班偏差 | C9: =IFERROR(INDEX(每日经营日报!$AB$5:$AB$18,MATCH(店长看板!$B$3,每日经营日报!$A$5:$A$18,0)),0) -> 0.051237157 | D9: =INDEX(目标与口径!$F$5:$F$36,MATCH("labor_schedule_variance",目标与口径!$A$5:$A$36,0)) -> 0.02 | E9: =IFERROR(IF(INDEX(目标与口径!$E$5:$E$36,MATCH("labor_schedule_variance",目标与口径!$A$5:$A$36,0))="越高越好",IF($C$9>=INDEX(目标与口径!$G$5:$G$36,MATCH("labor_schedule_variance",目标与口径!$A$5:$A$36,0)),"绿",IF($C$9>=INDEX(目标与口径!$H$5:$H$36,MATCH("labor_schedule_variance",目标与口径!$A$5:$A$36,0)),"黄","红")),IF($C$9<=INDEX(目标与口径!$G$5:$G$36,MATCH("labor_schedule_variance",目标与口径!$A$5:$A$36,0)),"绿",IF($C$9<=INDEX(目标与口径!$H$5:$H$36,MATCH("labor_schedule_variance",目标与口径!$A$5:$A$36,0)),"黄","红"))),"—") -> 黄 | F9: =INDEX(目标与口径!$L$5:$L$36,MATCH("labor_schedule_variance",目标与口径!$A$5:$A$36,0)) -> 0.6 | G9: =INDEX(目标与口径!$M$5:$M$36,MATCH("labor_schedule_variance",目标与口径!$A$5:$A$36,0)) -> 0.95 | H9: =IF($F$9>=0.7,IF($G$9>=0.7,"Q1 今天就做","Q2 上报求援"),IF($G$9>=0.7,"Q3 顺手做掉","Q4 记录观察")) -> Q3 顺手做掉 | I9: =INDEX(目标与口径!$J$5:$J$36,MATCH("labor_schedule_variance",目标与口径!$A$5:$A$36,0)) -> 值班经理 | J9: =IFERROR(ROUND(IFERROR(MAX(0,IF(INDEX(目标与口径!$E$5:$E$36,MATCH("labor_schedule_variance",目标与口径!$A$5:$A$36,0))="越高越好",INDEX(目标与口径!$G$5:$G$36,MATCH("labor_schedule_variance",目标与口径!$A$5:$A$36,0))-$C$9,$C$9-INDEX(目标与口径!$G$5:$G$36,MATCH("labor_schedule_variance",目标与口径!$A$5:$A$36,0)))/ABS(INDEX(目标与口径!$H$5:$H$36,MATCH("labor_schedule_variance",目标与口径!$A$5:$A$36,0))-INDEX(目标与口径!$G$5:$G$36,MATCH("labor_schedule_variance",目标与口径!$A$5:$A$36,0)))),0)*$F$9*$G$9*IF($E$9="红",2,1),2),0) -> 0.4 | K9: =INDEX(目标与口径!$N$5:$N$36,MATCH("labor_schedule_variance",目标与口径!$A$5:$A$36,0)) -> PB-07 | L9: 看 SPLH 与速度的组合：都差 = 排班结构错，调岗位不是加人头 | M9: =RANK($J$9,$J$5:$J$36,0) -> 5
A10: upsell_rate | B10: 附加销售率 | C10: =IFERROR(INDEX(每日经营日报!$O$5:$O$18,MATCH(店长看板!$B$3,每日经营日报!$A$5:$A$18,0)),0) -> 0.24528302 | D10: =INDEX(目标与口径!$F$5:$F$36,MATCH("upsell_rate",目标与口径!$A$5:$A$36,0)) -> 0.3 | E10: =IFERROR(IF(INDEX(目标与口径!$E$5:$E$36,MATCH("upsell_rate",目标与口径!$A$5:$A$36,0))="越高越好",IF($C$10>=INDEX(目标与口径!$G$5:$G$36,MATCH("upsell_rate",目标与口径!$A$5:$A$36,0)),"绿",IF($C$10>=INDEX(目标与口径!$H$5:$H$36,MATCH("upsell_rate",目标与口径!$A$5:$A$36,0)),"黄","红")),IF($C$10<=INDEX(目标与口径!$G$5:$G$36,MATCH("upsell_rate",目标与口径!$A$5:$A$36,0)),"绿",IF($C$10<=INDEX(目标与口径!$H$5:$H$36,MATCH("upsell_rate",目标与口径!$A$5:$A$36,0)),"黄","红"))),"—") -> 黄 | F10: =INDEX(目标与口径!$L$5:$L$36,MATCH("upsell_rate",目标与口径!$A$5:$A$36,0)) -> 0.55 | G10: =INDEX(目标与口径!$M$5:$M$36,MATCH("upsell_rate",目标与口径!$A$5:$A$36,0)) -> 0.9 | H10: =IF($F$10>=0.7,IF($G$10>=0.7,"Q1 今天就做","Q2 上报求援"),IF($G$10>=0.7,"Q3 顺手做掉","Q4 记录观察")) -> Q3 顺手做掉 | I10: =INDEX(目标与口径!$J$5:$J$36,MATCH("upsell_rate",目标与口径!$A$5:$A$36,0)) -> 组长 | J10: =IFERROR(ROUND(IFERROR(MAX(0,IF(INDEX(目标与口径!$E$5:$E$36,MATCH("upsell_rate",目标与口径!$A$5:$A$36,0))="越高越好",INDEX(目标与口径!$G$5:$G$36,MATCH("upsell_rate",目标与口径!$A$5:$A$36,0))-$C$10,$C$10-INDEX(目标与口径!$G$5:$G$36,MATCH("upsell_rate",目标与口径!$A$5:$A$36,0)))/ABS(INDEX(目标与口径!$H$5:$H$36,MATCH("upsell_rate",目标与口径!$A$5:$A$36,0))-INDEX(目标与口径!$G$5:$G$36,MATCH("upsell_rate",目标与口径!$A$5:$A$36,0)))),0)*$F$10*$G$10*IF($E$10="红",2,1),2),0) -> 0.29 | K10: =INDEX(目标与口径!$N$5:$N$36,MATCH("upsell_rate",目标与口径!$A$5:$A$36,0)) -> PB-02 | L10: 拉附加销售率 × 收银员，训练员跟班 2 小时；只主推 1 个品 | M10: =RANK($J$10,$J$5:$J$36,0) -> 6
A11: holding_time_violation | B11: 保温超时率 | C11: =IFERROR(INDEX(每日经营日报!$AQ$5:$AQ$18,MATCH(店长看板!$B$3,每日经营日报!$A$5:$A$18,0)),0) -> 0.025762355 | D11: =INDEX(目标与口径!$F$5:$F$36,MATCH("holding_time_violation",目标与口径!$A$5:$A$36,0)) -> 0.01 | E11: =IFERROR(IF(INDEX(目标与口径!$E$5:$E$36,MATCH("holding_time_violation",目标与口径!$A$5:$A$36,0))="越高越好",IF($C$11>=INDEX(目标与口径!$G$5:$G$36,MATCH("holding_time_violation",目标与口径!$A$5:$A$36,0)),"绿",IF($C$11>=INDEX(目标与口径!$H$5:$H$36,MATCH("holding_time_violation",目标与口径!$A$5:$A$36,0)),"黄","红")),IF($C$11<=INDEX(目标与口径!$G$5:$G$36,MATCH("holding_time_violation",目标与口径!$A$5:$A$36,0)),"绿",IF($C$11<=INDEX(目标与口径!$H$5:$H$36,MATCH("holding_time_violation",目标与口径!$A$5:$A$36,0)),"黄","红"))),"—") -> 黄 | F11: =INDEX(目标与口径!$L$5:$L$36,MATCH("holding_time_violation",目标与口径!$A$5:$A$36,0)) -> 0.7 | G11: =INDEX(目标与口径!$M$5:$M$36,MATCH("holding_time_violation",目标与口径!$A$5:$A$36,0)) -> 0.9 | H11: =IF($F$11>=0.7,IF($G$11>=0.7,"Q1 今天就做","Q2 上报求援"),IF($G$11>=0.7,"Q3 顺手做掉","Q4 记录观察")) -> Q1 今天就做 | I11: =INDEX(目标与口径!$J$5:$J$36,MATCH("holding_time_violation",目标与口径!$A$5:$A$36,0)) -> 组长 | J11: =IFERROR(ROUND(IFERROR(MAX(0,IF(INDEX(目标与口径!$E$5:$E$36,MATCH("holding_time_violation",目标与口径!$A$5:$A$36,0))="越高越好",INDEX(目标与口径!$G$5:$G$36,MATCH("holding_time_violation",目标与口径!$A$5:$A$36,0))-$C$11,$C$11-INDEX(目标与口径!$G$5:$G$36,MATCH("holding_time_violation",目标与口径!$A$5:$A$36,0)))/ABS(INDEX(目标与口径!$H$5:$H$36,MATCH("holding_time_violation",目标与口径!$A$5:$A$36,0))-INDEX(目标与口径!$G$5:$G$36,MATCH("holding_time_violation",目标与口径!$A$5:$A$36,0)))),0)*$F$11*$G$11*IF($E$11="红",2,1),2),0) -> 0.18 | K11: =INDEX(目标与口径!$N$5:$N$36,MATCH("holding_time_violation",目标与口径!$A$5:$A$36,0)) -> PB-06 | L11: 分成品/原料/保温三类：成品高改批量，原料高查先进先出 | M11: =RANK($J$11,$J$5:$J$36,0) -> 7
A12: net_sales | B12: 净销售额 | C12: =IFERROR(INDEX(每日经营日报!$D$5:$D$18,MATCH(店长看板!$B$3,每日经营日报!$A$5:$A$18,0)),0) -> 55987.74 | D12: =INDEX(目标与口径!$F$5:$F$36,MATCH("net_sales",目标与口径!$A$5:$A$36,0)) -> 62000 | E12: =IFERROR(IF(INDEX(目标与口径!$E$5:$E$36,MATCH("net_sales",目标与口径!$A$5:$A$36,0))="越高越好",IF($C$12>=INDEX(目标与口径!$G$5:$G$36,MATCH("net_sales",目标与口径!$A$5:$A$36,0)),"绿",IF($C$12>=INDEX(目标与口径!$H$5:$H$36,MATCH("net_sales",目标与口径!$A$5:$A$36,0)),"黄","红")),IF($C$12<=INDEX(目标与口径!$G$5:$G$36,MATCH("net_sales",目标与口径!$A$5:$A$36,0)),"绿",IF($C$12<=INDEX(目标与口径!$H$5:$H$36,MATCH("net_sales",目标与口径!$A$5:$A$36,0)),"黄","红"))),"—") -> 黄 | F12: =INDEX(目标与口径!$L$5:$L$36,MATCH("net_sales",目标与口径!$A$5:$A$36,0)) -> 1 | G12: =INDEX(目标与口径!$M$5:$M$36,MATCH("net_sales",目标与口径!$A$5:$A$36,0)) -> 0.45 | H12: =IF($F$12>=0.7,IF($G$12>=0.7,"Q1 今天就做","Q2 上报求援"),IF($G$12>=0.7,"Q3 顺手做掉","Q4 记录观察")) -> Q2 上报求援 | I12: =INDEX(目标与口径!$J$5:$J$36,MATCH("net_sales",目标与口径!$A$5:$A$36,0)) -> 店长 | J12: =IFERROR(ROUND(IFERROR(MAX(0,IF(INDEX(目标与口径!$E$5:$E$36,MATCH("net_sales",目标与口径!$A$5:$A$36,0))="越高越好",INDEX(目标与口径!$G$5:$G$36,MATCH("net_sales",目标与口径!$A$5:$A$36,0))-$C$12,$C$12-INDEX(目标与口径!$G$5:$G$36,MATCH("net_sales",目标与口径!$A$5:$A$36,0)))/ABS(INDEX(目标与口径!$H$5:$H$36,MATCH("net_sales",目标与口径!$A$5:$A$36,0))-INDEX(目标与口径!$G$5:$G$36,MATCH("net_sales",目标与口径!$A$5:$A$36,0)))),0)*$F$12*$G$12*IF($E$12="红",2,1),2),0) -> 0.15 | K12: =INDEX(目标与口径!$N$5:$N$36,MATCH("net_sales",目标与口径!$A$5:$A$36,0)) -> PB-01 | L12: 分清是客流少还是客单少：GC 跌查外部与曝光，客单跌走附加销售 | M12: =RANK($J$12,$J$5:$J$36,0) -> 8
A13: waste_pct | B13: 废弃率 | C13: =IFERROR(INDEX(每日经营日报!$S$5:$S$18,MATCH(店长看板!$B$3,每日经营日报!$A$5:$A$18,0)),0) -> 0.011011518 | D13: =INDEX(目标与口径!$F$5:$F$36,MATCH("waste_pct",目标与口径!$A$5:$A$36,0)) -> 0.008 | E13: =IFERROR(IF(INDEX(目标与口径!$E$5:$E$36,MATCH("waste_pct",目标与口径!$A$5:$A$36,0))="越高越好",IF($C$13>=INDEX(目标与口径!$G$5:$G$36,MATCH("waste_pct",目标与口径!$A$5:$A$36,0)),"绿",IF($C$13>=INDEX(目标与口径!$H$5:$H$36,MATCH("waste_pct",目标与口径!$A$5:$A$36,0)),"黄","红")),IF($C$13<=INDEX(目标与口径!$G$5:$G$36,MATCH("waste_pct",目标与口径!$A$5:$A$36,0)),"绿",IF($C$13<=INDEX(目标与口径!$H$5:$H$36,MATCH("waste_pct",目标与口径!$A$5:$A$36,0)),"黄","红"))),"—") -> 黄 | F13: =INDEX(目标与口径!$L$5:$L$36,MATCH("waste_pct",目标与口径!$A$5:$A$36,0)) -> 0.8 | G13: =INDEX(目标与口径!$M$5:$M$36,MATCH("waste_pct",目标与口径!$A$5:$A$36,0)) -> 0.9 | H13: =IF($F$13>=0.7,IF($G$13>=0.7,"Q1 今天就做","Q2 上报求援"),IF($G$13>=0.7,"Q3 顺手做掉","Q4 记录观察")) -> Q1 今天就做 | I13: =INDEX(目标与口径!$J$5:$J$36,MATCH("waste_pct",目标与口径!$A$5:$A$36,0)) -> 值班经理 | J13: =IFERROR(ROUND(IFERROR(MAX(0,IF(INDEX(目标与口径!$E$5:$E$36,MATCH("waste_pct",目标与口径!$A$5:$A$36,0))="越高越好",INDEX(目标与口径!$G$5:$G$36,MATCH("waste_pct",目标与口径!$A$5:$A$36,0))-$C$13,$C$13-INDEX(目标与口径!$G$5:$G$36,MATCH("waste_pct",目标与口径!$A$5:$A$36,0)))/ABS(INDEX(目标与口径!$H$5:$H$36,MATCH("waste_pct",目标与口径!$A$5:$A$36,0))-INDEX(目标与口径!$G$5:$G$36,MATCH("waste_pct",目标与口径!$A$5:$A$36,0)))),0)*$F$13*$G$13*IF($E$13="红",2,1),2),0) -> 0.15 | K13: =INDEX(目标与口径!$N$5:$N$36,MATCH("waste_pct",目标与口径!$A$5:$A$36,0)) -> PB-06 | L13: 分成品/原料/保温三类：成品高改批量，原料高查先进先出 | M13: =RANK($J$13,$J$5:$J$36,0) -> 8
A14: guest_count | B14: 交易笔数 (GC) | C14: =IFERROR(INDEX(每日经营日报!$E$5:$E$18,MATCH(店长看板!$B$3,每日经营日报!$A$5:$A$18,0)),0) -> 1564 | D14: =INDEX(目标与口径!$F$5:$F$36,MATCH("guest_count",目标与口径!$A$5:$A$36,0)) -> 1750 | E14: =IFERROR(IF(INDEX(目标与口径!$E$5:$E$36,MATCH("guest_count",目标与口径!$A$5:$A$36,0))="越高越好",IF($C$14>=INDEX(目标与口径!$G$5:$G$36,MATCH("guest_count",目标与口径!$A$5:$A$36,0)),"绿",IF($C$14>=INDEX(目标与口径!$H$5:$H$36,MATCH("guest_count",目标与口径!$A$5:$A$36,0)),"黄","红")),IF($C$14<=INDEX(目标与口径!$G$5:$G$36,MATCH("guest_count",目标与口径!$A$5:$A$36,0)),"绿",IF($C$14<=INDEX(目标与口径!$H$5:$H$36,MATCH("guest_count",目标与口径!$A$5:$A$36,0)),"黄","红"))),"—") -> 黄 | F14: =INDEX(目标与口径!$L$5:$L$36,MATCH("guest_count",目标与口径!$A$5:$A$36,0)) -> 0.9 | G14: =INDEX(目标与口径!$M$5:$M$36,MATCH("guest_count",目标与口径!$A$5:$A$36,0)) -> 0.35 | H14: =IF($F$14>=0.7,IF($G$14>=0.7,"Q1 今天就做","Q2 上报求援"),IF($G$14>=0.7,"Q3 顺手做掉","Q4 记录观察")) -> Q2 上报求援 | I14: =INDEX(目标与口径!$J$5:$J$36,MATCH("guest_count",目标与口径!$A$5:$A$36,0)) -> 店长 | J14: =IFERROR(ROUND(IFERROR(MAX(0,IF(INDEX(目标与口径!$E$5:$E$36,MATCH("guest_count",目标与口径!$A$5:$A$36,0))="越高越好",INDEX(目标与口径!$G$5:$G$36,MATCH("guest_count",目标与口径!$A$5:$A$36,0))-$C$14,$C$14-INDEX(目标与口径!$G$5:$G$36,MATCH("guest_count",目标与口径!$A$5:$A$36,0)))/ABS(INDEX(目标与口径!$H$5:$H$36,MATCH("guest_count",目标与口径!$A$5:$A$36,0))-INDEX(目标与口径!$G$5:$G$36,MATCH("guest_count",目标与口径!$A$5:$A$36,0)))),0)*$F$14*$G$14*IF($E$14="红",2,1),2),0) -> 0.13 | K14: =INDEX(目标与口径!$N$5:$N$36,MATCH("guest_count",目标与口径!$A$5:$A$36,0)) -> PB-01 | L14: 分清是客流少还是客单少：GC 跌查外部与曝光，客单跌走附加销售 | M14: =RANK($J$14,$J$5:$J$36,0) -> 10
A15: delivery_handover_time | B15: 外送出餐时长 | C15: =IFERROR(INDEX(每日经营日报!$AG$5:$AG$18,MATCH(店长看板!$B$3,每日经营日报!$A$5:$A$18,0)),0) -> 416.28 | D15: =INDEX(目标与口径!$F$5:$F$36,MATCH("delivery_handover_time",目标与口径!$A$5:$A$36,0)) -> 360 | E15: =IFERROR(IF(INDEX(目标与口径!$E$5:$E$36,MATCH("delivery_handover_time",目标与口径!$A$5:$A$36,0))="越高越好",IF($C$15>=INDEX(目标与口径!$G$5:$G$36,MATCH("delivery_handover_time",目标与口径!$A$5:$A$36,0)),"绿",IF($C$15>=INDEX(目标与口径!$H$5:$H$36,MATCH("delivery_handover_time",目标与口径!$A$5:$A$36,0)),"黄","红")),IF($C$15<=INDEX(目标与口径!$G$5:$G$36,MATCH("delivery_handover_time",目标与口径!$A$5:$A$36,0)),"绿",IF($C$15<=INDEX(目标与口径!$H$5:$H$36,MATCH("delivery_handover_time",目标与口径!$A$5:$A$36,0)),"黄","红"))),"—") -> 黄 | F15: =INDEX(目标与口径!$L$5:$L$36,MATCH("delivery_handover_time",目标与口径!$A$5:$A$36,0)) -> 0.6 | G15: =INDEX(目标与口径!$M$5:$M$36,MATCH("delivery_handover_time",目标与口径!$A$5:$A$36,0)) -> 0.7 | H15: =IF($F$15>=0.7,IF($G$15>=0.7,"Q1 今天就做","Q2 上报求援"),IF($G$15>=0.7,"Q3 顺手做掉","Q4 记录观察")) -> Q3 顺手做掉 | I15: =INDEX(目标与口径!$J$5:$J$36,MATCH("delivery_handover_time",目标与口径!$A$5:$A$36,0)) -> 组长 | J15: =IFERROR(ROUND(IFERROR(MAX(0,IF(INDEX(目标与口径!$E$5:$E$36,MATCH("delivery_handover_time",目标与口径!$A$5:$A$36,0))="越高越好",INDEX(目标与口径!$G$5:$G$36,MATCH("delivery_handover_time",目标与口径!$A$5:$A$36,0))-$C$15,$C$15-INDEX(目标与口径!$G$5:$G$36,MATCH("delivery_handover_time",目标与口径!$A$5:$A$36,0)))/ABS(INDEX(目标与口径!$H$5:$H$36,MATCH("delivery_handover_time",目标与口径!$A$5:$A$36,0))-INDEX(目标与口径!$G$5:$G$36,MATCH("delivery_handover_time",目标与口径!$A$5:$A$36,0)))),0)*$F$15*$G$15*IF($E$15="红",2,1),2),0) -> 0.09 | K15: =INDEX(目标与口径!$N$5:$N$36,MATCH("delivery_handover_time",目标与口径!$A$5:$A$36,0)) -> PB-03 | L15: 全时段慢=打包流程问题（上报）；只高峰慢=给外送单独留打包位 | M15: =RANK($J$15,$J$5:$J$36,0) -> 11
A16: food_cost_pct | B16: 食品成本率 | C16: =IFERROR(INDEX(每日经营日报!$Q$5:$Q$18,MATCH(店长看板!$B$3,每日经营日报!$A$5:$A$18,0)),0) -> 0.31219353 | D16: =INDEX(目标与口径!$F$5:$F$36,MATCH("food_cost_pct",目标与口径!$A$5:$A$36,0)) -> 0.305 | E16: =IFERROR(IF(INDEX(目标与口径!$E$5:$E$36,MATCH("food_cost_pct",目标与口径!$A$5:$A$36,0))="越高越好",IF($C$16>=INDEX(目标与口径!$G$5:$G$36,MATCH("food_cost_pct",目标与口径!$A$5:$A$36,0)),"绿",IF($C$16>=INDEX(目标与口径!$H$5:$H$36,MATCH("food_cost_pct",目标与口径!$A$5:$A$36,0)),"黄","红")),IF($C$16<=INDEX(目标与口径!$G$5:$G$36,MATCH("food_cost_pct",目标与口径!$A$5:$A$36,0)),"绿",IF($C$16<=INDEX(目标与口径!$H$5:$H$36,MATCH("food_cost_pct",目标与口径!$A$5:$A$36,0)),"黄","红"))),"—") -> 黄 | F16: =INDEX(目标与口径!$L$5:$L$36,MATCH("food_cost_pct",目标与口径!$A$5:$A$36,0)) -> 0.95 | G16: =INDEX(目标与口径!$M$5:$M$36,MATCH("food_cost_pct",目标与口径!$A$5:$A$36,0)) -> 0.6 | H16: =IF($F$16>=0.7,IF($G$16>=0.7,"Q1 今天就做","Q2 上报求援"),IF($G$16>=0.7,"Q3 顺手做掉","Q4 记录观察")) -> Q2 上报求援 | I16: =INDEX(目标与口径!$J$5:$J$36,MATCH("food_cost_pct",目标与口径!$A$5:$A$36,0)) -> 店长 | J16: =IFERROR(ROUND(IFERROR(MAX(0,IF(INDEX(目标与口径!$E$5:$E$36,MATCH("food_cost_pct",目标与口径!$A$5:$A$36,0))="越高越好",INDEX(目标与口径!$G$5:$G$36,MATCH("food_cost_pct",目标与口径!$A$5:$A$36,0))-$C$16,$C$16-INDEX(目标与口径!$G$5:$G$36,MATCH("food_cost_pct",目标与口径!$A$5:$A$36,0)))/ABS(INDEX(目标与口径!$H$5:$H$36,MATCH("food_cost_pct",目标与口径!$A$5:$A$36,0))-INDEX(目标与口径!$G$5:$G$36,MATCH("food_cost_pct",目标与口径!$A$5:$A$36,0)))),0)*$F$16*$G$16*IF($E$16="红",2,1),2),0) -> 0.08 | K16: =INDEX(目标与口径!$N$5:$N$36,MATCH("food_cost_pct",目标与口径!$A$5:$A$36,0)) -> PB-06 | L16: 分成品/原料/保温三类：成品高改批量，原料高查先进先出 | M16: =RANK($J$16,$J$5:$J$36,0) -> 12
A17: station_certification | B17: 岗位认证覆盖率 | C17: =IFERROR(INDEX(每日经营日报!$AZ$5:$AZ$18,MATCH(店长看板!$B$3,每日经营日报!$A$5:$A$18,0)),0) -> 0.89473684 | D17: =INDEX(目标与口径!$F$5:$F$36,MATCH("station_certification",目标与口径!$A$5:$A$36,0)) -> 0.95 | E17: =IFERROR(IF(INDEX(目标与口径!$E$5:$E$36,MATCH("station_certification",目标与口径!$A$5:$A$36,0))="越高越好",IF($C$17>=INDEX(目标与口径!$G$5:$G$36,MATCH("station_certification",目标与口径!$A$5:$A$36,0)),"绿",IF($C$17>=INDEX(目标与口径!$H$5:$H$36,MATCH("station_certification",目标与口径!$A$5:$A$36,0)),"黄","红")),IF($C$17<=INDEX(目标与口径!$G$5:$G$36,MATCH("station_certification",目标与口径!$A$5:$A$36,0)),"绿",IF($C$17<=INDEX(目标与口径!$H$5:$H$36,MATCH("station_certification",目标与口径!$A$5:$A$36,0)),"黄","红"))),"—") -> 黄 | F17: =INDEX(目标与口径!$L$5:$L$36,MATCH("station_certification",目标与口径!$A$5:$A$36,0)) -> 0.7 | G17: =INDEX(目标与口径!$M$5:$M$36,MATCH("station_certification",目标与口径!$A$5:$A$36,0)) -> 0.6 | H17: =IF($F$17>=0.7,IF($G$17>=0.7,"Q1 今天就做","Q2 上报求援"),IF($G$17>=0.7,"Q3 顺手做掉","Q4 记录观察")) -> Q2 上报求援 | I17: =INDEX(目标与口径!$J$5:$J$36,MATCH("station_certification",目标与口径!$A$5:$A$36,0)) -> 训练员 | J17: =IFERROR(ROUND(IFERROR(MAX(0,IF(INDEX(目标与口径!$E$5:$E$36,MATCH("station_certification",目标与口径!$A$5:$A$36,0))="越高越好",INDEX(目标与口径!$G$5:$G$36,MATCH("station_certification",目标与口径!$A$5:$A$36,0))-$C$17,$C$17-INDEX(目标与口径!$G$5:$G$36,MATCH("station_certification",目标与口径!$A$5:$A$36,0)))/ABS(INDEX(目标与口径!$H$5:$H$36,MATCH("station_certification",目标与口径!$A$5:$A$36,0))-INDEX(目标与口径!$G$5:$G$36,MATCH("station_certification",目标与口径!$A$5:$A$36,0)))),0)*$F$17*$G$17*IF($E$17="红",2,1),2),0) -> 0.02 | K17: =INDEX(目标与口径!$N$5:$N$36,MATCH("station_certification",目标与口径!$A$5:$A$36,0)) -> PB-12 | L17: 按司龄段/岗位下钻；<90 天流失高 = 新人被丢在高峰上 | M17: =RANK($J$17,$J$5:$J$36,0) -> 13
A18: sales_vs_forecast | B18: 销售达成率 | C18: =IFERROR(INDEX(每日经营日报!$G$5:$G$18,MATCH(店长看板!$B$3,每日经营日报!$A$5:$A$18,0)),0) -> 0.97868414 | D18: =INDEX(目标与口径!$F$5:$F$36,MATCH("sales_vs_forecast",目标与口径!$A$5:$A$36,0)) -> 1 | E18: =IFERROR(IF(INDEX(目标与口径!$E$5:$E$36,MATCH("sales_vs_forecast",目标与口径!$A$5:$A$36,0))="越高越好",IF($C$18>=INDEX(目标与口径!$G$5:$G$36,MATCH("sales_vs_forecast",目标与口径!$A$5:$A$36,0)),"绿",IF($C$18>=INDEX(目标与口径!$H$5:$H$36,MATCH("sales_vs_forecast",目标与口径!$A$5:$A$36,0)),"黄","红")),IF($C$18<=INDEX(目标与口径!$G$5:$G$36,MATCH("sales_vs_forecast",目标与口径!$A$5:$A$36,0)),"绿",IF($C$18<=INDEX(目标与口径!$H$5:$H$36,MATCH("sales_vs_forecast",目标与口径!$A$5:$A$36,0)),"黄","红"))),"—") -> 黄 | F18: =INDEX(目标与口径!$L$5:$L$36,MATCH("sales_vs_forecast",目标与口径!$A$5:$A$36,0)) -> 0.95 | G18: =INDEX(目标与口径!$M$5:$M$36,MATCH("sales_vs_forecast",目标与口径!$A$5:$A$36,0)) -> 0.5 | H18: =IF($F$18>=0.7,IF($G$18>=0.7,"Q1 今天就做","Q2 上报求援"),IF($G$18>=0.7,"Q3 顺手做掉","Q4 记录观察")) -> Q2 上报求援 | I18: =INDEX(目标与口径!$J$5:$J$36,MATCH("sales_vs_forecast",目标与口径!$A$5:$A$36,0)) -> 店长 | J18: =IFERROR(ROUND(IFERROR(MAX(0,IF(INDEX(目标与口径!$E$5:$E$36,MATCH("sales_vs_forecast",目标与口径!$A$5:$A$36,0))="越高越好",INDEX(目标与口径!$G$5:$G$36,MATCH("sales_vs_forecast",目标与口径!$A$5:$A$36,0))-$C$18,$C$18-INDEX(目标与口径!$G$5:$G$36,MATCH("sales_vs_forecast",目标与口径!$A$5:$A$36,0)))/ABS(INDEX(目标与口径!$H$5:$H$36,MATCH("sales_vs_forecast",目标与口径!$A$5:$A$36,0))-INDEX(目标与口径!$G$5:$G$36,MATCH("sales_vs_forecast",目标与口径!$A$5:$A$36,0)))),0)*$F$18*$G$18*IF($E$18="红",2,1),2),0) -> 0.01 | K18: =INDEX(目标与口径!$N$5:$N$36,MATCH("sales_vs_forecast",目标与口径!$A$5:$A$36,0)) -> PB-01 | L18: 分清是客流少还是客单少：GC 跌查外部与曝光，客单跌走附加销售 | M18: =RANK($J$18,$J$5:$J$36,0) -> 14
A19: cleanliness_score | B19: 清洁巡检得分 | C19: =IFERROR(INDEX(每日经营日报!$AR$5:$AR$18,MATCH(店长看板!$B$3,每日经营日报!$A$5:$A$18,0)),0) -> 91.867 | D19: =INDEX(目标与口径!$F$5:$F$36,MATCH("cleanliness_score",目标与口径!$A$5:$A$36,0)) -> 95 | E19: =IFERROR(IF(INDEX(目标与口径!$E$5:$E$36,MATCH("cleanliness_score",目标与口径!$A$5:$A$36,0))="越高越好",IF($C$19>=INDEX(目标与口径!$G$5:$G$36,MATCH("cleanliness_score",目标与口径!$A$5:$A$36,0)),"绿",IF($C$19>=INDEX(目标与口径!$H$5:$H$36,MATCH("cleanliness_score",目标与口径!$A$5:$A$36,0)),"黄","红")),IF($C$19<=INDEX(目标与口径!$G$5:$G$36,MATCH("cleanliness_score",目标与口径!$A$5:$A$36,0)),"绿",IF($C$19<=INDEX(目标与口径!$H$5:$H$36,MATCH("cleanliness_score",目标与口径!$A$5:$A$36,0)),"黄","红"))),"—") -> 黄 | F19: =INDEX(目标与口径!$L$5:$L$36,MATCH("cleanliness_score",目标与口径!$A$5:$A$36,0)) -> 0.65 | G19: =INDEX(目标与口径!$M$5:$M$36,MATCH("cleanliness_score",目标与口径!$A$5:$A$36,0)) -> 0.95 | H19: =IF($F$19>=0.7,IF($G$19>=0.7,"Q1 今天就做","Q2 上报求援"),IF($G$19>=0.7,"Q3 顺手做掉","Q4 记录观察")) -> Q3 顺手做掉 | I19: =INDEX(目标与口径!$J$5:$J$36,MATCH("cleanliness_score",目标与口径!$A$5:$A$36,0)) -> 值班经理 | J19: =IFERROR(ROUND(IFERROR(MAX(0,IF(INDEX(目标与口径!$E$5:$E$36,MATCH("cleanliness_score",目标与口径!$A$5:$A$36,0))="越高越好",INDEX(目标与口径!$G$5:$G$36,MATCH("cleanliness_score",目标与口径!$A$5:$A$36,0))-$C$19,$C$19-INDEX(目标与口径!$G$5:$G$36,MATCH("cleanliness_score",目标与口径!$A$5:$A$36,0)))/ABS(INDEX(目标与口径!$H$5:$H$36,MATCH("cleanliness_score",目标与口径!$A$5:$A$36,0))-INDEX(目标与口径!$G$5:$G$36,MATCH("cleanliness_score",目标与口径!$A$5:$A$36,0)))),0)*$F$19*$G$19*IF($E$19="红",2,1),2),0) -> 0.01 | K19: =INDEX(目标与口径!$N$5:$N$36,MATCH("cleanliness_score",目标与口径!$A$5:$A$36,0)) -> PB-10 | L19: 分区看：洗手间失分优先（顾客对干净的判断在那里） | M19: =RANK($J$19,$J$5:$J$36,0) -> 14
A20: avg_check | B20: 客单价 (TC) | C20: =IFERROR(INDEX(每日经营日报!$F$5:$F$18,MATCH(店长看板!$B$3,每日经营日报!$A$5:$A$18,0)),0) -> 35.797788 | D20: =INDEX(目标与口径!$F$5:$F$36,MATCH("avg_check",目标与口径!$A$5:$A$36,0)) -> 35.5 | E20: =IFERROR(IF(INDEX(目标与口径!$E$5:$E$36,MATCH("avg_check",目标与口径!$A$5:$A$36,0))="越高越好",IF($C$20>=INDEX(目标与口径!$G$5:$G$36,MATCH("avg_check",目标与口径!$A$5:$A$36,0)),"绿",IF($C$20>=INDEX(目标与口径!$H$5:$H$36,MATCH("avg_check",目标与口径!$A$5:$A$36,0)),"黄","红")),IF($C$20<=INDEX(目标与口径!$G$5:$G$36,MATCH("avg_check",目标与口径!$A$5:$A$36,0)),"绿",IF($C$20<=INDEX(目标与口径!$H$5:$H$36,MATCH("avg_check",目标与口径!$A$5:$A$36,0)),"黄","红"))),"—") -> 绿 | F20: =INDEX(目标与口径!$L$5:$L$36,MATCH("avg_check",目标与口径!$A$5:$A$36,0)) -> 0.8 | G20: =INDEX(目标与口径!$M$5:$M$36,MATCH("avg_check",目标与口径!$A$5:$A$36,0)) -> 0.75 | H20: =IF($F$20>=0.7,IF($G$20>=0.7,"Q1 今天就做","Q2 上报求援"),IF($G$20>=0.7,"Q3 顺手做掉","Q4 记录观察")) -> Q1 今天就做 | I20: =INDEX(目标与口径!$J$5:$J$36,MATCH("avg_check",目标与口径!$A$5:$A$36,0)) -> 值班经理 | J20: =IFERROR(ROUND(IFERROR(MAX(0,IF(INDEX(目标与口径!$E$5:$E$36,MATCH("avg_check",目标与口径!$A$5:$A$36,0))="越高越好",INDEX(目标与口径!$G$5:$G$36,MATCH("avg_check",目标与口径!$A$5:$A$36,0))-$C$20,$C$20-INDEX(目标与口径!$G$5:$G$36,MATCH("avg_check",目标与口径!$A$5:$A$36,0)))/ABS(INDEX(目标与口径!$H$5:$H$36,MATCH("avg_check",目标与口径!$A$5:$A$36,0))-INDEX(目标与口径!$G$5:$G$36,MATCH("avg_check",目标与口径!$A$5:$A$36,0)))),0)*$F$20*$G$20*IF($E$20="红",2,1),2),0) -> 0 | K20: =INDEX(目标与口径!$N$5:$N$36,MATCH("avg_check",目标与口径!$A$5:$A$36,0)) -> PB-02 | L20: 拉附加销售率 × 收银员，训练员跟班 2 小时；只主推 1 个品 | M20: =RANK($J$20,$J$5:$J$36,0) -> 16
A21: delivery_share | B21: 外送销售占比 | C21: =IFERROR(INDEX(每日经营日报!$L$5:$L$18,MATCH(店长看板!$B$3,每日经营日报!$A$5:$A$18,0)),0) -> 0.26601895 | D21: =INDEX(目标与口径!$F$5:$F$36,MATCH("delivery_share",目标与口径!$A$5:$A$36,0)) -> 0.22 | E21: =IFERROR(IF(INDEX(目标与口径!$E$5:$E$36,MATCH("delivery_share",目标与口径!$A$5:$A$36,0))="越高越好",IF($C$21>=INDEX(目标与口径!$G$5:$G$36,MATCH("delivery_share",目标与口径!$A$5:$A$36,0)),"绿",IF($C$21>=INDEX(目标与口径!$H$5:$H$36,MATCH("delivery_share",目标与口径!$A$5:$A$36,0)),"黄","红")),IF($C$21<=INDEX(目标与口径!$G$5:$G$36,MATCH("delivery_share",目标与口径!$A$5:$A$36,0)),"绿",IF($C$21<=INDEX(目标与口径!$H$5:$H$36,MATCH("delivery_share",目标与口径!$A$5:$A$36,0)),"黄","红"))),"—") -> 绿 | F21: =INDEX(目标与口径!$L$5:$L$36,MATCH("delivery_share",目标与口径!$A$5:$A$36,0)) -> 0.4 | G21: =INDEX(目标与口径!$M$5:$M$36,MATCH("delivery_share",目标与口径!$A$5:$A$36,0)) -> 0.2 | H21: =IF($F$21>=0.7,IF($G$21>=0.7,"Q1 今天就做","Q2 上报求援"),IF($G$21>=0.7,"Q3 顺手做掉","Q4 记录观察")) -> Q4 记录观察 | I21: =INDEX(目标与口径!$J$5:$J$36,MATCH("delivery_share",目标与口径!$A$5:$A$36,0)) -> 店长 | J21: =IFERROR(ROUND(IFERROR(MAX(0,IF(INDEX(目标与口径!$E$5:$E$36,MATCH("delivery_share",目标与口径!$A$5:$A$36,0))="越高越好",INDEX(目标与口径!$G$5:$G$36,MATCH("delivery_share",目标与口径!$A$5:$A$36,0))-$C$21,$C$21-INDEX(目标与口径!$G$5:$G$36,MATCH("delivery_share",目标与口径!$A$5:$A$36,0)))/ABS(INDEX(目标与口径!$H$5:$H$36,MATCH("delivery_share",目标与口径!$A$5:$A$36,0))-INDEX(目标与口径!$G$5:$G$36,MATCH("delivery_share",目标与口径!$A$5:$A$36,0)))),0)*$F$21*$G$21*IF($E$21="红",2,1),2),0) -> 0 | K21: =INDEX(目标与口径!$N$5:$N$36,MATCH("delivery_share",目标与口径!$A$5:$A$36,0)) -> PB-03 | L21: 全时段慢=打包流程问题（上报）；只高峰慢=给外送单独留打包位 | M21: =RANK($J$21,$J$5:$J$36,0) -> 16
A22: items_per_check | B22: 单均件数 | C22: =IFERROR(INDEX(每日经营日报!$I$5:$I$18,MATCH(店长看板!$B$3,每日经营日报!$A$5:$A$18,0)),0) -> 3.3382353 | D22: =INDEX(目标与口径!$F$5:$F$36,MATCH("items_per_check",目标与口径!$A$5:$A$36,0)) -> 3.2 | E22: =IFERROR(IF(INDEX(目标与口径!$E$5:$E$36,MATCH("items_per_check",目标与口径!$A$5:$A$36,0))="越高越好",IF($C$22>=INDEX(目标与口径!$G$5:$G$36,MATCH("items_per_check",目标与口径!$A$5:$A$36,0)),"绿",IF($C$22>=INDEX(目标与口径!$H$5:$H$36,MATCH("items_per_check",目标与口径!$A$5:$A$36,0)),"黄","红")),IF($C$22<=INDEX(目标与口径!$G$5:$G$36,MATCH("items_per_check",目标与口径!$A$5:$A$36,0)),"绿",IF($C$22<=INDEX(目标与口径!$H$5:$H$36,MATCH("items_per_check",目标与口径!$A$5:$A$36,0)),"黄","红"))),"—") -> 绿 | F22: =INDEX(目标与口径!$L$5:$L$36,MATCH("items_per_check",目标与口径!$A$5:$A$36,0)) -> 0.6 | G22: =INDEX(目标与口径!$M$5:$M$36,MATCH("items_per_check",目标与口径!$A$5:$A$36,0)) -> 0.8 | H22: =IF($F$22>=0.7,IF($G$22>=0.7,"Q1 今天就做","Q2 上报求援"),IF($G$22>=0.7,"Q3 顺手做掉","Q4 记录观察")) -> Q3 顺手做掉 | I22: =INDEX(目标与口径!$J$5:$J$36,MATCH("items_per_check",目标与口径!$A$5:$A$36,0)) -> 值班经理 | J22: =IFERROR(ROUND(IFERROR(MAX(0,IF(INDEX(目标与口径!$E$5:$E$36,MATCH("items_per_check",目标与口径!$A$5:$A$36,0))="越高越好",INDEX(目标与口径!$G$5:$G$36,MATCH("items_per_check",目标与口径!$A$5:$A$36,0))-$C$22,$C$22-INDEX(目标与口径!$G$5:$G$36,MATCH("items_per_check",目标与口径!$A$5:$A$36,0)))/ABS(INDEX(目标与口径!$H$5:$H$36,MATCH("items_per_check",目标与口径!$A$5:$A$36,0))-INDEX(目标与口径!$G$5:$G$36,MATCH("items_per_check",目标与口径!$A$5:$A$36,0)))),0)*$F$22*$G$22*IF($E$22="红",2,1),2),0) -> 0 | K22: =INDEX(目标与口径!$N$5:$N$36,MATCH("items_per_check",目标与口径!$A$5:$A$36,0)) -> PB-02 | L22: 拉附加销售率 × 收银员，训练员跟班 2 小时；只主推 1 个品 | M22: =RANK($J$22,$J$5:$J$36,0) -> 16
A23: dt_total_time | B23: 得来速总时长 | C23: =IFERROR(INDEX(每日经营日报!$AC$5:$AC$18,MATCH(店长看板!$B$3,每日经营日报!$A$5:$A$18,0)),0) -> 158.34 | D23: =INDEX(目标与口径!$F$5:$F$36,MATCH("dt_total_time",目标与口径!$A$5:$A$36,0)) -> 180 | E23: =IFERROR(IF(INDEX(目标与口径!$E$5:$E$36,MATCH("dt_total_time",目标与口径!$A$5:$A$36,0))="越高越好",IF($C$23>=INDEX(目标与口径!$G$5:$G$36,MATCH("dt_total_time",目标与口径!$A$5:$A$36,0)),"绿",IF($C$23>=INDEX(目标与口径!$H$5:$H$36,MATCH("dt_total_time",目标与口径!$A$5:$A$36,0)),"黄","红")),IF($C$23<=INDEX(目标与口径!$G$5:$G$36,MATCH("dt_total_time",目标与口径!$A$5:$A$36,0)),"绿",IF($C$23<=INDEX(目标与口径!$H$5:$H$36,MATCH("dt_total_time",目标与口径!$A$5:$A$36,0)),"黄","红"))),"—") -> 绿 | F23: =INDEX(目标与口径!$L$5:$L$36,MATCH("dt_total_time",目标与口径!$A$5:$A$36,0)) -> 0.9 | G23: =INDEX(目标与口径!$M$5:$M$36,MATCH("dt_total_time",目标与口径!$A$5:$A$36,0)) -> 0.85 | H23: =IF($F$23>=0.7,IF($G$23>=0.7,"Q1 今天就做","Q2 上报求援"),IF($G$23>=0.7,"Q3 顺手做掉","Q4 记录观察")) -> Q1 今天就做 | I23: =INDEX(目标与口径!$J$5:$J$36,MATCH("dt_total_time",目标与口径!$A$5:$A$36,0)) -> 值班经理 | J23: =IFERROR(ROUND(IFERROR(MAX(0,IF(INDEX(目标与口径!$E$5:$E$36,MATCH("dt_total_time",目标与口径!$A$5:$A$36,0))="越高越好",INDEX(目标与口径!$G$5:$G$36,MATCH("dt_total_time",目标与口径!$A$5:$A$36,0))-$C$23,$C$23-INDEX(目标与口径!$G$5:$G$36,MATCH("dt_total_time",目标与口径!$A$5:$A$36,0)))/ABS(INDEX(目标与口径!$H$5:$H$36,MATCH("dt_total_time",目标与口径!$A$5:$A$36,0))-INDEX(目标与口径!$G$5:$G$36,MATCH("dt_total_time",目标与口径!$A$5:$A$36,0)))),0)*$F$23*$G$23*IF($E$23="红",2,1),2),0) -> 0 | K23: =INDEX(目标与口径!$N$5:$N$36,MATCH("dt_total_time",目标与口径!$A$5:$A$36,0)) -> PB-04 | L23: 先分段定位（点单/排队/取餐窗/制作），再看是结构问题还是产能问题 | M23: =RANK($J$23,$J$5:$J$36,0) -> 16
A24: dt_window_time | B24: 得来速取餐窗时长 | C24: =IFERROR(INDEX(每日经营日报!$AD$5:$AD$18,MATCH(店长看板!$B$3,每日经营日报!$A$5:$A$18,0)),0) -> 58.36 | D24: =INDEX(目标与口径!$F$5:$F$36,MATCH("dt_window_time",目标与口径!$A$5:$A$36,0)) -> 55 | E24: =IFERROR(IF(INDEX(目标与口径!$E$5:$E$36,MATCH("dt_window_time",目标与口径!$A$5:$A$36,0))="越高越好",IF($C$24>=INDEX(目标与口径!$G$5:$G$36,MATCH("dt_window_time",目标与口径!$A$5:$A$36,0)),"绿",IF($C$24>=INDEX(目标与口径!$H$5:$H$36,MATCH("dt_window_time",目标与口径!$A$5:$A$36,0)),"黄","红")),IF($C$24<=INDEX(目标与口径!$G$5:$G$36,MATCH("dt_window_time",目标与口径!$A$5:$A$36,0)),"绿",IF($C$24<=INDEX(目标与口径!$H$5:$H$36,MATCH("dt_window_time",目标与口径!$A$5:$A$36,0)),"黄","红"))),"—") -> 绿 | F24: =INDEX(目标与口径!$L$5:$L$36,MATCH("dt_window_time",目标与口径!$A$5:$A$36,0)) -> 0.7 | G24: =INDEX(目标与口径!$M$5:$M$36,MATCH("dt_window_time",目标与口径!$A$5:$A$36,0)) -> 0.9 | H24: =IF($F$24>=0.7,IF($G$24>=0.7,"Q1 今天就做","Q2 上报求援"),IF($G$24>=0.7,"Q3 顺手做掉","Q4 记录观察")) -> Q1 今天就做 | I24: =INDEX(目标与口径!$J$5:$J$36,MATCH("dt_window_time",目标与口径!$A$5:$A$36,0)) -> 值班经理 | J24: =IFERROR(ROUND(IFERROR(MAX(0,IF(INDEX(目标与口径!$E$5:$E$36,MATCH("dt_window_time",目标与口径!$A$5:$A$36,0))="越高越好",INDEX(目标与口径!$G$5:$G$36,MATCH("dt_window_time",目标与口径!$A$5:$A$36,0))-$C$24,$C$24-INDEX(目标与口径!$G$5:$G$36,MATCH("dt_window_time",目标与口径!$A$5:$A$36,0)))/ABS(INDEX(目标与口径!$H$5:$H$36,MATCH("dt_window_time",目标与口径!$A$5:$A$36,0))-INDEX(目标与口径!$G$5:$G$36,MATCH("dt_window_time",目标与口径!$A$5:$A$36,0)))),0)*$F$24*$G$24*IF($E$24="红",2,1),2),0) -> 0 | K24: =INDEX(目标与口径!$N$5:$N$36,MATCH("dt_window_time",目标与口径!$A$5:$A$36,0)) -> PB-04 | L24: 先分段定位（点单/排队/取餐窗/制作），再看是结构问题还是产能问题 | M24: =RANK($J$24,$J$5:$J$36,0) -> 16
A25: front_otd | B25: 前台交付时长 (OTD) | C25: =IFERROR(INDEX(每日经营日报!$AF$5:$AF$18,MATCH(店长看板!$B$3,每日经营日报!$A$5:$A$18,0)),0) -> 129.08 | D25: =INDEX(目标与口径!$F$5:$F$36,MATCH("front_otd",目标与口径!$A$5:$A$36,0)) -> 150 | E25: =IFERROR(IF(INDEX(目标与口径!$E$5:$E$36,MATCH("front_otd",目标与口径!$A$5:$A$36,0))="越高越好",IF($C$25>=INDEX(目标与口径!$G$5:$G$36,MATCH("front_otd",目标与口径!$A$5:$A$36,0)),"绿",IF($C$25>=INDEX(目标与口径!$H$5:$H$36,MATCH("front_otd",目标与口径!$A$5:$A$36,0)),"黄","红")),IF($C$25<=INDEX(目标与口径!$G$5:$G$36,MATCH("front_otd",目标与口径!$A$5:$A$36,0)),"绿",IF($C$25<=INDEX(目标与口径!$H$5:$H$36,MATCH("front_otd",目标与口径!$A$5:$A$36,0)),"黄","红"))),"—") -> 绿 | F25: =INDEX(目标与口径!$L$5:$L$36,MATCH("front_otd",目标与口径!$A$5:$A$36,0)) -> 0.7 | G25: =INDEX(目标与口径!$M$5:$M$36,MATCH("front_otd",目标与口径!$A$5:$A$36,0)) -> 0.85 | H25: =IF($F$25>=0.7,IF($G$25>=0.7,"Q1 今天就做","Q2 上报求援"),IF($G$25>=0.7,"Q3 顺手做掉","Q4 记录观察")) -> Q1 今天就做 | I25: =INDEX(目标与口径!$J$5:$J$36,MATCH("front_otd",目标与口径!$A$5:$A$36,0)) -> 值班经理 | J25: =IFERROR(ROUND(IFERROR(MAX(0,IF(INDEX(目标与口径!$E$5:$E$36,MATCH("front_otd",目标与口径!$A$5:$A$36,0))="越高越好",INDEX(目标与口径!$G$5:$G$36,MATCH("front_otd",目标与口径!$A$5:$A$36,0))-$C$25,$C$25-INDEX(目标与口径!$G$5:$G$36,MATCH("front_otd",目标与口径!$A$5:$A$36,0)))/ABS(INDEX(目标与口径!$H$5:$H$36,MATCH("front_otd",目标与口径!$A$5:$A$36,0))-INDEX(目标与口径!$G$5:$G$36,MATCH("front_otd",目标与口径!$A$5:$A$36,0)))),0)*$F$25*$G$25*IF($E$25="红",2,1),2),0) -> 0 | K25: =INDEX(目标与口径!$N$5:$N$36,MATCH("front_otd",目标与口径!$A$5:$A$36,0)) -> PB-04 | L25: 先分段定位（点单/排队/取餐窗/制作），再看是结构问题还是产能问题 | M25: =RANK($J$25,$J$5:$J$36,0) -> 16
A26: kds_prep_time | B26: 后厨制作时长 | C26: =IFERROR(INDEX(每日经营日报!$AE$5:$AE$18,MATCH(店长看板!$B$3,每日经营日报!$A$5:$A$18,0)),0) -> 86.24 | D26: =INDEX(目标与口径!$F$5:$F$36,MATCH("kds_prep_time",目标与口径!$A$5:$A$36,0)) -> 90 | E26: =IFERROR(IF(INDEX(目标与口径!$E$5:$E$36,MATCH("kds_prep_time",目标与口径!$A$5:$A$36,0))="越高越好",IF($C$26>=INDEX(目标与口径!$G$5:$G$36,MATCH("kds_prep_time",目标与口径!$A$5:$A$36,0)),"绿",IF($C$26>=INDEX(目标与口径!$H$5:$H$36,MATCH("kds_prep_time",目标与口径!$A$5:$A$36,0)),"黄","红")),IF($C$26<=INDEX(目标与口径!$G$5:$G$36,MATCH("kds_prep_time",目标与口径!$A$5:$A$36,0)),"绿",IF($C$26<=INDEX(目标与口径!$H$5:$H$36,MATCH("kds_prep_time",目标与口径!$A$5:$A$36,0)),"黄","红"))),"—") -> 绿 | F26: =INDEX(目标与口径!$L$5:$L$36,MATCH("kds_prep_time",目标与口径!$A$5:$A$36,0)) -> 0.75 | G26: =INDEX(目标与口径!$M$5:$M$36,MATCH("kds_prep_time",目标与口径!$A$5:$A$36,0)) -> 0.85 | H26: =IF($F$26>=0.7,IF($G$26>=0.7,"Q1 今天就做","Q2 上报求援"),IF($G$26>=0.7,"Q3 顺手做掉","Q4 记录观察")) -> Q1 今天就做 | I26: =INDEX(目标与口径!$J$5:$J$36,MATCH("kds_prep_time",目标与口径!$A$5:$A$36,0)) -> 组长 | J26: =IFERROR(ROUND(IFERROR(MAX(0,IF(INDEX(目标与口径!$E$5:$E$36,MATCH("kds_prep_time",目标与口径!$A$5:$A$36,0))="越高越好",INDEX(目标与口径!$G$5:$G$36,MATCH("kds_prep_time",目标与口径!$A$5:$A$36,0))-$C$26,$C$26-INDEX(目标与口径!$G$5:$G$36,MATCH("kds_prep_time",目标与口径!$A$5:$A$36,0)))/ABS(INDEX(目标与口径!$H$5:$H$36,MATCH("kds_prep_time",目标与口径!$A$5:$A$36,0))-INDEX(目标与口径!$G$5:$G$36,MATCH("kds_prep_time",目标与口径!$A$5:$A$36,0)))),0)*$F$26*$G$26*IF($E$26="红",2,1),2),0) -> 0 | K26: =INDEX(目标与口径!$N$5:$N$36,MATCH("kds_prep_time",目标与口径!$A$5:$A$36,0)) -> PB-04 | L26: 先分段定位（点单/排队/取餐窗/制作），再看是结构问题还是产能问题 | M26: =RANK($J$26,$J$5:$J$36,0) -> 16
A27: order_accuracy | B27: 订单准确率 | C27: =IFERROR(INDEX(每日经营日报!$AK$5:$AK$18,MATCH(店长看板!$B$3,每日经营日报!$A$5:$A$18,0)),0) -> 0.99936061 | D27: =INDEX(目标与口径!$F$5:$F$36,MATCH("order_accuracy",目标与口径!$A$5:$A$36,0)) -> 0.996 | E27: =IFERROR(IF(INDEX(目标与口径!$E$5:$E$36,MATCH("order_accuracy",目标与口径!$A$5:$A$36,0))="越高越好",IF($C$27>=INDEX(目标与口径!$G$5:$G$36,MATCH("order_accuracy",目标与口径!$A$5:$A$36,0)),"绿",IF($C$27>=INDEX(目标与口径!$H$5:$H$36,MATCH("order_accuracy",目标与口径!$A$5:$A$36,0)),"黄","红")),IF($C$27<=INDEX(目标与口径!$G$5:$G$36,MATCH("order_accuracy",目标与口径!$A$5:$A$36,0)),"绿",IF($C$27<=INDEX(目标与口径!$H$5:$H$36,MATCH("order_accuracy",目标与口径!$A$5:$A$36,0)),"黄","红"))),"—") -> 绿 | F27: =INDEX(目标与口径!$L$5:$L$36,MATCH("order_accuracy",目标与口径!$A$5:$A$36,0)) -> 0.8 | G27: =INDEX(目标与口径!$M$5:$M$36,MATCH("order_accuracy",目标与口径!$A$5:$A$36,0)) -> 0.85 | H27: =IF($F$27>=0.7,IF($G$27>=0.7,"Q1 今天就做","Q2 上报求援"),IF($G$27>=0.7,"Q3 顺手做掉","Q4 记录观察")) -> Q1 今天就做 | I27: =INDEX(目标与口径!$J$5:$J$36,MATCH("order_accuracy",目标与口径!$A$5:$A$36,0)) -> 值班经理 | J27: =IFERROR(ROUND(IFERROR(MAX(0,IF(INDEX(目标与口径!$E$5:$E$36,MATCH("order_accuracy",目标与口径!$A$5:$A$36,0))="越高越好",INDEX(目标与口径!$G$5:$G$36,MATCH("order_accuracy",目标与口径!$A$5:$A$36,0))-$C$27,$C$27-INDEX(目标与口径!$G$5:$G$36,MATCH("order_accuracy",目标与口径!$A$5:$A$36,0)))/ABS(INDEX(目标与口径!$H$5:$H$36,MATCH("order_accuracy",目标与口径!$A$5:$A$36,0))-INDEX(目标与口径!$G$5:$G$36,MATCH("order_accuracy",目标与口径!$A$5:$A$36,0)))),0)*$F$27*$G$27*IF($E$27="红",2,1),2),0) -> 0 | K27: =INDEX(目标与口径!$N$5:$N$36,MATCH("order_accuracy",目标与口径!$A$5:$A$36,0)) -> PB-05 | L27: 按差错类型归因；同一 tag 一周 3 次以上 = 流程缺陷，进周复盘 | M27: =RANK($J$27,$J$5:$J$36,0) -> 16
A28: cash_over_short | B28: 现金短溢 | C28: =IFERROR(INDEX(每日经营日报!$BF$5:$BF$18,MATCH(店长看板!$B$3,每日经营日报!$A$5:$A$18,0)),0) -> 8.5 | D28: =INDEX(目标与口径!$F$5:$F$36,MATCH("cash_over_short",目标与口径!$A$5:$A$36,0)) -> 0 | E28: =IFERROR(IF(INDEX(目标与口径!$E$5:$E$36,MATCH("cash_over_short",目标与口径!$A$5:$A$36,0))="越高越好",IF($C$28>=INDEX(目标与口径!$G$5:$G$36,MATCH("cash_over_short",目标与口径!$A$5:$A$36,0)),"绿",IF($C$28>=INDEX(目标与口径!$H$5:$H$36,MATCH("cash_over_short",目标与口径!$A$5:$A$36,0)),"黄","红")),IF($C$28<=INDEX(目标与口径!$G$5:$G$36,MATCH("cash_over_short",目标与口径!$A$5:$A$36,0)),"绿",IF($C$28<=INDEX(目标与口径!$H$5:$H$36,MATCH("cash_over_short",目标与口径!$A$5:$A$36,0)),"黄","红"))),"—") -> 绿 | F28: =INDEX(目标与口径!$L$5:$L$36,MATCH("cash_over_short",目标与口径!$A$5:$A$36,0)) -> 0.35 | G28: =INDEX(目标与口径!$M$5:$M$36,MATCH("cash_over_short",目标与口径!$A$5:$A$36,0)) -> 0.9 | H28: =IF($F$28>=0.7,IF($G$28>=0.7,"Q1 今天就做","Q2 上报求援"),IF($G$28>=0.7,"Q3 顺手做掉","Q4 记录观察")) -> Q3 顺手做掉 | I28: =INDEX(目标与口径!$J$5:$J$36,MATCH("cash_over_short",目标与口径!$A$5:$A$36,0)) -> 值班经理 | J28: =IFERROR(ROUND(IFERROR(MAX(0,IF(INDEX(目标与口径!$E$5:$E$36,MATCH("cash_over_short",目标与口径!$A$5:$A$36,0))="越高越好",INDEX(目标与口径!$G$5:$G$36,MATCH("cash_over_short",目标与口径!$A$5:$A$36,0))-$C$28,$C$28-INDEX(目标与口径!$G$5:$G$36,MATCH("cash_over_short",目标与口径!$A$5:$A$36,0)))/ABS(INDEX(目标与口径!$H$5:$H$36,MATCH("cash_over_short",目标与口径!$A$5:$A$36,0))-INDEX(目标与口径!$G$5:$G$36,MATCH("cash_over_short",目标与口径!$A$5:$A$36,0)))),0)*$F$28*$G$28*IF($E$28="红",2,1),2),0) -> 0 | K28: =INDEX(目标与口径!$N$5:$N$36,MATCH("cash_over_short",目标与口径!$A$5:$A$36,0)) -> PB-08 | L28: 定位班次与收银员，复核交接记录，当天闭环不隔夜 | M28: =RANK($J$28,$J$5:$J$36,0) -> 16
A29: labor_cost_pct | B29: 人工成本率 | C29: =IFERROR(INDEX(每日经营日报!$Z$5:$Z$18,MATCH(店长看板!$B$3,每日经营日报!$A$5:$A$18,0)),0) -> 0.13246748 | D29: =INDEX(目标与口径!$F$5:$F$36,MATCH("labor_cost_pct",目标与口径!$A$5:$A$36,0)) -> 0.135 | E29: =IFERROR(IF(INDEX(目标与口径!$E$5:$E$36,MATCH("labor_cost_pct",目标与口径!$A$5:$A$36,0))="越高越好",IF($C$29>=INDEX(目标与口径!$G$5:$G$36,MATCH("labor_cost_pct",目标与口径!$A$5:$A$36,0)),"绿",IF($C$29>=INDEX(目标与口径!$H$5:$H$36,MATCH("labor_cost_pct",目标与口径!$A$5:$A$36,0)),"黄","红")),IF($C$29<=INDEX(目标与口径!$G$5:$G$36,MATCH("labor_cost_pct",目标与口径!$A$5:$A$36,0)),"绿",IF($C$29<=INDEX(目标与口径!$H$5:$H$36,MATCH("labor_cost_pct",目标与口径!$A$5:$A$36,0)),"黄","红"))),"—") -> 绿 | F29: =INDEX(目标与口径!$L$5:$L$36,MATCH("labor_cost_pct",目标与口径!$A$5:$A$36,0)) -> 0.9 | G29: =INDEX(目标与口径!$M$5:$M$36,MATCH("labor_cost_pct",目标与口径!$A$5:$A$36,0)) -> 0.8 | H29: =IF($F$29>=0.7,IF($G$29>=0.7,"Q1 今天就做","Q2 上报求援"),IF($G$29>=0.7,"Q3 顺手做掉","Q4 记录观察")) -> Q1 今天就做 | I29: =INDEX(目标与口径!$J$5:$J$36,MATCH("labor_cost_pct",目标与口径!$A$5:$A$36,0)) -> 店长 | J29: =IFERROR(ROUND(IFERROR(MAX(0,IF(INDEX(目标与口径!$E$5:$E$36,MATCH("labor_cost_pct",目标与口径!$A$5:$A$36,0))="越高越好",INDEX(目标与口径!$G$5:$G$36,MATCH("labor_cost_pct",目标与口径!$A$5:$A$36,0))-$C$29,$C$29-INDEX(目标与口径!$G$5:$G$36,MATCH("labor_cost_pct",目标与口径!$A$5:$A$36,0)))/ABS(INDEX(目标与口径!$H$5:$H$36,MATCH("labor_cost_pct",目标与口径!$A$5:$A$36,0))-INDEX(目标与口径!$G$5:$G$36,MATCH("labor_cost_pct",目标与口径!$A$5:$A$36,0)))),0)*$F$29*$G$29*IF($E$29="红",2,1),2),0) -> 0 | K29: =INDEX(目标与口径!$N$5:$N$36,MATCH("labor_cost_pct",目标与口径!$A$5:$A$36,0)) -> PB-07 | L29: 看 SPLH 与速度的组合：都差 = 排班结构错，调岗位不是加人头 | M29: =RANK($J$29,$J$5:$J$36,0) -> 16
A30: splh | B30: 人时销售 (SPLH) | C30: =IFERROR(INDEX(每日经营日报!$AA$5:$AA$18,MATCH(店长看板!$B$3,每日经营日报!$A$5:$A$18,0)),0) -> 215.14714 | D30: =INDEX(目标与口径!$F$5:$F$36,MATCH("splh",目标与口径!$A$5:$A$36,0)) -> 210 | E30: =IFERROR(IF(INDEX(目标与口径!$E$5:$E$36,MATCH("splh",目标与口径!$A$5:$A$36,0))="越高越好",IF($C$30>=INDEX(目标与口径!$G$5:$G$36,MATCH("splh",目标与口径!$A$5:$A$36,0)),"绿",IF($C$30>=INDEX(目标与口径!$H$5:$H$36,MATCH("splh",目标与口径!$A$5:$A$36,0)),"黄","红")),IF($C$30<=INDEX(目标与口径!$G$5:$G$36,MATCH("splh",目标与口径!$A$5:$A$36,0)),"绿",IF($C$30<=INDEX(目标与口径!$H$5:$H$36,MATCH("splh",目标与口径!$A$5:$A$36,0)),"黄","红"))),"—") -> 绿 | F30: =INDEX(目标与口径!$L$5:$L$36,MATCH("splh",目标与口径!$A$5:$A$36,0)) -> 0.85 | G30: =INDEX(目标与口径!$M$5:$M$36,MATCH("splh",目标与口径!$A$5:$A$36,0)) -> 0.85 | H30: =IF($F$30>=0.7,IF($G$30>=0.7,"Q1 今天就做","Q2 上报求援"),IF($G$30>=0.7,"Q3 顺手做掉","Q4 记录观察")) -> Q1 今天就做 | I30: =INDEX(目标与口径!$J$5:$J$36,MATCH("splh",目标与口径!$A$5:$A$36,0)) -> 值班经理 | J30: =IFERROR(ROUND(IFERROR(MAX(0,IF(INDEX(目标与口径!$E$5:$E$36,MATCH("splh",目标与口径!$A$5:$A$36,0))="越高越好",INDEX(目标与口径!$G$5:$G$36,MATCH("splh",目标与口径!$A$5:$A$36,0))-$C$30,$C$30-INDEX(目标与口径!$G$5:$G$36,MATCH("splh",目标与口径!$A$5:$A$36,0)))/ABS(INDEX(目标与口径!$H$5:$H$36,MATCH("splh",目标与口径!$A$5:$A$36,0))-INDEX(目标与口径!$G$5:$G$36,MATCH("splh",目标与口径!$A$5:$A$36,0)))),0)*$F$30*$G$30*IF($E$30="红",2,1),2),0) -> 0 | K30: =INDEX(目标与口径!$N$5:$N$36,MATCH("splh",目标与口径!$A$5:$A$36,0)) -> PB-07 | L30: 看 SPLH 与速度的组合：都差 = 排班结构错，调岗位不是加人头 | M30: =RANK($J$30,$J$5:$J$36,0) -> 16
A31: critical_temp_fail | B31: 关键温度点异常数 | C31: =IFERROR(INDEX(每日经营日报!$AN$5:$AN$18,MATCH(店长看板!$B$3,每日经营日报!$A$5:$A$18,0)),0) -> 0 | D31: =INDEX(目标与口径!$F$5:$F$36,MATCH("critical_temp_fail",目标与口径!$A$5:$A$36,0)) -> 0 | E31: =IFERROR(IF(INDEX(目标与口径!$E$5:$E$36,MATCH("critical_temp_fail",目标与口径!$A$5:$A$36,0))="越高越好",IF($C$31>=INDEX(目标与口径!$G$5:$G$36,MATCH("critical_temp_fail",目标与口径!$A$5:$A$36,0)),"绿",IF($C$31>=INDEX(目标与口径!$H$5:$H$36,MATCH("critical_temp_fail",目标与口径!$A$5:$A$36,0)),"黄","红")),IF($C$31<=INDEX(目标与口径!$G$5:$G$36,MATCH("critical_temp_fail",目标与口径!$A$5:$A$36,0)),"绿",IF($C$31<=INDEX(目标与口径!$H$5:$H$36,MATCH("critical_temp_fail",目标与口径!$A$5:$A$36,0)),"黄","红"))),"—") -> 绿 | F31: =INDEX(目标与口径!$L$5:$L$36,MATCH("critical_temp_fail",目标与口径!$A$5:$A$36,0)) -> 1 | G31: =INDEX(目标与口径!$M$5:$M$36,MATCH("critical_temp_fail",目标与口径!$A$5:$A$36,0)) -> 0.9 | H31: =IF($F$31>=0.7,IF($G$31>=0.7,"Q1 今天就做","Q2 上报求援"),IF($G$31>=0.7,"Q3 顺手做掉","Q4 记录观察")) -> Q1 今天就做 | I31: =INDEX(目标与口径!$J$5:$J$36,MATCH("critical_temp_fail",目标与口径!$A$5:$A$36,0)) -> 值班经理 | J31: =IFERROR(ROUND(IFERROR(MAX(0,IF(INDEX(目标与口径!$E$5:$E$36,MATCH("critical_temp_fail",目标与口径!$A$5:$A$36,0))="越高越好",INDEX(目标与口径!$G$5:$G$36,MATCH("critical_temp_fail",目标与口径!$A$5:$A$36,0))-$C$31,$C$31-INDEX(目标与口径!$G$5:$G$36,MATCH("critical_temp_fail",目标与口径!$A$5:$A$36,0)))/ABS(INDEX(目标与口径!$H$5:$H$36,MATCH("critical_temp_fail",目标与口径!$A$5:$A$36,0))-INDEX(目标与口径!$G$5:$G$36,MATCH("critical_temp_fail",目标与口径!$A$5:$A$36,0)))),0)*$F$31*$G$31*IF($E$31="红",2,1),2),0) -> 0 | K31: =INDEX(目标与口径!$N$5:$N$36,MATCH("critical_temp_fail",目标与口径!$A$5:$A$36,0)) -> PB-09 | L31: 关键项 fail 立即停止该产品出品，整改复检通过才恢复 | M31: =RANK($J$31,$J$5:$J$36,0) -> 16
A32: food_safety_score | B32: 食安日检得分 | C32: =IFERROR(INDEX(每日经营日报!$AM$5:$AM$18,MATCH(店长看板!$B$3,每日经营日报!$A$5:$A$18,0)),0) -> 100 | D32: =INDEX(目标与口径!$F$5:$F$36,MATCH("food_safety_score",目标与口径!$A$5:$A$36,0)) -> 100 | E32: =IFERROR(IF(INDEX(目标与口径!$E$5:$E$36,MATCH("food_safety_score",目标与口径!$A$5:$A$36,0))="越高越好",IF($C$32>=INDEX(目标与口径!$G$5:$G$36,MATCH("food_safety_score",目标与口径!$A$5:$A$36,0)),"绿",IF($C$32>=INDEX(目标与口径!$H$5:$H$36,MATCH("food_safety_score",目标与口径!$A$5:$A$36,0)),"黄","红")),IF($C$32<=INDEX(目标与口径!$G$5:$G$36,MATCH("food_safety_score",目标与口径!$A$5:$A$36,0)),"绿",IF($C$32<=INDEX(目标与口径!$H$5:$H$36,MATCH("food_safety_score",目标与口径!$A$5:$A$36,0)),"黄","红"))),"—") -> 绿 | F32: =INDEX(目标与口径!$L$5:$L$36,MATCH("food_safety_score",目标与口径!$A$5:$A$36,0)) -> 1 | G32: =INDEX(目标与口径!$M$5:$M$36,MATCH("food_safety_score",目标与口径!$A$5:$A$36,0)) -> 0.95 | H32: =IF($F$32>=0.7,IF($G$32>=0.7,"Q1 今天就做","Q2 上报求援"),IF($G$32>=0.7,"Q3 顺手做掉","Q4 记录观察")) -> Q1 今天就做 | I32: =INDEX(目标与口径!$J$5:$J$36,MATCH("food_safety_score",目标与口径!$A$5:$A$36,0)) -> 店长 | J32: =IFERROR(ROUND(IFERROR(MAX(0,IF(INDEX(目标与口径!$E$5:$E$36,MATCH("food_safety_score",目标与口径!$A$5:$A$36,0))="越高越好",INDEX(目标与口径!$G$5:$G$36,MATCH("food_safety_score",目标与口径!$A$5:$A$36,0))-$C$32,$C$32-INDEX(目标与口径!$G$5:$G$36,MATCH("food_safety_score",目标与口径!$A$5:$A$36,0)))/ABS(INDEX(目标与口径!$H$5:$H$36,MATCH("food_safety_score",目标与口径!$A$5:$A$36,0))-INDEX(目标与口径!$G$5:$G$36,MATCH("food_safety_score",目标与口径!$A$5:$A$36,0)))),0)*$F$32*$G$32*IF($E$32="红",2,1),2),0) -> 0 | K32: =INDEX(目标与口径!$N$5:$N$36,MATCH("food_safety_score",目标与口径!$A$5:$A$36,0)) -> PB-09 | L32: 关键项 fail 立即停止该产品出品，整改复检通过才恢复 | M32: =RANK($J$32,$J$5:$J$36,0) -> 16
A33: attendance_rate | B33: 出勤达成率 | C33: =IFERROR(INDEX(每日经营日报!$AV$5:$AV$18,MATCH(店长看板!$B$3,每日经营日报!$A$5:$A$18,0)),0) -> 1 | D33: =INDEX(目标与口径!$F$5:$F$36,MATCH("attendance_rate",目标与口径!$A$5:$A$36,0)) -> 1 | E33: =IFERROR(IF(INDEX(目标与口径!$E$5:$E$36,MATCH("attendance_rate",目标与口径!$A$5:$A$36,0))="越高越好",IF($C$33>=INDEX(目标与口径!$G$5:$G$36,MATCH("attendance_rate",目标与口径!$A$5:$A$36,0)),"绿",IF($C$33>=INDEX(目标与口径!$H$5:$H$36,MATCH("attendance_rate",目标与口径!$A$5:$A$36,0)),"黄","红")),IF($C$33<=INDEX(目标与口径!$G$5:$G$36,MATCH("attendance_rate",目标与口径!$A$5:$A$36,0)),"绿",IF($C$33<=INDEX(目标与口径!$H$5:$H$36,MATCH("attendance_rate",目标与口径!$A$5:$A$36,0)),"黄","红"))),"—") -> 绿 | F33: =INDEX(目标与口径!$L$5:$L$36,MATCH("attendance_rate",目标与口径!$A$5:$A$36,0)) -> 0.75 | G33: =INDEX(目标与口径!$M$5:$M$36,MATCH("attendance_rate",目标与口径!$A$5:$A$36,0)) -> 0.7 | H33: =IF($F$33>=0.7,IF($G$33>=0.7,"Q1 今天就做","Q2 上报求援"),IF($G$33>=0.7,"Q3 顺手做掉","Q4 记录观察")) -> Q1 今天就做 | I33: =INDEX(目标与口径!$J$5:$J$36,MATCH("attendance_rate",目标与口径!$A$5:$A$36,0)) -> 值班经理 | J33: =IFERROR(ROUND(IFERROR(MAX(0,IF(INDEX(目标与口径!$E$5:$E$36,MATCH("attendance_rate",目标与口径!$A$5:$A$36,0))="越高越好",INDEX(目标与口径!$G$5:$G$36,MATCH("attendance_rate",目标与口径!$A$5:$A$36,0))-$C$33,$C$33-INDEX(目标与口径!$G$5:$G$36,MATCH("attendance_rate",目标与口径!$A$5:$A$36,0)))/ABS(INDEX(目标与口径!$H$5:$H$36,MATCH("attendance_rate",目标与口径!$A$5:$A$36,0))-INDEX(目标与口径!$G$5:$G$36,MATCH("attendance_rate",目标与口径!$A$5:$A$36,0)))),0)*$F$33*$G$33*IF($E$33="红",2,1),2),0) -> 0 | K33: =INDEX(目标与口径!$N$5:$N$36,MATCH("attendance_rate",目标与口径!$A$5:$A$36,0)) -> PB-07 | L33: 看 SPLH 与速度的组合：都差 = 排班结构错，调岗位不是加人头 | M33: =RANK($J$33,$J$5:$J$36,0) -> 16
A34: crew_turnover_30d | B34: 30日员工流失率 | C34: =IFERROR(INDEX(每日经营日报!$BA$5:$BA$18,MATCH(店长看板!$B$3,每日经营日报!$A$5:$A$18,0)),0) -> 0.047619048 | D34: =INDEX(目标与口径!$F$5:$F$36,MATCH("crew_turnover_30d",目标与口径!$A$5:$A$36,0)) -> 0.05 | E34: =IFERROR(IF(INDEX(目标与口径!$E$5:$E$36,MATCH("crew_turnover_30d",目标与口径!$A$5:$A$36,0))="越高越好",IF($C$34>=INDEX(目标与口径!$G$5:$G$36,MATCH("crew_turnover_30d",目标与口径!$A$5:$A$36,0)),"绿",IF($C$34>=INDEX(目标与口径!$H$5:$H$36,MATCH("crew_turnover_30d",目标与口径!$A$5:$A$36,0)),"黄","红")),IF($C$34<=INDEX(目标与口径!$G$5:$G$36,MATCH("crew_turnover_30d",目标与口径!$A$5:$A$36,0)),"绿",IF($C$34<=INDEX(目标与口径!$H$5:$H$36,MATCH("crew_turnover_30d",目标与口径!$A$5:$A$36,0)),"黄","红"))),"—") -> 绿 | F34: =INDEX(目标与口径!$L$5:$L$36,MATCH("crew_turnover_30d",目标与口径!$A$5:$A$36,0)) -> 0.8 | G34: =INDEX(目标与口径!$M$5:$M$36,MATCH("crew_turnover_30d",目标与口径!$A$5:$A$36,0)) -> 0.5 | H34: =IF($F$34>=0.7,IF($G$34>=0.7,"Q1 今天就做","Q2 上报求援"),IF($G$34>=0.7,"Q3 顺手做掉","Q4 记录观察")) -> Q2 上报求援 | I34: =INDEX(目标与口径!$J$5:$J$36,MATCH("crew_turnover_30d",目标与口径!$A$5:$A$36,0)) -> 店长 | J34: =IFERROR(ROUND(IFERROR(MAX(0,IF(INDEX(目标与口径!$E$5:$E$36,MATCH("crew_turnover_30d",目标与口径!$A$5:$A$36,0))="越高越好",INDEX(目标与口径!$G$5:$G$36,MATCH("crew_turnover_30d",目标与口径!$A$5:$A$36,0))-$C$34,$C$34-INDEX(目标与口径!$G$5:$G$36,MATCH("crew_turnover_30d",目标与口径!$A$5:$A$36,0)))/ABS(INDEX(目标与口径!$H$5:$H$36,MATCH("crew_turnover_30d",目标与口径!$A$5:$A$36,0))-INDEX(目标与口径!$G$5:$G$36,MATCH("crew_turnover_30d",目标与口径!$A$5:$A$36,0)))),0)*$F$34*$G$34*IF($E$34="红",2,1),2),0) -> 0 | K34: =INDEX(目标与口径!$N$5:$N$36,MATCH("crew_turnover_30d",目标与口径!$A$5:$A$36,0)) -> PB-12 | L34: 按司龄段/岗位下钻；<90 天流失高 = 新人被丢在高峰上 | M34: =RANK($J$34,$J$5:$J$36,0) -> 16
A35: complaints_per_1k | B35: 千单投诉数 | C35: =IFERROR(INDEX(每日经营日报!$AL$5:$AL$18,MATCH(店长看板!$B$3,每日经营日报!$A$5:$A$18,0)),0) -> 0.63938619 | D35: =INDEX(目标与口径!$F$5:$F$36,MATCH("complaints_per_1k",目标与口径!$A$5:$A$36,0)) -> 0.8 | E35: =IFERROR(IF(INDEX(目标与口径!$E$5:$E$36,MATCH("complaints_per_1k",目标与口径!$A$5:$A$36,0))="越高越好",IF($C$35>=INDEX(目标与口径!$G$5:$G$36,MATCH("complaints_per_1k",目标与口径!$A$5:$A$36,0)),"绿",IF($C$35>=INDEX(目标与口径!$H$5:$H$36,MATCH("complaints_per_1k",目标与口径!$A$5:$A$36,0)),"黄","红")),IF($C$35<=INDEX(目标与口径!$G$5:$G$36,MATCH("complaints_per_1k",目标与口径!$A$5:$A$36,0)),"绿",IF($C$35<=INDEX(目标与口径!$H$5:$H$36,MATCH("complaints_per_1k",目标与口径!$A$5:$A$36,0)),"黄","红"))),"—") -> 绿 | F35: =INDEX(目标与口径!$L$5:$L$36,MATCH("complaints_per_1k",目标与口径!$A$5:$A$36,0)) -> 0.75 | G35: =INDEX(目标与口径!$M$5:$M$36,MATCH("complaints_per_1k",目标与口径!$A$5:$A$36,0)) -> 0.7 | H35: =IF($F$35>=0.7,IF($G$35>=0.7,"Q1 今天就做","Q2 上报求援"),IF($G$35>=0.7,"Q3 顺手做掉","Q4 记录观察")) -> Q1 今天就做 | I35: =INDEX(目标与口径!$J$5:$J$36,MATCH("complaints_per_1k",目标与口径!$A$5:$A$36,0)) -> 值班经理 | J35: =IFERROR(ROUND(IFERROR(MAX(0,IF(INDEX(目标与口径!$E$5:$E$36,MATCH("complaints_per_1k",目标与口径!$A$5:$A$36,0))="越高越好",INDEX(目标与口径!$G$5:$G$36,MATCH("complaints_per_1k",目标与口径!$A$5:$A$36,0))-$C$35,$C$35-INDEX(目标与口径!$G$5:$G$36,MATCH("complaints_per_1k",目标与口径!$A$5:$A$36,0)))/ABS(INDEX(目标与口径!$H$5:$H$36,MATCH("complaints_per_1k",目标与口径!$A$5:$A$36,0))-INDEX(目标与口径!$G$5:$G$36,MATCH("complaints_per_1k",目标与口径!$A$5:$A$36,0)))),0)*$F$35*$G$35*IF($E$35="红",2,1),2),0) -> 0 | K35: =INDEX(目标与口径!$N$5:$N$36,MATCH("complaints_per_1k",目标与口径!$A$5:$A$36,0)) -> PB-05 | L35: 按差错类型归因；同一 tag 一周 3 次以上 = 流程缺陷，进周复盘 | M35: =RANK($J$35,$J$5:$J$36,0) -> 16
A36: csat | B36: 顾客满意度 | C36: =IFERROR(INDEX(每日经营日报!$BD$5:$BD$18,MATCH(店长看板!$B$3,每日经营日报!$A$5:$A$18,0)),0) -> 92.571429 | D36: =INDEX(目标与口径!$F$5:$F$36,MATCH("csat",目标与口径!$A$5:$A$36,0)) -> 88 | E36: =IFERROR(IF(INDEX(目标与口径!$E$5:$E$36,MATCH("csat",目标与口径!$A$5:$A$36,0))="越高越好",IF($C$36>=INDEX(目标与口径!$G$5:$G$36,MATCH("csat",目标与口径!$A$5:$A$36,0)),"绿",IF($C$36>=INDEX(目标与口径!$H$5:$H$36,MATCH("csat",目标与口径!$A$5:$A$36,0)),"黄","红")),IF($C$36<=INDEX(目标与口径!$G$5:$G$36,MATCH("csat",目标与口径!$A$5:$A$36,0)),"绿",IF($C$36<=INDEX(目标与口径!$H$5:$H$36,MATCH("csat",目标与口径!$A$5:$A$36,0)),"黄","红"))),"—") -> 绿 | F36: =INDEX(目标与口径!$L$5:$L$36,MATCH("csat",目标与口径!$A$5:$A$36,0)) -> 0.9 | G36: =INDEX(目标与口径!$M$5:$M$36,MATCH("csat",目标与口径!$A$5:$A$36,0)) -> 0.6 | H36: =IF($F$36>=0.7,IF($G$36>=0.7,"Q1 今天就做","Q2 上报求援"),IF($G$36>=0.7,"Q3 顺手做掉","Q4 记录观察")) -> Q2 上报求援 | I36: =INDEX(目标与口径!$J$5:$J$36,MATCH("csat",目标与口径!$A$5:$A$36,0)) -> 店长 | J36: =IFERROR(ROUND(IFERROR(MAX(0,IF(INDEX(目标与口径!$E$5:$E$36,MATCH("csat",目标与口径!$A$5:$A$36,0))="越高越好",INDEX(目标与口径!$G$5:$G$36,MATCH("csat",目标与口径!$A$5:$A$36,0))-$C$36,$C$36-INDEX(目标与口径!$G$5:$G$36,MATCH("csat",目标与口径!$A$5:$A$36,0)))/ABS(INDEX(目标与口径!$H$5:$H$36,MATCH("csat",目标与口径!$A$5:$A$36,0))-INDEX(目标与口径!$G$5:$G$36,MATCH("csat",目标与口径!$A$5:$A$36,0)))),0)*$F$36*$G$36*IF($E$36="红",2,1),2),0) -> 0 | K36: =INDEX(目标与口径!$N$5:$N$36,MATCH("csat",目标与口径!$A$5:$A$36,0)) -> PB-05 | L36: 按差错类型归因；同一 tag 一周 3 次以上 = 流程缺陷，进周复盘 | M36: =RANK($J$36,$J$5:$J$36,0) -> 16
A38: 四象限的含义
A39: 象限 | B39: 影响度 | C39: 可控度 | D39: 含义
A40: Q1 今天就做 | B40: 高 | C40: 高 | D40: 这就是今天班前会的内容
A41: Q2 上报求援 | B41: 高 | C41: 低 | D41: 影响大但不在你手上——找营运经理/供应商/总部，别自己耗一整天
A42: Q3 顺手做掉 | B42: 低 | C42: 高 | D42: 一动就好，交给值班经理清单化处理
A43: Q4 记录观察 | B43: 低 | C43: 低 | D43: 别在今天的会上讲，记进周复盘看趋势
A45: 行序在生成时按行动分排好，但「排名」列（M）是公式：改了阈值或影响度/可控度，排名会立刻重算，「店长看板」的三件事也跟着换人——它取的是排名前三，不是前三行。想让行序也跟着动，用「数据 → 排序」按 J 列降序即可。

Sheet 时段矩阵
A1: 时段矩阵 · Interval Matrix（15 分钟 × 指标）
A2: 2026-08-18 全天，每格 15 分钟。看法只有一条：单点飘红是噪声，连成一片才是问题——下方自动列出了连续 2 格以上的告警窗口。
A4: 指标 | B4: 单位 | C4: 06:00 | D4: 06:15 | E4: 06:30 | F4: 06:45 | G4: 07:00 | H4: 07:15 | I4: 07:30 | J4: 07:45 | K4: 08:00 | L4: 08:15 | M4: 08:30 | N4: 08:45 | O4: 09:00 | P4: 09:15 | Q4: 09:30 | R4: 09:45 | S4: 10:00 | T4: 10:15 | U4: 10:30 | V4: 10:45 | W4: 11:00 | X4: 11:15 | Y4: 11:30 | Z4: 11:45 | AA4: 12:00 | AB4: 12:15 | AC4: 12:30 | AD4: 12:45 | AE4: 13:00 | AF4: 13:15 | AG4: 13:30 | AH4: 13:45 | AI4: 14:00 | AJ4: 14:15 | AK4: 14:30 | AL4: 14:45 | AM4: 15:00 | AN4: 15:15 | AO4: 15:30 | AP4: 15:45 | AQ4: 16:00 | AR4: 16:15 | AS4: 16:30 | AT4: 16:45 | AU4: 17:00 | AV4: 17:15 | AW4: 17:30 | AX4: 17:45 | AY4: 18:00 | AZ4: 18:15 | BA4: 18:30 | BB4: 18:45 | BC4: 19:00 | BD4: 19:15 | BE4: 19:30 | BF4: 19:45 | BG4: 20:00 | BH4: 20:15 | BI4: 20:30 | BJ4: 20:45 | BK4: 21:00 | BL4: 21:15 | BM4: 21:30 | BN4: 21:45 | BO4: 22:00 | BP4: 22:15 | BQ4: 22:30 | BR4: 22:45 | BS4: 23:00 | BT4: 23:15 | BU4: 23:30 | BV4: 23:45
A5: 销售达成率 | B5: % | C5: 0.9901 | D5: 0.9146 | E5: 1.1055 | F5: 0.9484 | G5: 0.875 | H5: 0.9518 | I5: 1.1172 | J5: 0.7906 | K5: 0.9924 | L5: 0.8458 | M5: 1.1284 | N5: 1.2589 | O5: 0.9964 | P5: 0.9336 | Q5: 1.4484 | R5: 0.8687 | S5: 1.3017 | T5: 1.3313 | U5: 0.9139 | V5: 0.9174 | W5: 0.87 | X5: 0.9369 | Y5: 1.0686 | Z5: 0.8906 | AA5: 0.9167 | AB5: 1.1057 | AC5: 1.0317 | AD5: 0.757 | AE5: 0.9398 | AF5: 0.8861 | AG5: 0.7978 | AH5: 0.8968 | AI5: 0.852 | AJ5: 0.9788 | AK5: 0.8916 | AL5: 0.8766 | AM5: 1.029 | AN5: 1.2627 | AO5: 1.0296 | AP5: 0.8203 | AQ5: 0.9648 | AR5: 0.9837 | AS5: 1.0514 | AT5: 0.6773 | AU5: 1.0449 | AV5: 1.2569 | AW5: 1.1043 | AX5: 0.9613 | AY5: 0.8858 | AZ5: 1.1425 | BA5: 0.874 | BB5: 1.4121 | BC5: 1.0442 | BD5: 1.2125 | BE5: 0.9006 | BF5: 0.9066 | BG5: 1.0093 | BH5: 0.8613 | BI5: 1.0143 | BJ5: 1.0292 | BK5: 0.9616 | BL5: 1.1738 | BM5: 0.8183 | BN5: 0.8679 | BO5: 1.0755 | BP5: 0.8299 | BQ5: 0.7631 | BR5: 1.1835 | BS5: 1.0998 | BT5: 1.072 | BU5: 0.7583 | BV5: 0.438
A6: 服务速度达标率 | B6: % | C6: 0.5714 | D6: 1 | E6: 0.9231 | F6: 0.9375 | G6: 0.9444 | H6: 0.95 | I6: 0.9524 | J6: 0.9524 | K6: 1 | L6: 0.9444 | M6: 1 | N6: 0.9231 | O6: 1 | P6: 1 | Q6: 1 | R6: 1 | S6: 1 | T6: 0.875 | U6: 0.9286 | V6: 0.9091 | W6: 0.8438 | X6: 0.8605 | Y6: 0.566 | Z6: 0.6333 | AA6: 0.7097 | AB6: 0.7458 | AC6: 0.7451 | AD6: 0.878 | AE6: 0.9 | AF6: 0.85 | AG6: 1 | AH6: 0.8571 | AI6: 0.7857 | AJ6: 1 | AK6: 1 | AL6: 1 | AM6: 0.913 | AN6: 0.913 | AO6: 0.9091 | AP6: 0.9048 | AQ6: 0.8333 | AR6: 0.9375 | AS6: 0.7692 | AT6: 1 | AU6: 0.7727 | AV6: 0.5862 | AW6: 0.4865 | AX6: 0.4651 | AY6: 0.5 | AZ6: 0.54 | BA6: 0.4792 | BB6: 0.4545 | BC6: 0.3947 | BD6: 0.5161 | BE6: 0.6522 | BF6: 0.8235 | BG6: 1 | BH6: 1 | BI6: 1 | BJ6: 1 | BK6: 1 | BL6: 0.9444 | BM6: 0.8 | BN6: 0.95 | BO6: 0.8421 | BP6: 0.8235 | BQ6: 1 | BR6: 0.8182 | BS6: 0.875 | BT6: 1 | BU6: 1 | BV6: 1
A7: 得来速总时长 | B7: 秒 | C7: 171.6 | D7: 127.8 | E7: 143.4 | F7: 133.9 | G7: 129.4333 | H7: 145.725 | I7: 132.45 | J7: 143.45 | K7: 140.85 | L7: 147.0167 | M7: 136.06 | N7: 142.9667 | O7: 115.02 | P7: 128.6 | Q7: 159.3 | R7: 151.7 | T7: 162.5 | U7: 163.1 | V7: 139.25 | W7: 126.8667 | X7: 173.0556 | Y7: 174.7538 | Z7: 180.25 | AA7: 169.9375 | AB7: 153.125 | AC7: 151.2667 | AD7: 145.7 | AE7: 149.1333 | AF7: 145.225 | AG7: 156.2 | AH7: 147.35 | AI7: 141.9 | AJ7: 141.5667 | AK7: 127.05 | AL7: 127.9 | AM7: 137.7625 | AN7: 156.8333 | AO7: 136.7 | AP7: 163.7 | AQ7: 122 | AR7: 147.025 | AS7: 157.75 | AT7: 146.3 | AU7: 172.75 | AV7: 179.78 | AW7: 189.4125 | AX7: 189.625 | AY7: 197.86 | AZ7: 183.45 | BA7: 186.0571 | BB7: 191.79 | BC7: 189.825 | BD7: 185.75 | BE7: 153.45 | BF7: 152.25 | BG7: 122.8 | BH7: 149.2 | BI7: 140.4 | BK7: 132.74 | BL7: 137.8 | BM7: 157.45 | BN7: 133.8714 | BO7: 146.85 | BP7: 149.7 | BQ7: 116.6667 | BR7: 156.9 | BS7: 143.65 | BT7: 96.9 | BU7: 154.1 | BV7: 128.3
A8: 后厨制作时长 | B8: 秒 | C8: 84.6143 | D8: 79.69 | E8: 78.0538 | F8: 79.7125 | G8: 77.5833 | H8: 80.275 | I8: 82.1667 | J8: 74.5238 | K8: 77.745 | L8: 79.35 | M8: 79.2187 | N8: 77.1231 | O8: 72.12 | P8: 86.5571 | Q8: 80.7 | R8: 60.7 | S8: 84.2 | T8: 84.0125 | U8: 82.8357 | V8: 81.6409 | W8: 81.9656 | X8: 90.7628 | Y8: 99.0434 | Z8: 89.35 | AA8: 88.4565 | AB8: 90.7593 | AC8: 92.1922 | AD8: 87.0756 | AE8: 83.7967 | AF8: 81.975 | AG8: 72.0833 | AH8: 78.5714 | AI8: 75.5214 | AJ8: 74.8941 | AK8: 80.63 | AL8: 76.5 | AM8: 77.2174 | AN8: 80.0043 | AO8: 80.9591 | AP8: 74.7429 | AQ8: 85.6778 | AR8: 82.5938 | AS8: 84.0923 | AT8: 72.09 | AU8: 91.0591 | AV8: 89.031 | AW8: 100.127 | AX8: 91.8163 | AY8: 97.9 | AZ8: 94.57 | BA8: 99.0938 | BB8: 93.6659 | BC8: 99.0921 | BD8: 96.7645 | BE8: 88.6217 | BF8: 82.6941 | BG8: 81.6182 | BH8: 80.7714 | BI8: 77.2 | BJ8: 68.95 | BK8: 72.5438 | BL8: 79.9111 | BM8: 74.295 | BN8: 74.41 | BO8: 84.1474 | BP8: 76.9529 | BQ8: 76.6071 | BR8: 83.2636 | BS8: 81.2125 | BT8: 78.4167 | BU8: 72.225 | BV8: 72.2
A9: 人时销售 (SPLH) | B9: CNY/工时 | C9: 164 | D9: 165.381 | E9: 193.6875 | F9: 209.5076 | G9: 230.7487 | H9: 224.7961 | I9: 220.8273 | J9: 181.049 | K9: 222.3392 | L9: 214.3369 | M9: 230.0989 | N9: 209.05 | O9: 219.5995 | P9: 121.893 | Q9: 159.535 | R9: 74.7209 | S9: 166.8792 | T9: 183.632 | U9: 221.9519 | V9: 268.209 | W9: 276.2904 | X9: 277.5696 | Y9: 325.4548 | Z9: 290.0205 | AA9: 272.9394 | AB9: 303.7778 | AC9: 316.3963 | AD9: 276.4479 | AE9: 252.5796 | AF9: 234.4032 | AG9: 170.6682 | AH9: 154.06 | AI9: 193.5804 | AJ9: 201.2308 | AK9: 237.4176 | AL9: 233.9642 | AM9: 281.3291 | AN9: 280.0725 | AO9: 252.1522 | AP9: 216.1064 | AQ9: 228.8549 | AR9: 226.5941 | AS9: 190.8792 | AT9: 135.3408 | AU9: 296.2862 | AV9: 298.7536 | AW9: 330.3146 | AX9: 309.6898 | AY9: 305.9366 | AZ9: 331.4631 | BA9: 292.4624 | BB9: 313.97 | BC9: 344.2171 | BD9: 317.2907 | BE9: 308.6655 | BF9: 239.1642 | BG9: 173.5045 | BH9: 131.8817 | BI9: 120.7026 | BJ9: 56.032 | BK9: 163.1193 | BL9: 229.7607 | BM9: 220.6978 | BN9: 238.8736 | BO9: 244.6711 | BP9: 203.0881 | BQ9: 186.816 | BR9: 224.5636 | BS9: 193.3314 | BT9: 101.8443 | BU9: 94.8312 | BV9: 23.9156
A11: 连续告警窗口（连续 ≥2 个 15 分钟非绿）
A12: 指标 | B12: 从 | C12: 到 | D12: 连续格数 | E12: 均值 | F12: 最差 | G12: 含红灯 | H12: → 说明
A13: 销售达成率 | B13: 12:45 | C13: 14:45 | D13: 9 | E13: 0.87515592 | F13: 0.75699908 | G13: 是 | H13: 连片告警，去「交叉矩阵」确认是某个渠道的结构问题还是整段的产能问题
A14: 销售达成率 | B14: 10:30 | C14: 11:15 | D14: 4 | E14: 0.909548 | F14: 0.87003948 | G14: 是 | H14: 连片告警，去「交叉矩阵」确认是某个渠道的结构问题还是整段的产能问题
A15: 销售达成率 | B15: 06:45 | C15: 07:15 | D15: 3 | E15: 0.92504815 | F15: 0.87495463 | G15: 是 | H15: 连片告警，去「交叉矩阵」确认是某个渠道的结构问题还是整段的产能问题
A16: 销售达成率 | B16: 11:45 | C16: 12:00 | D16: 2 | E16: 0.90364562 | F16: 0.89056164 | G16: 是 | H16: 连片告警，去「交叉矩阵」确认是某个渠道的结构问题还是整段的产能问题
A17: 销售达成率 | B17: 15:45 | C17: 16:00 | D17: 2 | E17: 0.89254948 | F17: 0.82032577 | G17: 是 | H17: 连片告警，去「交叉矩阵」确认是某个渠道的结构问题还是整段的产能问题
A18: 销售达成率 | B18: 17:45 | C18: 18:00 | D18: 2 | E18: 0.92353315 | F18: 0.8858085 | G18: 是 | H18: 连片告警，去「交叉矩阵」确认是某个渠道的结构问题还是整段的产能问题
A19: 销售达成率 | B19: 19:30 | C19: 19:45 | D19: 2 | E19: 0.90360497 | F19: 0.9005639 | G19: 是 | H19: 连片告警，去「交叉矩阵」确认是某个渠道的结构问题还是整段的产能问题
A20: 销售达成率 | B20: 21:30 | C20: 21:45 | D20: 2 | E20: 0.84312983 | F20: 0.81831012 | G20: 是 | H20: 连片告警，去「交叉矩阵」确认是某个渠道的结构问题还是整段的产能问题
A21: 销售达成率 | B21: 22:15 | C21: 22:30 | D21: 2 | E21: 0.79650954 | F21: 0.76314972 | G21: 是 | H21: 连片告警，去「交叉矩阵」确认是某个渠道的结构问题还是整段的产能问题
A22: 销售达成率 | B22: 23:30 | C22: 23:45 | D22: 2 | E22: 0.59815402 | F22: 0.43802164 | G22: 是 | H22: 连片告警，去「交叉矩阵」确认是某个渠道的结构问题还是整段的产能问题
A23: 服务速度达标率 | B23: 17:00 | C23: 19:45 | D23: 12 | E23: 0.55590152 | F23: 0.39473684 | G23: 是 | H23: 连片告警，去「交叉矩阵」确认是某个渠道的结构问题还是整段的产能问题
A24: 服务速度达标率 | B24: 11:00 | C24: 12:45 | D24: 8 | E24: 0.74777164 | F24: 0.56603774 | G24: 是 | H24: 连片告警，去「交叉矩阵」确认是某个渠道的结构问题还是整段的产能问题
... A34: 人时销售 (SPLH) | B34: 22:15 | C34: 22:30 | D34: 2 | E34: 194.95205 | F34: 186.816 | G34: 否 | H34: 连片告警，去「交叉矩阵」确认是某个渠道的结构问题还是整段的产能问题
A36: 为什么用 15 分钟而不是小时：排班和备货的最小调整单位就是 15 分钟。按小时看，一个 20 分钟的塌陷会被两边的好数据稀释掉，什么也看不见。

Sheet 交叉矩阵
A1: 交叉矩阵 · Cross Matrix（时段 × 渠道）
A2: 一张表同时读出两种问题：某一列全红 = 结构问题（那个渠道的流程本身有毛病，加人没用）；某一行全红 = 产能问题（那个时段人不够，排班能解决）。两种问题的动作、责任人、时间尺度都不一样。
A4: 服务速度达标率（%） · 时段 × 渠道
A5: 时段 | B5: 前台点餐 | C5: 自助点餐机 | D5: 得来速 | E5: 小程序自取 | F5: 外送 | G5: 行合计/均值 | H5: 读法
A6: 早餐 | B6: 0.9231 | C6: 1 | D6: 0.9718 | E6: 1 | F6: 0.7391 | G6: =IFERROR(AVERAGE(B6:F6),0) -> 0.9268
A7: 午市 | B7: 0.7439 | C7: 0.9437 | D7: 0.7812 | E7: 0.8182 | F7: 0.5175 | G7: =IFERROR(AVERAGE(B7:F7),0) -> 0.7609
A8: 下午茶 | B8: 0.96 | C8: 1 | D8: 0.9318 | E8: 0.9565 | F8: 0.7719 | G8: =IFERROR(AVERAGE(B8:F8),0) -> 0.92404
A9: 晚市 | B9: 0.5 | C9: 0.8833 | D9: 0.4717 | E9: 0.6809 | F9: 0.2478 | G9: =IFERROR(AVERAGE(B9:F9),0) -> 0.55674
A10: 夜宵 | B10: 0.9375 | C10: 1 | D10: 0.9722 | E10: 1 | F10: 0.7969 | G10: =IFERROR(AVERAGE(B10:F10),0) -> 0.94132
A11: 列合计/均值 | B11: =IFERROR(AVERAGE(B6:B10),0) -> 0.8129 | C11: =IFERROR(AVERAGE(C6:C10),0) -> 0.9654 | D11: =IFERROR(AVERAGE(D6:D10),0) -> 0.82574 | E11: =IFERROR(AVERAGE(E6:E10),0) -> 0.89112 | F11: =IFERROR(AVERAGE(F6:F10),0) -> 0.61464
A12: → 最拖后腿的格子：晚市 × 外送（拖累度 5.5）
A14: 净销售额（CNY） · 时段 × 渠道
A15: 时段 | B15: 前台点餐 | C15: 自助点餐机 | D15: 得来速 | E15: 小程序自取 | F15: 外送 | G15: 行合计/均值 | H15: 读法
A16: 早餐 | B16: 1203.67 | C16: 2265.05 | D16: 2349.78 | E16: 803.75 | F16: 885.71 | G16: =IFERROR(SUM(B16:F16),0) -> 7507.96
A17: 午市 | B17: 2736.92 | C17: 5993.97 | D17: 3242.34 | E17: 2191.9 | F17: 4655.69 | G17: =IFERROR(SUM(B17:F17),0) -> 18820.82
A18: 下午茶 | B18: 881.35 | C18: 2490.06 | D18: 1673.36 | E18: 728.06 | F18: 2164.37 | G18: =IFERROR(SUM(B18:F18),0) -> 7937.2
A19: 晚市 | B19: 2443.69 | C19: 4168.43 | D19: 3616.19 | E19: 1282.79 | F19: 4760.91 | G19: =IFERROR(SUM(B19:F19),0) -> 16272.01
A20: 夜宵 | B20: 425.93 | C20: 1041.05 | D20: 1247.62 | E20: 308.03 | F20: 2427.12 | G20: =IFERROR(SUM(B20:F20),0) -> 5449.75
A21: 列合计/均值 | B21: =IFERROR(SUM(B16:B20),0) -> 7691.56 | C21: =IFERROR(SUM(C16:C20),0) -> 15958.56 | D21: =IFERROR(SUM(D16:D20),0) -> 12129.29 | E21: =IFERROR(SUM(E16:E20),0) -> 5314.53 | F21: =IFERROR(SUM(F16:F20),0) -> 14893.8
A22: → 最拖后腿的格子：午市 × 得来速（拖累度 389.8）
A24: 红黄绿的判定：率型指标直接对「目标与口径」的绿黄线；量型指标（净销售）改判「对该切片预测的达成率」——拿全店目标 62,000 去判晚市的 4,761 元，整张表会永远是红的，那就没有信息了。详见 docs/03 第 3.3 节。

Sheet 归因矩阵
A1: 归因矩阵 · Attribution Matrix（指标 × 维度）
A2: 排序列是「拖累度」，不是指标值本身。外送废弃率再高，只占 3% 的量也不值得先动；堂食占 70%，压 0.2 个百分点就顶外送归零的两倍。
A4: 外卖平台评分 × 外卖平台 （全店 4.1，贡献度口径：偏差 × 销售权重）
A5: 外卖平台 | B5: 值 | C5: 状态 | D5: 量占比 | E5: 该格预算 | F5: 对目标 | G5: 拖累度 | H5: 累计占比 | I5: 读法
A6: Meituan | B6: 4.0793 | C6: 红 | D6: 0.44204852 | E6: =INDEX(目标与口径!$F$5:$F$36,MATCH("delivery_rating",目标与口径!$A$5:$A$36,0)) -> 4.8 | F6: -0.72073171 | G6: 0.32 | H6: 0.48087876
A7: Eleme | B7: 4.156 | C7: 红 | D7: 0.38005391 | E7: =INDEX(目标与口径!$F$5:$F$36,MATCH("delivery_rating",目标与口径!$A$5:$A$36,0)) -> 4.8 | F7: -0.64397163 | G7: 0.24 | H7: 0.85028478
A8: McDeliveryApp | B8: 4.2424 | C8: 红 | D8: 0.17789757 | E8: =INDEX(目标与口径!$F$5:$F$36,MATCH("delivery_rating",目标与口径!$A$5:$A$36,0)) -> 4.8 | F8: -0.55757576 | G8: 0.1 | H8: 1
A9: → 先动 Meituan：它占了拖累度的 48%（量占比 44%）
A11: 外卖平台评分 × 时段 （全店 4.1，贡献度口径：偏差 × 销售权重）
A12: 时段 | B12: 值 | C12: 状态 | D12: 量占比 | E12: 该格预算 | F12: 对目标 | G12: 拖累度 | H12: 累计占比 | I12: 读法
A13: Dinner | B13: 3.7345 | C13: 红 | D13: 0.29063524 | E13: =INDEX(目标与口径!$F$5:$F$36,MATCH("delivery_rating",目标与口径!$A$5:$A$36,0)) -> 4.8 | F13: -1.0654867 | G13: 0.31 | H13: 0.47158597
A14: Lunch | B14: 4.1053 | C14: 红 | D14: 0.33615967 | E14: =INDEX(目标与口径!$F$5:$F$36,MATCH("delivery_rating",目标与口径!$A$5:$A$36,0)) -> 4.8 | F14: -0.69473684 | G14: 0.23 | H14: 0.82724226
A15: Afternoon | B15: 4.4386 | C15: 红 | D15: 0.14176675 | E15: =INDEX(目标与口径!$F$5:$F$36,MATCH("delivery_rating",目标与口径!$A$5:$A$36,0)) -> 4.8 | F15: -0.36140351 | G15: 0.05 | H15: 0.90526682
A16: Breakfast | B16: 4.5652 | C16: 黄 | D16: 0.13410007 | E16: =INDEX(目标与口径!$F$5:$F$36,MATCH("delivery_rating",目标与口径!$A$5:$A$36,0)) -> 4.8 | F16: -0.23478261 | G16: 0.03 | H16: 0.9532136
A17: LateNight | B17: 4.4844 | C17: 红 | D17: 0.097338274 | E17: =INDEX(目标与口径!$F$5:$F$36,MATCH("delivery_rating",目标与口径!$A$5:$A$36,0)) -> 4.8 | F17: -0.315625 | G17: 0.03 | H17: 1
A18: → 先动 Dinner：它占了拖累度的 47%（量占比 29%）
A20: 服务速度达标率 × 时段 （全店 76.6%，贡献度口径：偏差 × 销售权重）
A21: 时段 | B21: 值 | C21: 状态 | D21: 量占比 | E21: 该格预算 | F21: 对目标 | G21: 拖累度 | H21: 累计占比 | I21: 读法
A22: Dinner | B22: 0.5507 | C22: 红 | D22: 0.29063524 | E22: =INDEX(目标与口径!$F$5:$F$36,MATCH("speed_hit_rate",目标与口径!$A$5:$A$36,0)) -> 0.9 | F22: -0.34933921 | G22: 10.15 | H22: 0.70267437
A23: Lunch | B23: 0.7722 | C23: 红 | D23: 0.33615967 | E23: =INDEX(目标与口径!$F$5:$F$36,MATCH("speed_hit_rate",目标与口径!$A$5:$A$36,0)) -> 0.9 | F23: -0.12779923 | G23: 4.3 | H23: 1
A24: LateNight | B24: 0.9032 | C24: 绿 | D24: 0.097338274 | E24: =INDEX(目标与口径!$F$5:$F$36,MATCH("speed_hit_rate",目标与口径!$A$5:$A$36,0)) -> 0.9 | F24: 0.0032258065 | G24: -0.03 | H24: 1
A25: Afternoon | B25: 0.9178 | C25: 绿 | D25: 0.14176675 | E25: =INDEX(目标与口径!$F$5:$F$36,MATCH("speed_hit_rate",目标与口径!$A$5:$A$36,0)) -> 0.9 | F25: 0.017808219 | G25: -0.25 | H25: 1
A26: Breakfast | B26: 0.9495 | C26: 绿 | D26: 0.13410007 | E26: =INDEX(目标与口径!$F$5:$F$36,MATCH("speed_hit_rate",目标与口径!$A$5:$A$36,0)) -> 0.9 | F26: 0.049541284 | G26: -0.66 | H26: 1
A27: → 先动 Dinner：它占了拖累度的 70%（量占比 29%）
A29: 服务速度达标率 × 渠道 （全店 76.6%，贡献度口径：偏差 × 销售权重）
A30: 渠道 | B30: 值 | C30: 状态 | D30: 量占比 | E30: 该格预算 | F30: 对目标 | G30: 拖累度 | H30: 累计占比 | I30: 读法
A31: Delivery | B31: 0.5364 | C31: 红 | D31: 0.26601895 | E31: =INDEX(目标与口径!$F$5:$F$36,MATCH("speed_hit_rate",目标与口径!$A$5:$A$36,0)) -> 0.9 | F31: -0.36361186 | G31: 9.67 | H31: 0.62784734
A32: DriveThru | B32: 0.7649 | C32: 红 | D32: 0.21664189 | E32: =INDEX(目标与口径!$F$5:$F$36,MATCH("speed_hit_rate",目标与口径!$A$5:$A$36,0)) -> 0.9 | F32: -0.13512748 | G32: 2.93 | H32: 0.81786307
A33: FrontCounter | B33: 0.7391 | C33: 红 | D33: 0.13737936 | E33: =INDEX(目标与口径!$F$5:$F$36,MATCH("speed_hit_rate",目标与口径!$A$5:$A$36,0)) -> 0.9 | F33: -0.16086957 | G33: 2.21 | H33: 0.9613125
A34: MobileApp | B34: 0.8372 | C34: 黄 | D34: 0.094923103 | E34: =INDEX(目标与口径!$F$5:$F$36,MATCH("speed_hit_rate",目标与口径!$A$5:$A$36,0)) -> 0.9 | F34: -0.062790698 | G34: 0.6 | H34: 1
A35: Kiosk | B35: 0.9475 | C35: 绿 | D35: 0.28503669 | E35: =INDEX(目标与口径!$F$5:$F$36,MATCH("speed_hit_rate",目标与口径!$A$5:$A$36,0)) -> 0.9 | F35: 0.047488584 | G35: -1.35 | H35: 1
A36: → 先动 Delivery：它占了拖累度的 63%（量占比 27%）
A38: 迟到率 × 时段 （全店 10.5%，贡献度口径：无数据）
A39: 时段 | B39: 值 | C39: 状态 | D39: 量占比 | E39: 该格预算 | F39: 对目标 | G39: 拖累度 | H39: 累计占比 | I39: 读法
A40: Breakfast | B40: 0.2857 | C40: 红 | D40: 0.13410007 | E40: =INDEX(目标与口径!$F$5:$F$36,MATCH("late_rate",目标与口径!$A$5:$A$36,0)) -> 0.02 | F40: -0.26571429 | G40: 3.56 | H40: 0.47587736
A41: Lunch | B41: 0.1 | C41: 红 | D41: 0.33615967 | E41: =INDEX(目标与口径!$F$5:$F$36,MATCH("late_rate",目标与口径!$A$5:$A$36,0)) -> 0.02 | F41: -0.08 | G41: 2.69 | H41: 0.83503633
A42: Dinner | B42: 0.0625 | C42: 黄 | D42: 0.29063524 | E42: =INDEX(目标与口径!$F$5:$F$36,MATCH("late_rate",目标与口径!$A$5:$A$36,0)) -> 0.02 | F42: -0.0425 | G42: 1.24 | H42: 1
A43: Afternoon | B43: 0 | C43: 绿 | D43: 0.14176675 | E43: =INDEX(目标与口径!$F$5:$F$36,MATCH("late_rate",目标与口径!$A$5:$A$36,0)) -> 0.02 | F43: 0.02 | G43: -0.28 | H43: 1
A44: → 先动 Breakfast：它占了拖累度的 48%（量占比 13%）
A46: 迟到率 × 岗位 （全店 10.5%，贡献度口径：偏差 × 销售权重）
A47: 岗位 | B47: 值 | C47: 状态 | D47: 量占比 | E47: 该格预算 | F47: 对目标 | G47: 拖累度 | H47: 累计占比 | I47: 读法
A48: Kitchen_Grill | B48: 0 | C48: 绿 | D48: 0 | E48: =INDEX(目标与口径!$F$5:$F$36,MATCH("late_rate",目标与口径!$A$5:$A$36,0)) -> 0.02 | F48: 0.02 | G48: 0 | H48: 0
A49: Kitchen_Fry | B49: 0.1667 | C49: 红 | D49: 0 | E49: =INDEX(目标与口径!$F$5:$F$36,MATCH("late_rate",目标与口径!$A$5:$A$36,0)) -> 0.02 | F49: -0.14666667 | G49: 0 | H49: 0
A50: Beverage | B50: 0.5 | C50: 红 | D50: 0 | E50: =INDEX(目标与口径!$F$5:$F$36,MATCH("late_rate",目标与口径!$A$5:$A$36,0)) -> 0.02 | F50: -0.48 | G50: 0 | H50: 0
A51: DriveThru_Order | B51: 0 | C51: 绿 | D51: 0 | E51: =INDEX(目标与口径!$F$5:$F$36,MATCH("late_rate",目标与口径!$A$5:$A$36,0)) -> 0.02 | F51: 0.02 | G51: 0 | H51: 0
A52: DriveThru_Window | B52: 0.1429 | C52: 红 | D52: 0 | E52: =INDEX(目标与口径!$F$5:$F$36,MATCH("late_rate",目标与口径!$A$5:$A$36,0)) -> 0.02 | F52: -0.12285714 | G52: 0 | H52: 0
A53: Lobby | B53: 0 | C53: 绿 | D53: 0 | E53: =INDEX(目标与口径!$F$5:$F$36,MATCH("late_rate",目标与口径!$A$5:$A$36,0)) -> 0.02 | F53: 0.02 | G53: 0 | H53: 0
A54: Delivery_Pack | B54: 0 | C54: 绿 | D54: 0 | E54: =INDEX(目标与口径!$F$5:$F$36,MATCH("late_rate",目标与口径!$A$5:$A$36,0)) -> 0.02 | F54: 0.02 | G54: 0 | H54: 0
A55: Assembly | B55: 0 | C55: 绿 | D55: 1 | E55: =INDEX(目标与口径!$F$5:$F$36,MATCH("late_rate",目标与口径!$A$5:$A$36,0)) -> 0.02 | F55: 0.02 | G55: -2 | H55: 0
A56: → 先动 Kitchen_Grill：它占了拖累度的 0%（量占比 0%）
A58: 设备停机时长 × 设备 （全店 76，贡献度口径：绝对量）
A59: 设备 | B59: 值 | C59: 状态 | D59: 量占比 | E59: 该格预算 | F59: 对目标 | G59: 拖累度 | H59: 累计占比 | I59: 读法
A60: FRYER-2 | B60: 76 | C60: 红 | D60: 0 | E60: =INDEX(目标与口径!$F$5:$F$36,MATCH("equipment_downtime",目标与口径!$A$5:$A$36,0)) -> 0 | F60: -76 | G60: 76 | H60: 1
A61: UHC-1 | B61: 0 | C61: 绿 | D61: 0.33333333 | E61: =INDEX(目标与口径!$F$5:$F$36,MATCH("equipment_downtime",目标与口径!$A$5:$A$36,0)) -> 0 | F61: 0 | G61: 0 | H61: 1
A62: WALKIN-C | B62: 0 | C62: 绿 | D62: 0.33333333 | E62: =INDEX(目标与口径!$F$5:$F$36,MATCH("equipment_downtime",目标与口径!$A$5:$A$36,0)) -> 0 | F62: 0 | G62: 0 | H62: 1
A63: WALKIN-F | B63: 0 | C63: 绿 | D63: 0.33333333 | E63: =INDEX(目标与口径!$F$5:$F$36,MATCH("equipment_downtime",目标与口径!$A$5:$A$36,0)) -> 0 | F63: 0 | G63: 0 | H63: 1
A64: → 先动 FRYER-2：它占了拖累度的 100%（量占比 0%）
A66: 工时排班偏差 × 时段 （全店 5.1%，贡献度口径：偏差 × 销售权重）
A67: 时段 | B67: 值 | C67: 状态 | D67: 量占比 | E67: 该格预算 | F67: 对目标 | G67: 拖累度 | H67: 累计占比 | I67: 读法
A68: Dinner | B68: 0.1228 | C68: 红 | D68: 0.29063524 | E68: =INDEX(目标与口径!$F$5:$F$36,MATCH("labor_schedule_variance",目标与口径!$A$5:$A$36,0)) -> 0.02 | F68: -0.10282481 | G68: 2.99 | H68: 0.89500089
A69: Breakfast | B69: 0.0415 | C69: 黄 | D69: 0.13410007 | E69: =INDEX(目标与口径!$F$5:$F$36,MATCH("labor_schedule_variance",目标与口径!$A$5:$A$36,0)) -> 0.02 | F69: -0.021518987 | G69: 0.29 | H69: 0.98142365
A70: Lunch | B70: 0.0218 | C70: 绿 | D70: 0.33615967 | E70: =INDEX(目标与口径!$F$5:$F$36,MATCH("labor_schedule_variance",目标与口径!$A$5:$A$36,0)) -> 0.02 | F70: -0.001845175 | G70: 0.06 | H70: 1
A71: LateNight | B71: 0.0181 | C71: 绿 | D71: 0.097338274 | E71: =INDEX(目标与口径!$F$5:$F$36,MATCH("labor_schedule_variance",目标与口径!$A$5:$A$36,0)) -> 0.02 | F71: 0.001897302 | G71: -0.02 | H71: 1
A72: Afternoon | B72: 0.0181 | C72: 绿 | D72: 0.14176675 | E72: =INDEX(目标与口径!$F$5:$F$36,MATCH("labor_schedule_variance",目标与口径!$A$5:$A$36,0)) -> 0.02 | F72: 0.001863091 | G72: -0.03 | H72: 1
A73: → 先动 Dinner：它占了拖累度的 90%（量占比 29%）
A75: 工时排班偏差 × 岗位 （全店 5.1%，贡献度口径：偏差 × 销售权重）
A76: 岗位 | B76: 值 | C76: 状态 | D76: 量占比 | E76: 该格预算 | F76: 对目标 | G76: 拖累度 | H76: 累计占比 | I76: 读法
A77: Kitchen_Grill | B77: 0.15 | C77: 红 | D77: 0 | E77: =INDEX(目标与口径!$F$5:$F$36,MATCH("labor_schedule_variance",目标与口径!$A$5:$A$36,0)) -> 0.02 | F77: -0.13 | G77: 0 | H77: 0
A78: Kitchen_Fry | B78: 0.0058 | C78: 绿 | D78: 0 | E78: =INDEX(目标与口径!$F$5:$F$36,MATCH("labor_schedule_variance",目标与口径!$A$5:$A$36,0)) -> 0.02 | F78: 0.014153846 | G78: 0 | H78: 0
A79: Beverage | B79: 0.0082 | C79: 绿 | D79: 0 | E79: =INDEX(目标与口径!$F$5:$F$36,MATCH("labor_schedule_variance",目标与口径!$A$5:$A$36,0)) -> 0.02 | F79: 0.011836735 | G79: 0 | H79: 0
A80: DriveThru_Order | B80: 0.0167 | C80: 绿 | D80: 0 | E80: =INDEX(目标与口径!$F$5:$F$36,MATCH("labor_schedule_variance",目标与口径!$A$5:$A$36,0)) -> 0.02 | F80: 0.0033333333 | G80: 0 | H80: 0
A81: DriveThru_Window | B81: 0.0109 | C81: 绿 | D81: 0 | E81: =INDEX(目标与口径!$F$5:$F$36,MATCH("labor_schedule_variance",目标与口径!$A$5:$A$36,0)) -> 0.02 | F81: 0.0091358025 | G81: 0 | H81: 0
A82: Lobby | B82: 0.0188 | C82: 绿 | D82: 0 | E82: =INDEX(目标与口径!$F$5:$F$36,MATCH("labor_schedule_variance",目标与口径!$A$5:$A$36,0)) -> 0.02 | F82: 0.0012121212 | G82: 0 | H82: 0
A83: Delivery_Pack | B83: 0.0111 | C83: 绿 | D83: 0 | E83: =INDEX(目标与口径!$F$5:$F$36,MATCH("labor_schedule_variance",目标与口径!$A$5:$A$36,0)) -> 0.02 | F83: 0.0089473684 | G83: 0 | H83: 0
A84: Assembly | B84: 0.0119 | C84: 绿 | D84: 1 | E84: =INDEX(目标与口径!$F$5:$F$36,MATCH("labor_schedule_variance",目标与口径!$A$5:$A$36,0)) -> 0.02 | F84: 0.0081012658 | G84: -0.81 | H84: 0
A85: → 先动 Kitchen_Grill：它占了拖累度的 0%（量占比 0%）
A87: 附加销售率 × 时段 （全店 24.5%，贡献度口径：偏差 × 销售权重）
A88: 时段 | B88: 值 | C88: 状态 | D88: 量占比 | E88: 该格预算 | F88: 对目标 | G88: 拖累度 | H88: 累计占比 | I88: 读法
A89: Dinner | B89: 0.2069 | C89: 红 | D89: 0.29063524 | E89: =INDEX(目标与口径!$F$5:$F$36,MATCH("upsell_rate",目标与口径!$A$5:$A$36,0)) -> 0.3 | F89: -0.093103448 | G89: 2.71 | H89: 0.47939129
A90: Lunch | B90: 0.2472 | C90: 黄 | D90: 0.33615967 | E90: =INDEX(目标与口径!$F$5:$F$36,MATCH("upsell_rate",目标与口径!$A$5:$A$36,0)) -> 0.3 | F90: -0.052808989 | G90: 1.78 | H90: 0.79389774
A91: Afternoon | B91: 0.2609 | C91: 黄 | D91: 0.14176675 | E91: =INDEX(目标与口径!$F$5:$F$36,MATCH("upsell_rate",目标与口径!$A$5:$A$36,0)) -> 0.3 | F91: -0.039130435 | G91: 0.55 | H91: 0.89217774
A92: LateNight | B92: 0.25 | C92: 黄 | D92: 0.097338274 | E92: =INDEX(目标与口径!$F$5:$F$36,MATCH("upsell_rate",目标与口径!$A$5:$A$36,0)) -> 0.3 | F92: -0.05 | G92: 0.49 | H92: 0.97840205
A93: Breakfast | B93: 0.2909 | C93: 绿 | D93: 0.13410007 | E93: =INDEX(目标与口径!$F$5:$F$36,MATCH("upsell_rate",目标与口径!$A$5:$A$36,0)) -> 0.3 | F93: -0.0090909091 | G93: 0.12 | H93: 1
A94: → 先动 Dinner：它占了拖累度的 48%（量占比 29%）
A96: 附加销售率 × 渠道 （全店 24.5%，贡献度口径：无数据）
A97: 渠道 | B97: 值 | C97: 状态 | D97: 量占比 | E97: 该格预算 | F97: 对目标 | G97: 拖累度 | H97: 累计占比 | I97: 读法
A98: DriveThru | B98: 0.2295 | C98: 黄 | D98: 0.21664189 | E98: =INDEX(目标与口径!$F$5:$F$36,MATCH("upsell_rate",目标与口径!$A$5:$A$36,0)) -> 0.3 | F98: -0.070538244 | G98: 1.53 | H98: 0.78517257
A99: FrontCounter | B99: 0.2696 | C99: 黄 | D99: 0.13737936 | E99: =INDEX(目标与口径!$F$5:$F$36,MATCH("upsell_rate",目标与口径!$A$5:$A$36,0)) -> 0.3 | F99: -0.030434783 | G99: 0.42 | H99: 1
A100: → 先动 DriveThru：它占了拖累度的 79%（量占比 22%）
A102: 「该格预算」= 全店目标 × 该格量占比，只对全店分母口径的指标（废弃率、食品成本率、千单投诉数）成立：全店废弃率目标 0.8%、午市占 34% 的销售，午市的预算就是 0.27 个百分点。各格预算加起来正好等于全店目标，所以这样判色是自洽的。切片分母口径的指标（速度、人工率、客单价）目标与切片大小无关，直接用全店目标。

Sheet 报表清单
A1: 报表清单 · Manager Report Package
A2: 一张报表如果回答不了「看完要做什么」，它就不该出现在这个清单里。所以最后一栏是动作，不是描述。全天合计不超过 75 分钟——超过这个数，报表就开始和营运抢时间了。
A4: A. 每日报表（按一天的时间轴）
A5: 编号 | B5: 报表 | C5: 什么时候 | D5: 分钟 | E5: 谁看 | F5: 回答什么问题 | G5: 关键指标 | H5: 数据来源表 | I5: 看完做什么
A6: R01 | B6: 昨日日结一页纸 (DSR) | C6: 07:00 开店前 | D6: 5 | E6: 店长 | F6: 昨天到底做成什么样？有没有需要今天补的窟窿？ | G6: 净销售额、销售达成率、交易笔数 (GC)、客单价 (TC)、食品成本率、人工成本率、现金短溢 | H6: fct_daily_sales_summary、agg_food_cost_day、agg_labor_day、fct_cash_declaration | I6: 只有一个动作：把偏差最大的那一项，写进今天班前会的第一句话。
A7: R02 | B7: 今日销售预测 × 排班对照表 | C7: 07:10 | D7: 8 | E7: 店长 | F7: 今天的人，够不够撑住今天的生意？缺口在哪个 15 分钟？ | G7: 销售达成率、工时排班偏差、人时销售 (SPLH)、出勤达成率 | H7: dim_sales_forecast、fct_schedule、fct_timecard | I7: 高峰前 30 分钟人力缺口 > 1 人 → 现在就打电话调班，不要等到高峰再救。
A8: R03 | B8: 开店食安与设备检查表 | C8: 07:20 开店前 | D8: 10 | E8: 值班经理 | F8: 今天能不能安全地开门？ | G8: 食安日检得分、关键温度点异常数、设备停机时长 | H8: fct_food_safety_check、fct_temperature_log、fct_equipment_ticket、dim_equipment | I8: 关键项任意一项 fail = 停止该产品出品并立即整改。这张表没有'先记着'这个选项。
A9: R04 | B9: 库存盘点与订货建议 | C9: 07:40 | D9: 8 | E9: 店长 | F9: 今天会不会断货？会不会又订多了明天扔掉？ | G9: 食品成本率、废弃率 | H9: fct_inventory_count、dim_sales_forecast、fct_goods_receipt、dim_item | I9: 关键品缺口 → 调整备货计划；连续三天盘点差异同向 → 查配方/打料/收货。
A10: R05 | B10: 实时销售 vs 预测（日内滚动） | C10: 每小时 + 高峰前 | D10: 2 | E10: 值班经理 | F10: 今天走在预算线上吗？差在哪个渠道？ | G10: 净销售额、销售达成率、交易笔数 (GC)、客单价 (TC)、单均件数、外送销售占比 | H10: fct_pos_transaction、dim_sales_forecast | I10: 落后 > 5% 且原因在客单价 → 立刻做附加销售动员；原因在客流 → 改动的是外场和外送曝光。
A11: R06 | B11: 服务速度日内看板 | C11: 高峰进行中（11:30 / 18:00） | D11: 3 | E11: 值班经理 | F11: 现在慢在哪一段？点单、厨房、还是交付？ | G11: 得来速总时长、得来速取餐窗时长、后厨制作时长、前台交付时长 (OTD)、服务速度达标率、外送出餐时长 | H11: fct_dt_timer、fct_kds_order、fct_delivery_order | I11: 窗口时长高 → 后厨备餐没跟上，加人到理货；点单段高 → 加点单员或开第二车道。
A12: R07 | B12: 人力投放与 SPLH 追踪 | C12: 高峰后（14:00 / 20:30） | D12: 5 | E12: 店长 | F12: 这一波高峰，人是花值了还是花冤了？ | G12: 人时销售 (SPLH)、人工成本率、工时排班偏差、出勤达成率、迟到率 | H12: fct_timecard、fct_schedule、fct_pos_transaction | I12: SPLH 低 + 速度也差 = 排班结构错（不是人不够，是人站错岗）→ 调岗位不是加人头。
A13: R08 | B13: 废弃与保温批次报表 | C13: 14:00 / 21:00 交接班 | D13: 5 | E13: 值班经理 | F13: 今天扔了多少？为什么扔？ | G13: 废弃率、保温超时率、食品成本率 | H13: fct_waste_log、fct_holding_batch、fct_pos_line_item | I13: 成品废弃高 = 备货节奏问题（改批量大小）；原料废弃高 = 先进先出与订货量问题。
A14: R09 | B14: 外送平台运营报表 | C14: 15:00 | D14: 5 | E14: 店长 | F14: 外送这四分之一的生意，是在赚钱还是在赔口碑？ | G14: 外送出餐时长、外卖平台评分、外送销售占比、订单准确率 | H14: fct_delivery_order、fct_order_issue、fct_guest_survey | I14: 出餐时长超标 → 高峰给外送单独留一个打包位；差评集中在漏餐 → 上双人核对。
A15: R10 | B15: 顾客反馈与差错清单 | C15: 16:00 | D15: 5 | E15: 值班经理 | F15: 顾客今天在抱怨什么？是不是同一件事在重复发生？ | G15: 顾客满意度、千单投诉数、订单准确率、清洁巡检得分 | H15: fct_guest_survey、fct_order_issue、fct_travel_path_check | I15: 同一个 comment_tag 一周出现 3 次以上 → 它不是个案，是流程缺陷，进周复盘。
A16: R11 | B16: 闭店日结：销售 / 成本 / 现金 | C16: 23:30 闭店 | D16: 12 | E16: 店长 | F16: 今天的账对不对？成本控住了吗？ | G16: 净销售额、食品成本率、废弃率、人工成本率、人时销售 (SPLH)、现金短溢 | H16: fct_pos_transaction、fct_payment、agg_food_cost_day、agg_labor_day、fct_cash_declaration、fct_daily_sales_summary | I16: 现金短溢超阈值 → 当班复核录像与交接记录，当天闭环，不隔夜。
A17: R12 | B17: 次日准备与交接单 | C17: 闭店前 | D17: 5 | E17: 值班经理 | F17: 明天早班一进门，需要知道哪三件事？ | G17: 设备停机时长、岗位认证覆盖率、出勤达成率 | H17: fct_equipment_ticket、fct_schedule、fct_training_record | I17: 交接单只写三件事：坏了什么、缺了谁、明天几点最忙。写多了没人看。
B18: 合计 | D18: =SUM(D6:D17) -> 73 | F18: 全天报表时间上限：75 分钟
A20: B. 每周报表
A21: 编号 | B21: 报表 | C21: 频率 | E21: 谁看 | F21: 回答什么问题 | G21: 关键指标
A22: W01 | B22: 周 P&L 与可控成本复盘 | C22: 每周 | E22: 店长 | F22: 这周的钱花在哪，下周能省回来多少？ | G22: 食品成本率、人工成本率、废弃率、净销售额
A23: W02 | B23: 周人员报表：排班效率 / 认证 / 流失 | C23: 每周 | E23: 店长 | F23: 队伍在变强还是在流血？ | G23: 30日员工流失率、岗位认证覆盖率、出勤达成率、人时销售 (SPLH)
A24: W03 | B24: 周食安与设备健康 | C24: 每周 | E24: 值班经理 | F24: 有没有反复出现的同一个隐患？ | G24: 食安日检得分、关键温度点异常数、设备停机时长、清洁巡检得分
A25: W04 | B25: 周顾客体验与活动复盘 | C25: 每周 | E25: 店长 | F25: 顾客的评价，和我们内部的数说的是同一件事吗？ | G25: 顾客满意度、外卖平台评分、千单投诉数、客单价 (TC)、附加销售率
A27: C. 责任矩阵：谁 × 什么节奏 × 盯什么
A28: 责任人 | B28: 每日 | C28: 每周 | D28: 每月
A29: 店长 | B29: 净销售额、销售达成率、交易笔数 (GC)、外送销售占比、食品成本率、人工成本率、食安日检得分、设备停机时长、顾客满意度、外卖平台评分 | C29: 30日员工流失率 | D29: —
A30: 值班经理 | B30: 客单价 (TC)、单均件数、得来速总时长、得来速取餐窗时长、前台交付时长 (OTD)、服务速度达标率、订单准确率、废弃率、人时销售 (SPLH)、工时排班偏差、现金短溢、关键温度点异常数、清洁巡检得分、出勤达成率、千单投诉数 | C30: — | D30: —
A31: 组长 | B31: 附加销售率、后厨制作时长、外送出餐时长、保温超时率、迟到率 | C31: — | D31: —
A32: 训练员 | B32: — | C32: 岗位认证覆盖率 | D32: —
A34: 责任矩阵一年也不改几次，但它是「这本工作簿到底归谁管」的唯一答案，也是新店长交接时第一份要看的东西。

Sheet 行动卡
A1: 行动卡 · Action Playbooks
A2: 红灯亮了做什么。每张卡的结构固定：先判断根因（同一个红灯，根因不同则动作相反，猜错了比不做还糟），再给动作，最后给验证方式。
A4: 编号 | B4: 适用情况 | C4: 先判断什么（诊断） | D4: 动作 | E4: 怎么验证
A5: PB-01 | B5: 销售 / 客流不达标 | C5: 先分清是「人少」还是「人均少」：看交易笔数和客单价哪个先塌 | D5: 客流少 → 查天气/施工/竞品/平台曝光/点餐机故障；客单少 → 走 PB-02；两个都跌 → 单时段跌是具体事件，全时段跌是商圈或平台层面 | E5: 次日同时段同渠道回到预测的 ±3% 以内
A6: PB-02 | B6: 客单价 / 附加销售不足 | C6: 人工点单低、点餐机正常 = 人的问题；两个都低 = 产品结构问题（上报） | D6: 拉附加销售率 × 收银员找出后 30%；班前会只指定 1 个主推品（推三个等于不推）；训练员跟班 2 小时 | E6: 三天内后 30% 的人追上门店均值的 80%
A7: PB-03 | B7: 外送时效 / 评分下滑 | C7: 用堂食的办法救外送通常无效——它是两套流程 | D7: 全时段慢 = 打包动线与堂食抢人（跨部门，上报）；只高峰慢 = 高峰给外送单独留人；某平台慢 = 联系平台商务；差评集中漏餐 = 双人核对 + 封签 | E7: 出餐时长回到目标线连续 3 天；评分是滞后指标，一到两周后才跟上
A8: PB-04 | B8: 服务速度不达标 | C8: 最需要先诊断再动手的一张卡。直接「加人」是最常见也最贵的错误答案 | D8: ① 分段定位：点单段长→加点单员/开第二车道；取餐窗长→后厨备餐没跟上，加人到理货（不是点单）；制作段长→查设备/批量/新手 ② 分清结构问题（某渠道全时段红）还是产能问题（某时段所有渠道红） | E8: 目标时段达标率回绿，且 SPLH 没有明显下降（否则是靠堆人换的，不可持续）
A9: PB-05 | B9: 订单差错 / 投诉上升 | C9: 先看是不是同一件事在重复发生 | D9: 集中在一种差错类型 → 改流程；集中在一个时段 → 走 PB-04；集中在一个渠道 → 查该渠道的交接环节；分散无规律 → 看岗位认证覆盖率 | E9: 千单投诉数连续 5 天在绿线内，且同类差错不再出现在 top 3
A10: PB-06 | B10: 废弃 / 食品成本超标 | C10: 先分清废弃的三种类型，动作完全不同 | D10: 成品废弃（做多了）→ 减小批量、缩短备货提前量；原料废弃（过期掉落）→ 查先进先出、调订货量；保温超时 → 高峰前按预测分批做。食品成本高但废弃正常 → 问题在盘点差异：查配方/打料/收货/废弃漏登记 | E10: 次日同时段废弃回绿；一周后食品成本率跟上
A11: PB-07 | B11: 人工成本 / 排班效率 | C11: 看 SPLH 与速度的组合，这是判断根因的关键 | D11: SPLH 低 + 速度差 = 排班结构错（人站错岗），调岗位不是加人头；SPLH 低 + 速度好 = 人排多了，削平峰保高峰；SPLH 高 + 速度差 = 真的需要加人；两个都好 = 记下这天的排班曲线做模板 | E11: 目标时段 SPLH 回绿，且速度达标率不下降
A12: PB-08 | B12: 现金短溢 | C12: 金额小但性质是内控问题，不按金额大小排优先级 | D12: 定位到班次和收银员 → 复核交接记录与监控 → 当天闭环不隔夜 → 同一人连续出现转人事流程 | E12: 当日闭环并留下书面记录
A13: PB-09 | B13: 食安失分 / 温度异常 | C13: 这张卡没有「先记着」这个选项 | D13: 关键项 fail = 立即停止该产品出品，整改复检通过才恢复；温度超标 = 判断受影响批次范围并按标准处置 → 报修 → 加密监测；冷藏/冷冻库超标可能触发全库处置 | E13: 复检通过 + 连续 3 天该项无 fail；同一项一周 fail 两次必须上报
A14: PB-10 | B14: 清洁 / 巡店失分 | C14: 顾客对「干净」的判断在洗手间和餐桌，不在厨房 | D14: 洗手间失分 → 高峰期每小时巡检一次（投入产出比最高）；大堂失分 → 高峰收餐人力不足，走 PB-07；外围/车道失分 → 通常是排班里根本没有这个岗位 | E14: 分区得分全部回到绿线，且洗手间不再是最低分区
A15: PB-11 | B15: 设备停机 | C15: 先决定停售范围，再谈修 | D15: 关键设备停机 → 立刻决定哪些产品下架并同步到所有点单渠道（最容易忘的是外送平台：平台还在卖但门店做不出来，是差评的最大来源之一）→ 报修 → 同一设备一月两次故障走更换评估 | E15: 恢复出品 + 工单闭环；周会看一次保养到期清单
A16: PB-12 | B16: 人员流失 / 认证不足 | C16: 唯一一张不看日数据的卡——日维度上这两个指标全是噪声 | D16: 流失集中在 <90 天 → 入职培训和排班体验的问题（新人被丢在高峰上是最常见原因）；流失分布在 >1 年 → 发展通道或薪酬，超出门店范围，上报；某岗位认证覆盖率长期低 → 训练排期没覆盖到它，而它往往正是速度和废弃问题的源头 | E16: 进周会第一页跟踪；这两个指标是速度/废弃/食安/差错红灯的共同上游
A18: 行动卡编号挂在「目标与口径」的最后一列，所以「店长看板」和「优先级矩阵」上的每个红灯都会直接告诉你翻哪一张卡。

Sheet 目标与口径
A1: 目标与口径 · Targets, Thresholds & KPI Definitions
A2: 全本唯一的阈值来源。浅蓝格子可改；改完「店长看板」「优先级矩阵」「归因矩阵」的红黄绿与排序会一起变。示例阈值须按各自门店标准替换。
A4: 指标ID | B4: 指标 | C4: 家族 | D4: 定义 / 公式 | E4: 方向 | F4: 目标 | G4: 绿线 | H4: 黄线 | I4: 单位 | J4: 责任人 | K4: 频率 | L4: 影响度 | M4: 可控度 | N4: 行动卡
A5: avg_check | B5: 客单价 (TC) | C5: 生意 | D5: net_sales / guest_count | E5: 越高越好 | F5: 35.5 | G5: 35 | H5: 33 | I5: CNY | J5: 值班经理 | K5: 每日 | L5: 0.8 | M5: 0.75 | N5: PB-02
A6: delivery_share | B6: 外送销售占比 | C6: 生意 | D6: 外送渠道净销售 / 总净销售 * 100 | E6: 越低越好（上限） | F6: 0.22 | G6: 0.3 | H6: 0.38 | I6: % | J6: 店长 | K6: 每日 | L6: 0.4 | M6: 0.2 | N6: PB-03
A7: guest_count | B7: 交易笔数 (GC) | C7: 生意 | D7: COUNT(DISTINCT order_id WHERE status='completed') | E7: 越高越好 | F7: 1750 | G7: 1620 | H7: 1480 | I7: 笔 | J7: 店长 | K7: 每日 | L7: 0.9 | M7: 0.35 | N7: PB-01
A8: items_per_check | B8: 单均件数 | C8: 生意 | D8: SUM(qty) / guest_count | E8: 越高越好 | F8: 3.2 | G8: 3.1 | H8: 2.9 | I8: 件 | J8: 值班经理 | K8: 每日 | L8: 0.6 | M8: 0.8 | N8: PB-02
A9: net_sales | B9: 净销售额 | C9: 生意 | D9: SUM(gross_amount - discount_amount - refund_amount) | E9: 越高越好 | F9: 62000 | G9: 58000 | H9: 52000 | I9: CNY | J9: 店长 | K9: 每日 | L9: 1 | M9: 0.45 | N9: PB-01
A10: sales_vs_forecast | B10: 销售达成率 | C10: 生意 | D10: net_sales / forecast_sales * 100 | E10: 越高越好 | F10: 1 | G10: 0.98 | H10: 0.93 | I10: % | J10: 店长 | K10: 每日 | L10: 0.95 | M10: 0.5 | N10: PB-01
A11: upsell_rate | B11: 附加销售率 | C11: 生意 | D11: 含加价购/升级/甜品站附加品的订单数 / 人工点单订单数 * 100 | E11: 越高越好 | F11: 0.3 | G11: 0.28 | H11: 0.22 | I11: % | J11: 组长 | K11: 每日 | L11: 0.55 | M11: 0.9 | N11: PB-02
A12: delivery_handover_time | B12: 外送出餐时长 | C12: 速度 | D12: AVG(rider_pickup_ts - order_accept_ts) | E12: 越低越好 | F12: 360 | G12: 400 | H12: 480 | I12: 秒 | J12: 组长 | K12: 每日 | L12: 0.6 | M12: 0.7 | N12: PB-03
A13: dt_total_time | B13: 得来速总时长 | C13: 速度 | D13: AVG(depart_ts - arrive_ts) | E13: 越低越好 | F13: 180 | G13: 190 | H13: 215 | I13: 秒 | J13: 值班经理 | K13: 每日 | L13: 0.9 | M13: 0.85 | N13: PB-04
A14: dt_window_time | B14: 得来速取餐窗时长 | C14: 速度 | D14: AVG(depart_ts - window_arrive_ts) | E14: 越低越好 | F14: 55 | G14: 60 | H14: 75 | I14: 秒 | J14: 值班经理 | K14: 每日 | L14: 0.7 | M14: 0.9 | N14: PB-04
A15: front_otd | B15: 前台交付时长 (OTD) | C15: 速度 | D15: AVG(handover_ts - order_ts) WHERE channel IN ('FrontCounter','Kiosk') | E15: 越低越好 | F15: 150 | G15: 165 | H15: 195 | I15: 秒 | J15: 值班经理 | K15: 每日 | L15: 0.7 | M15: 0.85 | N15: PB-04
A16: kds_prep_time | B16: 后厨制作时长 | C16: 速度 | D16: AVG(bump_ts - fire_ts) | E16: 越低越好 | F16: 90 | G16: 100 | H16: 125 | I16: 秒 | J16: 组长 | K16: 每日 | L16: 0.75 | M16: 0.85 | N16: PB-04
... A36: delivery_rating | B36: 外卖平台评分 | C36: 顾客 | D36: 美团/饿了么门店评分加权均值（5 分制） | E36: 越高越好 | F36: 4.8 | G36: 4.7 | H36: 4.5 | I36: 分 | J36: 店长 | K36: 每日 | L36: 0.7 | M36: 0.55 | N36: PB-03
A38: 影响度 = 这个指标动一动对生意和顾客的影响有多大；可控度 = 店长今天真的能改变它多少。两者都是门店层面的常识判断，不是算出来的——原材料涨价推高的食品成本率，影响度高但可控度低，硬压只会逼出偷工减料。优先级矩阵用它们分四象限。
A39: 口径说明：百分比一律以分数存储（0.312 显示为 31.2%）。废弃率、食品成本率、千单投诉数采用「全店分母」口径（可加，用于归因）；人工成本率、SPLH、速度类采用「切片分母」口径（各块自己的体检值）。详见 docs/03。

Sheet 数据字典
A1: 数据字典 · Source Tables
A2: 一家门店每天真正在用的 30 张表。现实是它们分散在 6~8 个互不相通的系统里；把它们对齐到同一个 store_id + 营业日，是做任何报表的前提，也是最容易出错的地方（跨零点的夜宵单算哪一天）。
A4: 表名 | B4: 中文名 | C4: 业务域 | D4: 层级 | E4: 来源系统 | F4: 粒度 | G4: 刷新频率 | H4: 日增行数 | I4: 为什么需要它
A5: fct_pos_transaction | B5: POS 订单头 | C5: 交易 | D5: fct | E5: POS 收银系统 | F5: 1 行 = 1 张订单 | G5: 近实时（15 分钟增量） | H5: 1500 ~ 3000 | I5: 所有生意类指标的地基：销售、交易笔数、客单价、渠道结构、时段曲线
A6: fct_pos_line_item | B6: POS 订单行 | C6: 交易 | D6: fct | E6: POS 收银系统 | F6: 1 行 = 订单里的 1 个商品 | G6: 近实时 | H6: 5000 ~ 10000 | I6: 品类结构、单均件数、附加销售、理论食品成本都只能从这里算
A7: fct_payment | B7: 支付明细 | C7: 交易 | D7: fct | E7: POS / 聚合支付 | F7: 1 行 = 1 笔支付（一单可拆多笔） | G7: 近实时 | H7: 1600 ~ 3200 | I7: 现金短溢、平台回款对账、支付渠道手续费
A8: dim_product | B8: 商品主数据 | C8: 交易 | D8: dim | E8: 总部主数据 | F8: 1 行 = 1 个 SKU 的 1 个生效版本 | G8: 总部下发，周级 | H8: —（约 300 个在售 SKU） | I8: 标准成本 → 理论食品成本；有它才能把'实际 FC%'拆成'理论差'和'损耗差'
A9: dim_promotion | B9: 促销主数据 | C9: 交易 | D9: dim | E9: 总部营销 | F9: 1 行 = 1 个活动 | G9: 周级 | H9: — | I9: 解释销售异动：涨了是活动还是本事，跌了是去年有活动今年没有
A10: fct_delivery_order | B10: 外送订单 | C10: 数字与外送 | D10: fct | E10: 美团/饿了么/麦乐送 中台 | F10: 1 行 = 1 张外送订单 | G10: 近实时 | H10: 300 ~ 800 | I10: 外送已是四分之一的生意，但它的时效、差错、评分和堂食完全不同源，必须单独看
A11: fct_kiosk_session | B11: 自助点餐机会话 | C11: 数字与外送 | D11: fct | E11: 点餐机后台 | F11: 1 行 = 1 次触屏会话 | G11: 日批 | H11: 500 ~ 1200 | I11: 点餐机放弃率是隐形流失：屏幕坏了/网络慢/菜单卡顿，POS 上完全看不出来
A12: fct_kds_order | B12: 厨房显示系统订单 | C12: 出品时效 | D12: fct | E12: KDS | F12: 1 行 = 1 张订单在 1 个工作站的一段 | G12: 近实时 | H12: 2000 ~ 4000 | I12: 把'慢'拆开：是点单慢、厨房慢、还是交付慢。没有 KDS 就只能靠感觉
A13: fct_dt_timer | B13: 得来速计时 | C13: 出品时效 | D13: fct | E13: DT 计时器（地感线圈 + 计时主机） | F13: 1 行 = 1 辆车的一次通过 | G13: 近实时 | H13: 300 ~ 700 | I13: 得来速是分段计时：菜单板→点单→缴费→取餐→离开，堵在哪一段，动作完全不同
A14: fct_order_issue | B14: 订单差错与投诉 | C14: 出品时效 | D14: fct | E14: POS 退换 + 客服工单 + 平台售后 | F14: 1 行 = 1 个差错事件 | G14: 日批 | H14: 5 ~ 40 | I14: 订单准确率、千单投诉数的唯一来源；按 reason 归类才知道是配料错还是漏给
A15: dim_employee | B15: 员工主数据 | C15: 人员 | D15: dim | E15: 人事系统 | F15: 1 行 = 1 名员工 | G15: 日批 | H15: —（约 60~90 人在册） | I15: 工时成本要按人算时薪；流失率、认证覆盖都挂在这张表上
... A34: agg_metric_dim | B34: 指标 × 下钻维度 | C34: 聚合 | D34: agg | E34: 本 package 的指标引擎 | F34: 1 行 = 门店 × 营业日 × 指标 × 维度 × 维度值 | G34: 日批 + 日内滚动 | H34: 约 800 | I34: 归因矩阵（指标 × 渠道 / 品类 / 岗位 / 人）的物理落地

Sheet 使用说明
A1: 门店运营报表包 · 使用说明
A2: 本工作簿是快餐门店运营的通用模拟模板，不代表任何特定品牌的真实数据或内部标准；所有阈值均为示例，须按各自门店预算、合同与当地法规替换。
A4: 0. 怎么用这本工作簿
A5: ① 先改「目标与口径」 | B5: 那是全本唯一的阈值来源。改一个绿线，看板、优先级矩阵、所有归因表的红黄绿会一起变。
A6: ② 每天填「每日经营日报」 | B6: 只填浅蓝色格子（原子数）。白色格子是公式，会自己算，别覆盖。
A7: ③ 早会看「店长看板」 | B7: 四个数 + 六盏灯 + 今天的三件事。看完就去干活，别在这里停留超过 1 分钟。
A8: ④ 要找原因才翻矩阵 | B8: 时段矩阵找“哪半小时崩了”，交叉矩阵找“哪个渠道 × 哪个时段”，归因矩阵找“哪一格拖了全店最多”。
A9: ⑤ 「报表清单」是节奏表 | B9: 谁在什么时间看哪张表、看完做什么。新店长交接先看它。
A11: 1. 颜色与格式约定
A12: 标记 | B12: 含义 | C12: 说明
A13: 浅蓝底 | B13: 可编辑输入 | C13: 原子数：净销售、交易笔数、工时、废弃金额…… 每天由店长/系统填入
A14: 白底 | B14: 公式 | C14: 派生指标：客单价、达成率、成本率、SPLH、状态灯…… 自动计算，不要手改
A15: 绿 | B15: 达标 | C15: 在绿线以内
A16: 黄 | B16: 关注 | C16: 越过绿线但没到红线；单日出现是噪声，连续 3 天才是信号
A17: 红 | B17: 告警 | C17: 越过红线；当天必须有动作或有上报
A19: 2. 一天的管理节奏（详见「报表清单」）
A20: 时间点 | B20: 看什么 | C20: 重点问题 | D20: 输出 | E20: 时长 | F20: 数据来源 | G20: 负责人 | H20: 完成
A21: 07:00 开店前 | B21: 昨日日结一页纸 (DSR) | C21: 昨天到底做成什么样？有没有需要今天补的窟窿？ | D21: 只有一个动作：把偏差最大的那一项，写进今天班前会的第一句话。 | E21: 5 分钟 | F21: fct_daily_sales_summary、agg_food_cost_day | G21: 店长 | H21: ☐
A22: 07:10 | B22: 今日销售预测 × 排班对照表 | C22: 今天的人，够不够撑住今天的生意？缺口在哪个 15 分钟？ | D22: 高峰前 30 分钟人力缺口 > 1 人 → 现在就打电话调班，不要等到高峰再 | E22: 8 分钟 | F22: dim_sales_forecast、fct_schedule | G22: 店长 | H22: ☐
A23: 07:20 开店前 | B23: 开店食安与设备检查表 | C23: 今天能不能安全地开门？ | D23: 关键项任意一项 fail = 停止该产品出品并立即整改。这张表没有'先记着' | E23: 10 分钟 | F23: fct_food_safety_check、fct_temperature_log | G23: 值班经理 | H23: ☐
A24: 07:40 | B24: 库存盘点与订货建议 | C24: 今天会不会断货？会不会又订多了明天扔掉？ | D24: 关键品缺口 → 调整备货计划 | E24: 8 分钟 | F24: fct_inventory_count、dim_sales_forecast | G24: 店长 | H24: ☐
A25: 每小时 + 高峰前 | B25: 实时销售 vs 预测（日内滚动） | C25: 今天走在预算线上吗？差在哪个渠道？ | D25: 落后 > 5% 且原因在客单价 → 立刻做附加销售动员 | E25: 2 分钟 | F25: fct_pos_transaction、dim_sales_forecast | G25: 值班经理 | H25: ☐
A26: 高峰进行中（11:30 / 18:00） | B26: 服务速度日内看板 | C26: 现在慢在哪一段？点单、厨房、还是交付？ | D26: 窗口时长高 → 后厨备餐没跟上，加人到理货 | E26: 3 分钟 | F26: fct_dt_timer、fct_kds_order | G26: 值班经理 | H26: ☐
A27: 高峰后（14:00 / 20:30） | B27: 人力投放与 SPLH 追踪 | C27: 这一波高峰，人是花值了还是花冤了？ | D27: SPLH 低 + 速度也差 = 排班结构错（不是人不够，是人站错岗）→ 调岗 | E27: 5 分钟 | F27: fct_timecard、fct_schedule | G27: 店长 | H27: ☐
A28: 14:00 / 21:00 交接班 | B28: 废弃与保温批次报表 | C28: 今天扔了多少？为什么扔？ | D28: 成品废弃高 = 备货节奏问题（改批量大小） | E28: 5 分钟 | F28: fct_waste_log、fct_holding_batch | G28: 值班经理 | H28: ☐
A29: 15:00 | B29: 外送平台运营报表 | C29: 外送这四分之一的生意，是在赚钱还是在赔口碑？ | D29: 出餐时长超标 → 高峰给外送单独留一个打包位 | E29: 5 分钟 | F29: fct_delivery_order、fct_order_issue | G29: 店长 | H29: ☐
A30: 16:00 | B30: 顾客反馈与差错清单 | C30: 顾客今天在抱怨什么？是不是同一件事在重复发生？ | D30: 同一个 comment_tag 一周出现 3 次以上 → 它不是个案，是流程 | E30: 5 分钟 | F30: fct_guest_survey、fct_order_issue | G30: 值班经理 | H30: ☐
A31: 23:30 闭店 | B31: 闭店日结：销售 / 成本 / 现金 | C31: 今天的账对不对？成本控住了吗？ | D31: 现金短溢超阈值 → 当班复核录像与交接记录，当天闭环，不隔夜。 | E31: 12 分钟 | F31: fct_pos_transaction、fct_payment | G31: 店长 | H31: ☐
A32: 闭店前 | B32: 次日准备与交接单 | C32: 明天早班一进门，需要知道哪三件事？ | D32: 交接单只写三件事：坏了什么、缺了谁、明天几点最忙。写多了没人看。 | E32: 5 分钟 | F32: fct_equipment_ticket、fct_schedule | G32: 值班经理 | H32: ☐
A33: 合计 | E33: =TEXT(SUMPRODUCT(--SUBSTITUTE(E21:E32," 分钟","")),"0")&" 分钟/天" -> 73 分钟/天
A35: 门店：示例店 · 南京西路店（CN-SH-0731，FreeStanding_DT） · 数据区间：2026-08-05 至 2026-08-18 · 生成命令：python -m mcdops.cli excel
